Workbook

Sheet Budgeted_01jun
A1: Created on | D1: Fiscal Year | E1: Value TranCurr | K1: Object number | L1: Project Definition | R1: Val/COArea Crcy | U1: WBS Element | AA1: Report currency | AB1: Val.in rep.cur. | AC1: Total budget in report currency
A2: 46008 | E2: 7021000 | K2: WBS H-51I4 | L2: H-51I4 | R2: 7021000 | U2: H-51I4 | AA2: INR | AB2: 7021000 | AC2: 7021000
A3: 46021 | E3: -881000 | K3: WBS H-51I4 | L3: H-51I4 | R3: -881000 | U3: H-51I4 | AA3: INR | AB3: -881000 | AC3: -881000
A4: 46022 | E4: 437000 | K4: WBS H-51I4 | L4: H-51I4 | R4: 437000 | U4: H-51I4 | AA4: INR | AB4: 437000 | AC4: 437000
A5: 46022 | E5: 200000 | K5: WBS H-51I4 | L5: H-51I4 | R5: 200000 | U5: H-51I4 | AA5: INR | AB5: 200000 | AC5: 200000
A6: 46023 | E6: 4025000 | K6: WBS H-51I4 | L6: H-51I4 | R6: 4025000 | U6: H-51I4 | AA6: INR | AB6: 4025000 | AC6: 4025000
A7: 46023 | E7: 12625000 | K7: WBS H-51I4 | L7: H-51I4 | R7: 12625000 | U7: H-51I4 | AA7: INR | AB7: 12625000 | AC7: 12625000
A8: 46024 | E8: 14500 | K8: WBS H-51I4 | L8: H-51I4 | R8: 14500 | U8: H-51I4 | AA8: INR | AB8: 14500 | AC8: 14500
A9: 46029 | E9: 3915000 | K9: WBS H-51I4 | L9: H-51I4 | R9: 3915000 | U9: H-51I4 | AA9: INR | AB9: 3915000 | AC9: 3915000
A10: 46031 | E10: 2124000 | K10: WBS H-51I4 | L10: H-51I4 | R10: 2124000 | U10: H-51I4 | AA10: INR | AB10: 2124000 | AC10: 2124000
A11: 46045 | E11: 100000 | K11: WBS H-51I4 | L11: H-51I4 | R11: 100000 | U11: H-51I4 | AA11: INR | AB11: 100000 | AC11: 100000
A12: 46056 | E12: 800000 | K12: WBS H-51I4 | L12: H-51I4 | R12: 800000 | U12: H-51I4 | AA12: INR | AB12: 800000 | AC12: 800000
A13: 46058 | E13: 408000 | K13: WBS H-51I4 | L13: H-51I4 | R13: 408000 | U13: H-51I4 | AA13: INR | AB13: 408000 | AC13: 408000
... A27: 46122 | E27: 311030 | K27: WBS H-51I4 | L27: H-51I4 | R27: 311030 | U27: H-51I4 | AA27: INR | AB27: 311030 | AC27: 311030
E28: 3.1783771e+09
A29: 46008 | E29: 7021000 | K29: WBS H-51I4-07 | L29: H-51I4 | R29: 7021000 | U29: H-51I4-07 | AA29: INR | AB29: 7021000 | AC29: 7021000
A30: 46021 | E30: -881000 | K30: WBS H-51I4-07 | L30: H-51I4 | R30: -881000 | U30: H-51I4-07 | AA30: INR | AB30: -881000 | AC30: -881000
A31: 46022 | E31: 437000 | K31: WBS H-51I4-07 | L31: H-51I4 | R31: 437000 | U31: H-51I4-07 | AA31: INR | AB31: 437000 | AC31: 437000
A32: 46022 | E32: 200000 | K32: WBS H-51I4-07 | L32: H-51I4 | R32: 200000 | U32: H-51I4-07 | AA32: INR | AB32: 200000 | AC32: 200000
A33: 46023 | E33: 4025000 | K33: WBS H-51I4-07 | L33: H-51I4 | R33: 4025000 | U33: H-51I4-07 | AA33: INR | AB33: 4025000 | AC33: 4025000
A34: 46023 | E34: 12625000 | K34: WBS H-51I4-07 | L34: H-51I4 | R34: 12625000 | U34: H-51I4-07 | AA34: INR | AB34: 12625000 | AC34: 12625000
A35: 46024 | E35: 14500 | K35: WBS H-51I4-07 | L35: H-51I4 | R35: 14500 | U35: H-51I4-07 | AA35: INR | AB35: 14500 | AC35: 14500
A36: 46029 | E36: 3915000 | K36: WBS H-51I4-07 | L36: H-51I4 | R36: 3915000 | U36: H-51I4-07 | AA36: INR | AB36: 3915000 | AC36: 3915000
E37: 27356500
A38: 46023 | E38: 4025000 | K38: WBS H-51I4-07-01 | L38: H-51I4 | R38: 4025000 | U38: H-51I4-07-01 | AA38: INR | AB38: 4025000 | AC38: 4025000
A39: 46023 | E39: 12625000 | K39: WBS H-51I4-07-01 | L39: H-51I4 | R39: 12625000 | U39: H-51I4-07-01 | AA39: INR | AB39: 12625000 | AC39: 12625000
A40: 46029 | E40: 3915000 | K40: WBS H-51I4-07-01 | L40: H-51I4 | R40: 3915000 | U40: H-51I4-07-01 | AA40: INR | AB40: 3915000 | AC40: 3915000
E41: 20565000
A42: 46008 | E42: 7021000 | K42: WBS H-51I4-07-02 | L42: H-51I4 | R42: 7021000 | U42: H-51I4-07-02 | AA42: INR | AB42: 7021000 | AC42: 7021000
A43: 46021 | E43: -1071000 | K43: WBS H-51I4-07-02 | L43: H-51I4 | R43: -1071000 | U43: H-51I4-07-02 | AA43: INR | AB43: -1071000 | AC43: -1071000
E44: 5950000
A45: 46021 | E45: 190000 | K45: WBS H-51I4-07-04 | L45: H-51I4 | R45: 190000 | U45: H-51I4-07-04 | AA45: INR | AB45: 190000 | AC45: 190000
A46: 46022 | E46: 437000 | K46: WBS H-51I4-07-04 | L46: H-51I4 | R46: 437000 | U46: H-51I4-07-04 | AA46: INR | AB46: 437000 | AC46: 437000
A47: 46022 | E47: 200000 | K47: WBS H-51I4-07-04 | L47: H-51I4 | R47: 200000 | U47: H-51I4-07-04 | AA47: INR | AB47: 200000 | AC47: 200000
A48: 46024 | E48: 14500 | K48: WBS H-51I4-07-04 | L48: H-51I4 | R48: 14500 | U48: H-51I4-07-04 | AA48: INR | AB48: 14500 | AC48: 14500
E49: 841500
A50: 46045 | E50: 100000 | K50: WBS H-51I4-09 | L50: H-51I4 | R50: 100000 | U50: H-51I4-09 | AA50: INR | AB50: 100000 | AC50: 100000
E51: 100000
A52: 46045 | E52: 100000 | K52: WBS H-51I4-09-01 | L52: H-51I4 | R52: 100000 | U52: H-51I4-09-01 | AA52: INR | AB52: 100000 | AC52: 100000
E53: 100000
A54: 46031 | E54: 2124000 | K54: WBS H-51I4-10 | L54: H-51I4 | R54: 2124000 | U54: H-51I4-10 | AA54: INR | AB54: 2124000 | AC54: 2124000
A55: 46056 | E55: 800000 | K55: WBS H-51I4-10 | L55: H-51I4 | R55: 800000 | U55: H-51I4-10 | AA55: INR | AB55: 800000 | AC55: 800000
A56: 46058 | E56: 408000 | K56: WBS H-51I4-10 | L56: H-51I4 | R56: 408000 | U56: H-51I4-10 | AA56: INR | AB56: 408000 | AC56: 408000
A57: 46058 | E57: 490560 | K57: WBS H-51I4-10 | L57: H-51I4 | R57: 490560 | U57: H-51I4-10 | AA57: INR | AB57: 490560 | AC57: 490560
A58: 46058 | E58: 964000 | K58: WBS H-51I4-10 | L58: H-51I4 | R58: 964000 | U58: H-51I4-10 | AA58: INR | AB58: 964000 | AC58: 964000
A59: 46060 | E59: 613452 | K59: WBS H-51I4-10 | L59: H-51I4 | R59: 613452 | U59: H-51I4-10 | AA59: INR | AB59: 613452 | AC59: 613452
A60: 46064 | E60: 750000 | K60: WBS H-51I4-10 | L60: H-51I4 | R60: 750000 | U60: H-51I4-10 | AA60: INR | AB60: 750000 | AC60: 750000
A61: 46064 | E61: -750000 | K61: WBS H-51I4-10 | L61: H-51I4 | R61: -750000 | U61: H-51I4-10 | AA61: INR | AB61: -750000 | AC61: -750000
A62: 46066 | E62: 262000 | K62: WBS H-51I4-10 | L62: H-51I4 | R62: 262000 | U62: H-51I4-10 | AA62: INR | AB62: 262000 | AC62: 262000
A63: 46069 | E63: 88300.8 | K63: WBS H-51I4-10 | L63: H-51I4 | R63: 88300.8 | U63: H-51I4-10 | AA63: INR | AB63: 88300.8 | AC63: 88300.8
A64: 46070 | E64: 134000 | K64: WBS H-51I4-10 | L64: H-51I4 | R64: 134000 | U64: H-51I4-10 | AA64: INR | AB64: 134000 | AC64: 134000
A65: 46078 | E65: 1305289.2 | K65: WBS H-51I4-10 | L65: H-51I4 | R65: 1305289.2 | U65: H-51I4-10 | AA65: INR | AB65: 1305289.2 | AC65: 1305289.2
... A68: 46122 | E68: 311030 | K68: WBS H-51I4-10 | L68: H-51I4 | R68: 311030 | U68: H-51I4-10 | AA68: INR | AB68: 311030 | AC68: 311030
E69: 8706616
A70: 46070 | E70: 134000 | K70: WBS H-51I4-10-01 | L70: H-51I4 | R70: 134000 | U70: H-51I4-10-01 | AA70: INR | AB70: 134000 | AC70: 134000
E71: 134000
A72: 46058 | E72: 408000 | K72: WBS H-51I4-10-02 | L72: H-51I4 | R72: 408000 | U72: H-51I4-10-02 | AA72: INR | AB72: 408000 | AC72: 408000
A73: 46060 | E73: 613452 | K73: WBS H-51I4-10-02 | L73: H-51I4 | R73: 613452 | U73: H-51I4-10-02 | AA73: INR | AB73: 613452 | AC73: 613452
E74: 1021452
A75: 46056 | E75: 800000 | K75: WBS H-51I4-10-03 | L75: H-51I4 | R75: 800000 | U75: H-51I4-10-03 | AA75: INR | AB75: 800000 | AC75: 800000
A76: 46064 | E76: -800000 | K76: WBS H-51I4-10-03 | L76: H-51I4 | R76: -800000 | U76: H-51I4-10-03 | AA76: INR | AB76: -800000 | AC76: -800000
A77: 46098 | E77: 1045984 | K77: WBS H-51I4-10-03 | L77: H-51I4 | R77: 1045984 | U77: H-51I4-10-03 | AA77: INR | AB77: 1045984 | AC77: 1045984
A78: 46116 | E78: 160000 | K78: WBS H-51I4-10-03 | L78: H-51I4 | R78: 160000 | U78: H-51I4-10-03 | AA78: INR | AB78: 160000 | AC78: 160000
E79: 1205984
A80: 46064 | E80: 750000 | K80: WBS H-51I4-10-08 | L80: H-51I4 | R80: 750000 | U80: H-51I4-10-08 | AA80: INR | AB80: 750000 | AC80: 750000
A81: 46064 | E81: -750000 | K81: WBS H-51I4-10-08 | L81: H-51I4 | R81: -750000 | U81: H-51I4-10-08 | AA81: INR | AB81: -750000 | AC81: -750000
E82: 0
A83: 46122 | E83: 311030 | K83: WBS H-51I4-10-09 | L83: H-51I4 | R83: 311030 | U83: H-51I4-10-09 | AA83: INR | AB83: 311030 | AC83: 311030
E84: 311030
A85: 46058 | E85: 490560 | K85: WBS H-51I4-10-10 | L85: H-51I4 | R85: 490560 | U85: H-51I4-10-10 | AA85: INR | AB85: 490560 | AC85: 490560
A86: 46058 | E86: 964000 | K86: WBS H-51I4-10-10 | L86: H-51I4 | R86: 964000 | U86: H-51I4-10-10 | AA86: INR | AB86: 964000 | AC86: 964000
A87: 46069 | E87: 88300.8 | K87: WBS H-51I4-10-10 | L87: H-51I4 | R87: 88300.8 | U87: H-51I4-10-10 | AA87: INR | AB87: 88300.8 | AC87: 88300.8
A88: 46078 | E88: 1305289.2 | K88: WBS H-51I4-10-10 | L88: H-51I4 | R88: 1305289.2 | U88: H-51I4-10-10 | AA88: INR | AB88: 1305289.2 | AC88: 1305289.2
E89: 2848150
A90: 46066 | E90: 1062000 | K90: WBS H-51I4-10-14 | L90: H-51I4 | R90: 1062000 | U90: H-51I4-10-14 | AA90: INR | AB90: 1062000 | AC90: 1062000
E91: 1062000
A92: 46031 | E92: 2124000 | K92: WBS H-51I4-10-18 | L92: H-51I4 | R92: 2124000 | U92: H-51I4-10-18 | AA92: INR | AB92: 2124000 | AC92: 2124000
E93: 2124000
A94: 46031 | E94: 2124000 | K94: WBS H-51I4-10-18-03 | L94: H-51I4 | R94: 2124000 | U94: H-51I4-10-18-03 | AA94: INR | AB94: 2124000 | AC94: 2124000
E95: 2124000
A96: 46066 | E96: 3135593220 | K96: WBS H-51I4-12 | L96: H-51I4 | R96: 3135593220 | U96: H-51I4-12 | AA96: INR | AB96: 3135593220 | AC96: 3135593220
E97: 3135593220
A98: 46115 | E98: 6620737.9 | K98: WBS H-51I4-15 | L98: H-51I4 | R98: 6620737.9 | U98: H-51I4-15 | AA98: INR | AB98: 6620737.9 | AC98: 6620737.9
E99: 6620737.9
A100: 46018 | E100: 14950000 | K100: WBS H-51N2 | L100: H-51N2 | R100: 14950000 | U100: H-51N2 | AA100: INR | AB100: 14950000 | AC100: 14950000
A101: 46021 | E101: 190000 | K101: WBS H-51N2 | L101: H-51N2 | R101: 190000 | U101: H-51N2 | AA101: INR | AB101: 190000 | AC101: 190000
A102: 46022 | E102: 209000 | K102: WBS H-51N2 | L102: H-51N2 | R102: 209000 | U102: H-51N2 | AA102: INR | AB102: 209000 | AC102: 209000
A103: 46022 | E103: 200000 | K103: WBS H-51N2 | L103: H-51N2 | R103: 200000 | U103: H-51N2 | AA103: INR | AB103: 200000 | AC103: 200000
A104: 46024 | E104: 4025000 | K104: WBS H-51N2 | L104: H-51N2 | R104: 4025000 | U104: H-51N2 | AA104: INR | AB104: 4025000 | AC104: 4025000
A105: 46024 | E105: 14500 | K105: WBS H-51N2 | L105: H-51N2 | R105: 14500 | U105: H-51N2 | AA105: INR | AB105: 14500 | AC105: 14500
A106: 46028 | E106: 1062000 | K106: WBS H-51N2 | L106: H-51N2 | R106: 1062000 | U106: H-51N2 | AA106: INR | AB106: 1062000 | AC106: 1062000
A107: 46029 | E107: 7940000 | K107: WBS H-51N2 | L107: H-51N2 | R107: 7940000 | U107: H-51N2 | AA107: INR | AB107: 7940000 | AC107: 7940000
A108: 46030 | E108: 4684999 | K108: WBS H-51N2 | L108: H-51N2 | R108: 4684999 | U108: H-51N2 | AA108: INR | AB108: 4684999 | AC108: 4684999
A109: 46031 | E109: 2124000 | K109: WBS H-51N2 | L109: H-51N2 | R109: 2124000 | U109: H-51N2 | AA109: INR | AB109: 2124000 | AC109: 2124000
A110: 46045 | E110: 100000 | K110: WBS H-51N2 | L110: H-51N2 | R110: 100000 | U110: H-51N2 | AA110: INR | AB110: 100000 | AC110: 100000
A111: 46057 | E111: 191160 | K111: WBS H-51N2 | L111: H-51N2 | R111: 191160 | U111: H-51N2 | AA111: INR | AB111: 191160 | AC111: 191160
... A135: 46157 | E135: 1600000 | K135: WBS H-51N2 | L135: H-51N2 | R135: 1600000 | U135: H-51N2 | AA135: INR | AB135: 1600000 | AC135: 1600000
E136: 2702397124
A137: 46018 | E137: 14550000 | K137: WBS H-51N2-07 | L137: H-51N2 | R137: 14550000 | U137: H-51N2-07 | AA137: INR | AB137: 14550000 | AC137: 14550000
A138: 46021 | E138: 190000 | K138: WBS H-51N2-07 | L138: H-51N2 | R138: 190000 | U138: H-51N2-07 | AA138: INR | AB138: 190000 | AC138: 190000
...

Sheet Actual_30 jun
A1: Company Code | B1: Document Number | C1: Document Date | D1: Ref Document Number | E1: Posting Date | F1: Created on | G1: Period | H1: Fiscal Year | I1: WBS Element | J1: Project Definition | K1: Val/COArea Crcy | M1: Cost element descr. | N1: Var.val.in rep.cur. | O1: Item | P1: Purchase order text | Q1: CO object name | R1: Cost Element | S1: Total quantity | T1: Posted unit of meas. | U1: Value Type | V1: Document type | W1: CO area currency | X1: Purchasing Document | Y1: Material | Z1: Material Description | AA1: Name | AB1: Document Header Text | AC1: Offsetting acct no. | AD1: Name of offsetting account | AE1: Plant
I2: H-51I4-09-01 | J2: H-51I4 | K2: =L2*5100 -> 5610 | L2: 1.1 | N2: 5100 | W2: INR | AE2: 51I4
I3: H-51N3-09-01 | J3: H-51N3 | K3: =L3*5100 -> 6120 | L3: 1.2 | N3: 5100 | W3: INR | AE3: 51N2
I4: H-51N3-09-01 | J4: H-51N3 | K4: =L4*5100 -> 6630 | L4: 1.3 | N4: -5100 | W4: INR | AE4: 51N2
I5: H-51N3-07-04 | J5: H-51N3 | K5: =L5*5100 -> 7140 | L5: 1.4 | N5: 14500 | W5: INR | AE5: 51N2
I6: H-6497-07-04 | J6: H-6497 | K6: =L6*5100 -> 7650 | L6: 1.5 | N6: 14500 | W6: INR | AE6: 6497
I7: H-6074-07-04 | J7: H-6074 | K7: =L7*5100 -> 8160 | L7: 1.6 | N7: 14500 | W7: INR | AE7: 6074
I8: H-6764-07-04 | J8: H-6764 | K8: =L8*5100 -> 8670 | L8: 1.7 | N8: 14500 | W8: INR | AE8: 6764
I9: H-51N2-07-04 | J9: H-51N2 | K9: =L9*5100 -> 9180 | L9: 1.8 | N9: 14500 | W9: INR | AE9: 51N2
I10: H-63A1-08-01-02 | J10: H-63A1 | K10: =L10*5100 -> 9690 | L10: 1.9 | N10: 520000 | W10: INR | AE10: 6211
I11: H-63A1-08-01-02 | J11: H-63A1 | K11: =L11*5100 -> 10200 | L11: 2 | N11: 520000 | W11: INR | AE11: 6211
I12: H-5XA2-06-03 | J12: H-5XA2 | K12: =L12*5100 -> 10710 | L12: 2.1 | N12: 7124446.1 | W12: INR | AE12: 51XA
I13: H-5XA2-06-03 | J13: H-5XA2 | K13: =L13*5100 -> 11220 | L13: 2.2 | N13: 7129203.7 | W13: INR | AE13: 51XA
... I133: H-51X9-06-02 | J133: H-51X9 | K133: =L133*5100 -> 72420 | L133: 14.2 | N133: 2403500 | W133: INR | AE133: 51X9
I134: H-5XA2-11-02 | J134: H-5XA2 | K134: =L134*5100 -> 72930 | L134: 14.3 | N134: 1114867 | W134: INR
I135: H-51X9-11-02 | J135: H-51X9 | K135: =L135*5100 -> 73440 | L135: 14.4 | N135: 699535 | W135: INR
I136: H-5XA2-06-02 | J136: H-5XA2 | K136: =L136*5100 -> 73950 | L136: 14.5 | N136: 6258600 | W136: INR | AE136: 51XA
I137: H-5XA2-06-02 | J137: H-5XA2 | K137: =L137*5100 -> 74460 | L137: 14.6 | N137: 6253850 | W137: INR | AE137: 51XA
I138: H-5XA2-06-02 | J138: H-5XA2 | K138: =L138*5100 -> 74970 | L138: 14.7 | N138: 6252900 | W138: INR | AE138: 51XA
I139: H-5XA2-06-02 | J139: H-5XA2 | K139: =L139*5100 -> 75480 | L139: 14.8 | N139: 6245300 | W139: INR | AE139: 51XA
I140: H-5XA2-06-02 | J140: H-5XA2 | K140: =L140*5100 -> 75990 | L140: 14.9 | N140: 6269525 | W140: INR | AE140: 51XA
I141: H-5XA2-06-02 | J141: H-5XA2 | K141: =L141*5100 -> 76500 | L141: 15 | N141: 2411100 | W141: INR | AE141: 51XA
I142: H-5XA2-06-02 | J142: H-5XA2 | K142: =L142*5100 -> 77010 | L142: 15.1 | N142: 6270000 | W142: INR | AE142: 51XA
I143: H-5XA1-06-04 | J143: H-5XA1 | K143: =L143*5100 -> 77520 | L143: 15.2 | N143: 874380 | W143: INR | AE143: 51XA
I144: H-5XA1-06-04 | J144: H-5XA1 | K144: =L144*5100 -> 78030 | L144: 15.3 | N144: 2486260 | W144: INR | AE144: 51XA
I145: H-5XA1-06-04 | J145: H-5XA1 | K145: =L145*5100 -> 78540 | L145: 15.4 | N145: 334502.46 | W145: INR | AE145: 51XA
I146: H-6497-09-01 | J146: H-6497 | K146: =L146*5100 -> 79050 | L146: 15.5 | N146: 6018 | W146: INR | AE146: 6497
I147: H-51N3-09-01 | J147: H-51N3 | K147: =L147*5100 -> 79560 | L147: 15.6 | N147: 5100 | W147: INR | AE147: 51N2
... I446: H-63A2-08-01-03-02 | J446: H-63A2 | K446: =L446*5100 -> 232050 | L446: 45.5 | N446: 365897.12 | W446: INR | AE446: 6211
I447: H-5XA1-06-02 | J447: H-5XA1 | K447: =L447*5100 -> 232560 | L447: 45.6 | N447: 0.18 | W447: INR
I448: H-63A1-08-01-01 | J448: H-63A1 | K448: =L448*5100 -> 233070 | L448: 45.7 | N448: 3897190 | W448: INR | AE448: 6211
I449: H-63X9-08-01-01 | J449: H-63X9 | K449: =L449*5100 -> 233580 | L449: 45.8 | N449: 2094240 | W449: INR | AE449: 6211
I450: H-5XA1-06-05 | J450: H-5XA1 | K450: =L450*5100 -> 234090 | L450: 45.9 | N450: -0.02 | W450: INR | AE450: 51XA
I451: H-63X9-08-01-02 | J451: H-63X9 | K451: =L451*5100 -> 234600 | L451: 46 | N451: 27615.82 | W451: INR | AE451: 6211
I452: H-63X9-08-01-02 | J452: H-63X9 | K452: =L452*5100 -> 235110 | L452: 46.1 | N452: 11208.78 | W452: INR | AE452: 6211
I453: H-63X9-08-01-03-01 | J453: H-63X9 | K453: =L453*5100 -> 235620 | L453: 46.2 | N453: 54997.8 | W453: INR | AE453: 6211
I454: H-63X9-08-01-03-01 | J454: H-63X9 | K454: =L454*5100 -> 236130 | L454: 46.3 | N454: 223669 | W454: INR | AE454: 6211
I455: H-63X9-08-01-03-01 | J455: H-63X9 | K455: =L455*5100 -> 236640 | L455: 46.4 | N455: 3340803 | W455: INR | AE455: 6211
I456: H-63X9-08-01-03-01 | J456: H-63X9 | K456: =L456*5100 -> 237150 | L456: 46.5 | N456: 162878.63 | W456: INR | AE456: 6211
I457: H-63X9-08-01-03-01 | J457: H-63X9 | K457: =L457*5100 -> 237660 | L457: 46.6 | N457: 57132 | W457: INR | AE457: 6211
I458: H-63X9-08-01-03-01 | J458: H-63X9 | K458: =L458*5100 -> 238170 | L458: 46.7 | N458: 170125.2 | W458: INR | AE458: 6211
I459: H-63X9-08-01-06-01 | J459: H-63X9 | K459: =L459*5100 -> 238680 | L459: 46.8 | N459: 19107 | W459: INR | AE459: 6211
... I606: H-5XWD-06-02 | J606: H-5XWD | K606: =L606*5100 -> 313650 | L606: 61.5 | N606: 5290075 | W606: INR | AE606: 51WD
I607: H-5XWG-06-02 | J607: H-5XWG | K607: =L607*5100 -> 314160 | L607: 61.6 | N607: 6264775 | W607: INR
I608: H-5XWG-06-02 | J608: H-5XWG | K608: =L608*5100 -> 314670 | L608: 61.7 | N608: 6274750 | W608: INR
I609: H-5XWG-06-02 | J609: H-5XWG | K609: =L609*5100 -> 315180 | L609: 61.8 | N609: 6275700 | W609: INR
I610: H-5XWG-06-02 | J610: H-5XWG | K610: =L610*5100 -> 315690 | L610: 61.9 | N610: 6274275 | W610: INR
I611: H-5XWG-06-02 | J611: H-5XWG | K611: =L611*5100 -> 316200 | L611: 62 | N611: 6270775 | W611: INR
I612: H-5XWG-06-02 | J612: H-5XWG | K612: =L612*5100 -> 316710 | L612: 62.1 | N612: 6267625 | W612: INR
I613: H-5XWG-06-02 | J613: H-5XWG | K613: =L613*5100 -> 317220 | L613: 62.2 | N613: 6276700 | W613: INR
I614: H-5XWG-06-02 | J614: H-5XWG | K614: =L614*5100 -> 317730 | L614: 62.3 | N614: 6270475 | W614: INR
I615: H-63WG-08-01-02 | J615: H-63WG | K615: =L615*5100 -> 318240 | L615: 62.4 | N615: 11794183 | W615: INR
I616: H-6074-10-03 | J616: H-6074 | K616: =L616*5100 -> 318750 | L616: 62.5 | N616: 90160 | W616: INR
I617: H-5XA1-06-05 | J617: H-5XA1 | K617: =L617*5100 -> 319260 | L617: 62.6 | N617: 1132723 | W617: INR
I618: H-5XWD-06-02 | J618: H-5XWD | K618: =L618*5100 -> 319770 | L618: 62.7 | N618: 5259200 | W618: INR
... I634: H-5XWG-06-02 | J634: H-5XWG | K634: =L634*5100 -> 327930 | L634: 64.3 | N634: 6276700 | W634: INR
I635: H-63WG-08-01-02 | J635: H-63WG | K635: =L635*5100 -> 328440 | L635: 64.4 | N635: 520000 | W635: INR | AE635: 6211
I636: H-63WG-08-01-02 | J636: H-63WG | K636: =L636*5100 -> 328950 | L636: 64.5 | N636: 520000 | W636: INR | AE636: 6211
I637: H-63WG-08-01-02 | J637: H-63WG | K637: =L637*5100 -> 329460 | L637: 64.6 | N637: 520000 | W637: INR | AE637: 6211
I638: H-63WG-08-01-02 | J638: H-63WG | K638: =L638*5100 -> 329970 | L638: 64.7 | N638: 520000 | W638: INR | AE638: 6211
I639: H-5XA2-04 | J639: H-5XA2 | K639: =L639*5100 -> 330480 | L639: 64.8 | N639: 16544397 | W639: INR | AE639: 51XA
I640: H-5XWG-15 | J640: H-5XWG | K640: =L640*5100 -> 330990 | L640: 64.9 | N640: 7114930 | W640: INR
I641: H-5XWG-15 | J641: H-5XWG | K641: =L641*5100 -> 331500 | L641: 65 | N641: 6862780 | W641: INR
I642: H-5XWG-15 | J642: H-5XWG | K642: =L642*5100 -> 332010 | L642: 65.1 | N642: 7138718 | W642: INR
I643: H-5XWG-06-04 | J643: H-5XWG | K643: =L643*5100 -> 332520 | L643: 65.2 | N643: 99000 | W643: INR | AE643: 51WG
I644: H-5XWG-06-04 | J644: H-5XWG | K644: =L644*5100 -> 333030 | L644: 65.3 | N644: -99000 | W644: INR | AE644: 51WG
I645: H-5XWG-06-04 | J645: H-5XWG | K645: =L645*5100 -> 333540 | L645: 65.4 | N645: 99000 | W645: INR | AE645: 51WG
I646: H-5XWG-06-04 | J646: H-5XWG | K646: =L646*5100 -> 334050 | L646: 65.5 | N646: 639646 | W646: INR | AE646: 51WG
I647: H-5XWG-15 | J647: H-5XWG | K647: =L647*5100 -> 334560 | L647: 65.6 | N647: 7114930 | W647: INR
I648: H-5XWG-15 | J648: H-5XWG | K648: =L648*5100 -> 335070 | L648: 65.7 | N648: 6862780 | W648: INR
I649: H-5XWG-15 | J649: H-5XWG | K649: =L649*5100 -> 335580 | L649: 65.8 | N649: 7138718 | W649: INR
I650: H-5XWG-15 | J650: H-5XWG | K650: =L650*5100 -> 336090 | L650: 65.9 | N650: 7119585 | W650: INR
I651: H-5XWG-15 | J651: H-5XWG | K651: =L651*5100 -> 336600 | L651: 66 | N651: 7164885 | W651: INR
I652: H-5XWG-15 | J652: H-5XWG | K652: =L652*5100 -> 337110 | L652: 66.1 | N652: 7091143 | W652: INR
I653: H-5XWG-15 | J653: H-5XWG | K653: =L653*5100 -> 337620 | L653: 66.2 | N653: 7124446 | W653: INR
I654: H-5XWG-15 | J654: H-5XWG | K654: =L654*5100 -> 338130 | L654: 66.3 | N654: 7122067 | W654: INR
I655: H-5XWG-15 | J655: H-5XWG | K655: =L655*5100 -> 338640 | L655: 66.4 | N655: 7114930 | W655: INR
I656: H-5XWG-15 | J656: H-5XWG | K656: =L656*5100 -> 339150 | L656: 66.5 | N656: 6270475 | W656: INR
I657: H-6764-15 | J657: H-6764 | K657: =L657*5100 -> 339660 | L657: 66.6 | N657: 892500 | W657: INR
I658: H-63X9-15 | J658: H-63X9 | K658: =L658*5100 -> 340170 | L658: 66.7 | N658: 2000000 | W658: INR
... I704: H-51X9-15 | J704: H-51X9 | K704: =L704*5100 -> 363630 | L704: 71.3 | N704: 1034992 | W704: INR
I705: H-63X9-08-01-03-02 | J705: H-63X9 | K705: =L705*5100 -> 364140 | L705: 71.4 | N705: 585203.9 | W705: INR | AE705: 6211
I706: H-63A1-08-01-03-02 | J706: H-63A1 | K706: =L706*5100 -> 364650 | L706: 71.5 | N706: 1042641.9 | W706: INR | AE706: 6211
I707: H-63A2-08-01-03-02 | J707: H-63A2 | K707: =L707*5100 -> 365160 | L707: 71.6 | N707: 927652.56 | W707: INR | AE707: 6211
I708: H-5XA2-04 | J708: H-5XA2 | K708: =L708*5100 -> 365670 | L708: 71.7 | N708: 6136000 | W708: INR | AE708: 51XA
I709: H-5XWD-06-02 | J709: H-5XWD | K709: =L709*5100 -> 366180 | L709: 71.8 | N709: 4759025 | W709: INR | AE709: 51WD
I710: H-5XWD-06-02 | J710: H-5XWD | K710: =L710*5100 -> 366690 | L710: 71.9 | N710: 5219300 | W710: INR | AE710: 51WD
I711: H-5XWG-06-03 | J711: H-5XWG | K711: =L711*5100 -> 367200 | L711: 72 | N711: 7084006.8 | W711: INR | AE711: 51WG
I712: H-5XWG-06-03 | J712: H-5XWG | K712: =L712*5100 -> 367710 | L712: 72.1 | N712: 7133961.2 | W712: INR | AE712: 51WG
I713: H-5XWD-06-03 | J713: H-5XWD | K713: =L713*5100 -> 368220 | L713: 72.2 | N713: 7124446.1 | W713: INR | AE713: 51WD
I714: H-5XWG-06-03 | J714: H-5XWG | K714: =L714*5100 -> 368730 | L714: 72.3 | N714: 7095900.7 | W714: INR | AE714: 51WG
I715: H-5XWD-06-03 | J715: H-5XWD | K715: =L715*5100 -> 369240 | L715: 72.4 | N715: 7143476.3 | W715: INR | AE715: 51WD
I716: H-5XWG-06-02 | J716: H-5XWG | K716: =L716*5100 -> 369750 | L716: 72.5 | N716: 6255750 | W716: INR | AE716: 51WG
... I728: H-5XWD-06-02 | J728: H-5XWD | K728: =L728*5100 -> 375870 | L728: 73.7 | N728: 5644131.9 | W728: INR | AE728: 51WD
I729: H-6764-09-01 | J729: H-6764 | K729: =L729*5100 -> 376380 | L729: 73.8 | N729: 151599.03 | W729: INR
I730: H-6764-10-12 | J730: H-6764 | K730: =L730*5100 -> 376890 | L730: 73.9 | N730: 8800 | W730: INR
I731: H-6764-11-03 | J731: H-6764 | K731: =L731*5100 -> 377400 | L731: 74 | N731: 60264 | W731: INR
I732: H-63WD-15 | J732: H-63WD | K732: =L732*5100 -> 377910 | L732: 74.1 | N732: 89726607 | W732: INR
I733: H-6764-16 | J733: H-6764 | K733: =L733*5100 -> 378420 | L733: 74.2 | N733: 50325.75 | W733: INR
I734: H-6074-09-01 | J734: H-6074 | K734: =L734*5100 -> 378930 | L734: 74.3 | N734: 166830.63 | W734: INR
...

Sheet Commited_30 Jun
A1: Company Code | B1: Reference document category | C1: Document Date | D1: Object | E1: CO object name | F1: Reference item | G1: Name | H1: WBS Element | I1: Val/COArea Crcy | K1: Ref Document Number | L1: Quantity/plan | M1: Plan/COCurrency | N1: Total Quantity | O1: Transaction Currency | P1: Value TranCurr | Q1: Unit of Measure | R1: Cost element descr. | S1: Deletion Indicator | T1: Supplier | U1: User Name | V1: Acct assgnmnt number | W1: Business Transaction | X1: Cost element | Y1: Cost element name | Z1: Debit date | AA1: Dr/Cr indicator | AB1: Exchange Rate | AC1: Fiscal Year | AD1: Ledger | AE1: Material | AF1: Material Description | AG1: Period | AH1: Project Definition | AI1: Deadline item | AJ1: Material Group | AK1: Object Currency | AL1: Object type | AM1: Object type | AN1: Plan Val. RCrcy | AO1: Plan/ObjectCur. | AP1: Plan/TC | AQ1: Reference doc. type | AR1: Report currency | AS1: Val.in rep.cur. | AT1: Value in Obj. Crcy | AU1: Value Type | AV1: Version | AW1: Trading partner
D2: H-63A2-08-01-03-02 | H2: H-63A2-08-01-03-02 | I2: =J2*4129564.5 -> 4542521 | J2: 1.1 | L2: 96 | M2: 8208000 | AN2: 8208000 | AO2: 8208000 | AP2: 8208000 | AR2: INR | AS2: 4129564.5 | AT2: 4129564.5 | AU2: 21 | AV2: 0
D3: H-63A2-08-01-03-02 | H3: H-63A2-08-01-03-02 | I3: =J3*4129564.5 -> 4955477.4 | J3: 1.2 | L3: 12.96 | M3: 1360800 | AN3: 1360800 | AO3: 1360800 | AP3: 1360800 | AR3: INR | AS3: 765345 | AT3: 765345 | AU3: 21 | AV3: 0
D4: H-63A2-08-01-03-02 | H4: H-63A2-08-01-03-02 | I4: =J4*4129564.5 -> 5368433.9 | J4: 1.3 | L4: 9.6 | M4: 1728000 | AN4: 1728000 | AO4: 1728000 | AP4: 1728000 | AR4: INR | AS4: 521820 | AT4: 521820 | AU4: 21 | AV4: 0
D5: H-63A2-08-01-03-02 | H5: H-63A2-08-01-03-02 | I5: =J5*4129564.5 -> 5781390.3 | J5: 1.4 | L5: 10971.36 | M5: 8886801.6 | AN5: 8886801.6 | AO5: 8886801.6 | AP5: 8886801.6 | AR5: INR | AS5: 61041.6 | AT5: 61041.6 | AU5: 21 | AV5: 0
D6: H-63A2-08-01-03-02 | H6: H-63A2-08-01-03-02 | I6: =J6*4129564.5 -> 6194346.8 | J6: 1.5 | L6: 43.2 | M6: 5832000 | AN6: 5832000 | AO6: 5832000 | AP6: 5832000 | AR6: INR | AS6: 3720195 | AT6: 3720195 | AU6: 21 | AV6: 0
D7: H-63X9-08-01-05-02 | H7: H-63X9-08-01-05-02 | I7: =J7*4129564.5 -> 6607303.2 | J7: 1.6 | L7: 8 | M7: 788000 | AN7: 788000 | AO7: 788000 | AP7: 788000 | AR7: INR | AS7: 788000 | AT7: 788000 | AU7: 21 | AV7: 0
D8: H-63X9-08-01-05-02 | H8: H-63X9-08-01-05-02 | I8: =J8*4129564.5 -> 7020259.6 | J8: 1.7 | L8: 90 | M8: 82800 | AN8: 82800 | AO8: 82800 | AP8: 82800 | AR8: INR | AS8: 78604.8 | AT8: 78604.8 | AU8: 21 | AV8: 0
D9: H-63X9-08-01-05-02 | H9: H-63X9-08-01-05-02 | I9: =J9*4129564.5 -> 7433216.1 | J9: 1.8 | L9: 225 | M9: 191250 | AN9: 191250 | AO9: 191250 | AP9: 191250 | AR9: INR | AS9: 169830 | AT9: 169830 | AU9: 21 | AV9: 0
D10: H-63X9-08-01-03-02 | H10: H-63X9-08-01-03-02 | I10: =J10*4129564.5 -> 7846172.5 | J10: 1.9 | L10: 9 | M10: 886500 | AN10: 886500 | AO10: 886500 | AP10: 886500 | AR10: INR | AS10: 886500 | AT10: 886500 | AU10: 21 | AV10: 0
D11: H-63X9-08-01-03-02 | H11: H-63X9-08-01-03-02 | I11: =J11*4129564.5 -> 8259129 | J11: 2 | L11: 60 | M11: 5130000 | AN11: 5130000 | AO11: 5130000 | AP11: 5130000 | AR11: INR | AS11: 2479927.5 | AT11: 2479927.5 | AU11: 21 | AV11: 0
D12: H-63X9-08-01-03-02 | H12: H-63X9-08-01-03-02 | I12: =J12*4129564.5 -> 8672085.5 | J12: 2.1 | L12: 126.9 | M12: 12499650 | AN12: 12499650 | AO12: 12499650 | AP12: 12499650 | AR12: INR | AS12: 716095 | AT12: 716095 | AU12: 21 | AV12: 0
D13: H-63X9-08-01-03-02 | H13: H-63X9-08-01-03-02 | I13: =J13*4129564.5 -> 9085041.9 | J13: 2.2 | L13: 8.1 | M13: 850500 | AN13: 850500 | AO13: 850500 | AP13: 850500 | AR13: INR | AS13: 314790 | AT13: 314790 | AU13: 21 | AV13: 0
... D467: H-63WD-06-06 | H467: H-63WD-06-06 | I467: =J467*4129564.5 -> 1.9656727e+08 | J467: 47.6 | L467: 1 | M467: 2062260 | AN467: 2062260 | AO467: 2062260 | AP467: 2062260 | AR467: INR | AS467: 72542 | AT467: 72542 | AU467: 21 | AV467: 0
I468: =J468*4129564.5 -> 1.9698023e+08 | J468: 47.7 | M468: 1.0716705e+10 | O468: INR | P468: 7.9075076e+09 | AN468: 1.0716705e+10 | AR468: INR
I469: =J469*4129564.5 -> 1.9739318e+08 | J469: 47.8 | O469: USD | P469: 15394668
D470: H-5XA1-03-01 | H470: H-5XA1-03-01 | I470: =J470*4129564.5 -> 1.9780614e+08 | J470: 47.9 | L470: 1 | M470: 125000000 | N470: 0.5 | O470: INR | P470: 62500000 | Q470: SET | R470: Stock of Project Material-Domestic | T470: 123467 | U470: WF-BATCH | V470: 1 | W470: RMBE | X470: 12211000 | Y470: Stk of Prj Mat-Dom | Z470: 46387 | AA470: D | AB470: 1.00000 | AC470: 2026 | AD470: 0 | AE470: 9922310642 | AF470: ENERGY MANAGEMENT SYSTEM | AG470: 9 | AH470: H-5XA1 | AI470: 1 | AJ470: 9922 | AK470: INR | AL470: WBS element | AM470: WBS | AN470: 125000000 | AO470: 125000000 | AP470: 125000000 | AQ470: P | AR470: INR | AS470: 62500000 | AT470: 62500000 | AU470: 22 | AV470: 0
D471: H-5XA2-04 | H471: H-5XA2-04 | I471: =J471*4129564.5 -> 1.982191e+08 | J471: 48 | L471: 48 | M471: 793711056 | N471: 1 | O471: INR | P471: 1718676 | Q471: EA | R471: Stock of Project Material-Domestic | T471: 232077 | U471: 30215701 | V471: 1 | W471: RMBE | X471: 12211000 | Y471: Stk of Prj Mat-Dom | Z471: 46203 | AA471: D | AB471: 1.00000 | AC471: 2026 | AD471: 0 | AE471: 6542020464 | AF471: TRANSFORMER,CONVERTER DUTY,18/20MVA | AG471: 3 | AH471: H-5XA2 | AI471: 1 | AJ471: 6542 | AK471: INR | AL471: WBS element | AM471: WBS | AN471: 793711056 | AO471: 793711056 | AP471: 793711056 | AQ471: P | AR471: INR | AS471: 1718676 | AT471: 1718676 | AU471: 22 | AV471: 0
D472: H-5XA2-04 | H472: H-5XA2-04 | I472: =J472*4129564.5 -> 1.9863205e+08 | J472: 48.1 | L472: 3 | M472: 30000 | N472: 3 | O472: INR | P472: 30000 | Q472: EA | R472: Stock of Project Material-Domestic | T472: 232077 | U472: WF-BATCH | V472: 1 | W472: RMBE | X472: 12211000 | Y472: Stk of Prj Mat-Dom | Z472: 46203 | AA472: D | AB472: 1.00000 | AC472: 2026 | AD472: 0 | AE472: 6542300273 | AF472: BUSHING,ELECTRICAL,ABB SWEDEN,400V,40A | AG472: 3 | AH472: H-5XA2 | AI472: 1 | AJ472: 6542 | AK472: INR | AL472: WBS element | AM472: WBS | AN472: 30000 | AO472: 30000 | AP472: 30000 | AQ472: P | AR472: INR | AS472: 30000 | AT472: 30000 | AU472: 22 | AV472: 0
D473: H-5XA2-04 | H473: H-5XA2-04 | I473: =J473*4129564.5 -> 1.9904501e+08 | J473: 48.2 | L473: 3 | M473: 75000 | N473: 3 | O473: INR | P473: 75000 | Q473: EA | R473: Stock of Project Material-Domestic | T473: 232077 | U473: WF-BATCH | V473: 1 | W473: RMBE | X473: 12211000 | Y473: Stk of Prj Mat-Dom | Z473: 46203 | AA473: D | AB473: 1.00000 | AC473: 2026 | AD473: 0 | AE473: 9922153193 | AF473: LV BUSHINGS WITH METAL PARTS | AG473: 3 | AH473: H-5XA2 | AI473: 1 | AJ473: 6791 | AK473: INR | AL473: WBS element | AM473: WBS | AN473: 75000 | AO473: 75000 | AP473: 75000 | AQ473: P | AR473: INR | AS473: 75000 | AT473: 75000 | AU473: 22 | AV473: 0
D474: H-5XA2-04 | H474: H-5XA2-04 | I474: =J474*4129564.5 -> 1.9945797e+08 | J474: 48.3 | L474: 2 | M474: 36000 | N474: 2 | O474: INR | P474: 36000 | Q474: SET | R474: Stock of Project Material-Domestic | T474: 232077 | U474: WF-BATCH | V474: 1 | W474: RMBE | X474: 12211000 | Y474: Stk of Prj Mat-Dom | Z474: 46203 | AA474: D | AB474: 1.00000 | AC474: 2026 | AD474: 0 | AE474: 5999979843 | AF474: INDICATOR,TEMP,PN:6005AHX,SCIECONT | AG474: 3 | AH474: H-5XA2 | AI474: 1 | AJ474: 6002 | AK474: INR | AL474: WBS element | AM474: WBS | AN474: 36000 | AO474: 36000 | AP474: 36000 | AQ474: P | AR474: INR | AS474: 36000 | AT474: 36000 | AU474: 22 | AV474: 0
D475: H-5XA2-04 | H475: H-5XA2-04 | I475: =J475*4129564.5 -> 1.9987092e+08 | J475: 48.4 | L475: 4 | M475: 72000 | N475: 4 | O475: INR | P475: 72000 | Q475: EA | R475: Stock of Project Material-Domestic | T475: 232077 | U475: WF-BATCH | V475: 1 | W475: RMBE | X475: 12211000 | Y475: Stk of Prj Mat-Dom | Z475: 46203 | AA475: D | AB475: 1.00000 | AC475: 2026 | AD475: 0 | AE475: 5999977643 | AF475: WINDING TEMPERATURE INDICATOR | AG475: 3 | AH475: H-5XA2 | AI475: 1 | AJ475: 6542 | AK475: INR | AL475: WBS element | AM475: WBS | AN475: 72000 | AO475: 72000 | AP475: 72000 | AQ475: P | AR475: INR | AS475: 72000 | AT475: 72000 | AU475: 22 | AV475: 0
D476: H-5XA2-04 | H476: H-5XA2-04 | I476: =J476*4129564.5 -> 2.0028388e+08 | J476: 48.5 | L476: 1 | M476: 85000 | N476: 1 | O476: INR | P476: 85000 | Q476: SET | R476: Stock of Project Material-Domestic | T476: 232077 | U476: WF-BATCH | V476: 1 | W476: RMBE | X476: 12211000 | Y476: Stk of Prj Mat-Dom | Z476: 46203 | AA476: D | AB476: 1.00000 | AC476: 2026 | AD476: 0 | AE476: 9922435153 | AF476: VALVE SET | AG476: 3 | AH476: H-5XA2 | AI476: 1 | AJ476: 7787 | AK476: INR | AL476: WBS element | AM476: WBS | AN476: 85000 | AO476: 85000 | AP476: 85000 | AQ476: P | AR476: INR | AS476: 85000 | AT476: 85000 | AU476: 22 | AV476: 0
D477: H-5XA2-04 | H477: H-5XA2-04 | I477: =J477*4129564.5 -> 2.0069683e+08 | J477: 48.6 | L477: 2 | M477: 5000 | N477: 2 | O477: INR | P477: 5000 | Q477: EA | R477: Stock of Project Material-Domestic | T477: 232077 | U477: WF-BATCH | V477: 1 | W477: RMBE | X477: 12211000 | Y477: Stk of Prj Mat-Dom | Z477: 46203 | AA477: D | AB477: 1.00000 | AC477: 2026 | AD477: 0 | AE477: 5999977633 | AF477: DIAL TYPE THERMOMETER | AG477: 3 | AH477: H-5XA2 | AI477: 1 | AJ477: 6789 | AK477: INR | AL477: WBS element | AM477: WBS | AN477: 5000 | AO477: 5000 | AP477: 5000 | AQ477: P | AR477: INR | AS477: 5000 | AT477: 5000 | AU477: 22 | AV477: 0
D478: H-5XA2-04 | H478: H-5XA2-04 | I478: =J478*4129564.5 -> 2.0110979e+08 | J478: 48.7 | L478: 2 | M478: 17000 | N478: 2 | O478: INR | P478: 17000 | Q478: NO | R478: Stock of Project Material-Domestic | T478: 232077 | U478: WF-BATCH | V478: 1 | W478: RMBE | X478: 12211000 | Y478: Stk of Prj Mat-Dom | Z478: 46203 | AA478: D | AB478: 1.00000 | AC478: 2026 | AD478: 0 | AE478: 9922130013 | AF478: GAUGE,MAGNETIC OIL LEVEL | AG478: 3 | AH478: H-5XA2 | AI478: 1 | AJ478: 6789 | AK478: INR | AL478: WBS element | AM478: WBS | AN478: 17000 | AO478: 17000 | AP478: 17000 | AQ478: P | AR478: INR | AS478: 17000 | AT478: 17000 | AU478: 22 | AV478: 0
D479: H-5XA2-04 | H479: H-5XA2-04 | I479: =J479*4129564.5 -> 2.0152275e+08 | J479: 48.8 | L479: 10 | M479: 60000 | N479: 10 | O479: INR | P479: 60000 | Q479: EA | R479: Stock of Project Material-Domestic | T479: 232077 | U479: WF-BATCH | V479: 1 | W479: RMBE | X479: 12211000 | Y479: Stk of Prj Mat-Dom | Z479: 46203 | AA479: D | AB479: 1.00000 | AC479: 2026 | AD479: 0 | AE479: 9922035603 | AF479: SILICA GEL BREATHER | AG479: 3 | AH479: H-5XA2 | AI479: 1 | AJ479: 7787 | AK479: INR | AL479: WBS element | AM479: WBS | AN479: 60000 | AO479: 60000 | AP479: 60000 | AQ479: P | AR479: INR | AS479: 60000 | AT479: 60000 | AU479: 22 | AV479: 0
D480: H-5XA2-04 | H480: H-5XA2-04 | I480: =J480*4129564.5 -> 2.019357e+08 | J480: 48.9 | L480: 2 | M480: 130000 | N480: 2 | O480: INR | P480: 130000 | Q480: EA | R480: Stock of Project Material-Domestic | T480: 232077 | U480: WF-BATCH | V480: 1 | W480: RMBE | X480: 12211000 | Y480: Stk of Prj Mat-Dom | Z480: 46203 | AA480: D | AB480: 1.00000 | AC480: 2026 | AD480: 0 | AE480: 1104080066 | AF480: GASKET SET,PN:02937594,JLG | AG480: 3 | AH480: H-5XA2 | AI480: 1 | AJ480: 1104 | AK480: INR | AL480: WBS element | AM480: WBS | AN480: 130000 | AO480: 130000 | AP480: 130000 | AQ480: P | AR480: INR | AS480: 130000 | AT480: 130000 | AU480: 22 | AV480: 0
D481: H-5XA2-04 | H481: H-5XA2-04 | I481: =J481*4129564.5 -> 2.0234866e+08 | J481: 49 | L481: 2 | M481: 17000 | N481: 2 | O481: INR | P481: 17000 | Q481: EA | R481: Stock of Project Material-Domestic | T481: 232077 | U481: WF-BATCH | V481: 1 | W481: RMBE | X481: 12211000 | Y481: Stk of Prj Mat-Dom | Z481: 46203 | AA481: D | AB481: 1.00000 | AC481: 2026 | AD481: 0 | AE481: 9922035623 | AF481: BUCHHOLZ RELAY | AG481: 3 | AH481: H-5XA2 | AI481: 1 | AJ481: 6781 | AK481: INR | AL481: WBS element | AM481: WBS | AN481: 17000 | AO481: 17000 | AP481: 17000 | AQ481: P | AR481: INR | AS481: 17000 | AT481: 17000 | AU481: 22 | AV481: 0
... D819: H-63WF-08-01-06-01 | H819: H-63WF-08-01-06-01 | I819: =J819*4129564.5 -> 3.4192794e+08 | J819: 82.8 | L819: 4 | M819: 222680 | N819: 4 | O819: INR | P819: 222680 | Q819: EA | R819: Stock of Project Material-Domestic | T819: 254711 | U819: RCSL10061 | V819: 1 | W819: RMBE | X819: 12211000 | Y819: Stk of Prj Mat-Dom | Z819: 46188 | AA819: D | AB819: 1.00000 | AC819: 2026 | AD819: 0 | AE819: 9922540001 | AF819: PERFORATED PRECAST SQUARE COVER | AG819: 3 | AH819: H-63WF | AI819: 1 | AJ819: 8080 | AK819: INR | AL819: WBS element | AM819: WBS | AN819: 222680 | AO819: 222680 | AP819: 222680 | AQ819: P | AR819: INR | AS819: 222680 | AT819: 222680 | AU819: 22 | AV819: 0
D820: H-63WD-08-01-01 | H820: H-63WD-08-01-01 | I820: =J820*4129564.5 -> 3.423409e+08 | J820: 82.9 | L820: 448 | M820: 31744384 | N820: 231 | O820: INR | P820: 16368198 | Q820: EA | R820: Stock of Project Material-Domestic | T820: 265604 | U820: 30213786 | V820: 1 | W820: RMBE | X820: 12211000 | Y820: Stk of Prj Mat-Dom | Z820: 46218 | AA820: D | AB820: 1.00000 | AC820: 2026 | AD820: 0 | AE820: 9911370443 | AF820: SUPPLY OF BEAM | AG820: 4 | AH820: H-63WD | AI820: 1 | AJ820: 7890 | AK820: INR | AL820: WBS element | AM820: WBS | AN820: 31744384 | AO820: 31744384 | AP820: 31744384 | AQ820: P | AR820: INR | AS820: 16368198 | AT820: 16368198 | AU820: 22 | AV820: 0 | AW820: 58C0
D821: H-63X9-08-01-01 | H821: H-63X9-08-01-01 | I821: =J821*4129564.5 -> 3.4275385e+08 | J821: 83 | L821: 240 | M821: 16753920 | N821: 2 | O821: INR | P821: 139616.2 | Q821: EA | R821: Stock of Project Material-Domestic | T821: 265604 | U821: RCSL10061 | V821: 1 | W821: RMBE | X821: 12211000 | Y821: Stk of Prj Mat-Dom | Z821: 46218 | AA821: D | AB821: 1.00000 | AC821: 2026 | AD821: 0 | AE821: 9911370443 | AF821: SUPPLY OF BEAM | AG821: 4 | AH821: H-63X9 | AI821: 1 | AJ821: 7890 | AK821: INR | AL821: WBS element | AM821: WBS | AN821: 16753920 | AO821: 16753920 | AP821: 16753920 | AQ821: P | AR821: INR | AS821: 139616.2 | AT821: 139616.2 | AU821: 22 | AV821: 0 | AW821: 58C0
D822: H-63WG-08-01-02 | H822: H-63WG-08-01-02 | I822: =J822*4129564.5 -> 3.4316681e+08 | J822: 83.1 | L822: 27 | M822: 7020000 | N822: 11 | O822: INR | P822: 2860000 | Q822: EA | R822: Stock of Project Material-Domestic | T822: 254496 | U822: WF-BATCH | V822: 1 | W822: RMBE | X822: 12211000 | Y822: Stk of Prj Mat-Dom | Z822: 46188 | AA822: D | AB822: 1.00000 | AC822: 2026 | AD822: 0 | AE822: 9922139723 | AF822: OIL STORAGE TANK | AG822: 3 | AH822: H-63WG | AI822: 1 | AJ822: 6190 | AK822: INR | AL822: WBS element | AM822: WBS | AN822: 7020000 | AO822: 7020000 | AP822: 7020000 | AQ822: P | AR822: INR | AS822: 2860000 | AT822: 2860000 | AU822: 22 | AV822: 0
D823: H-63WF-08-01-02 | H823: H-63WF-08-01-02 | I823: =J823*4129564.5 -> 3.4357977e+08 | J823: 83.2 | L823: 11 | M823: 3080000 | N823: 11 | O823: INR | P823: 3080000 | Q823: EA | R823: Stock of Project Material-Domestic | T823: 254496 | U823: WF-BATCH | V823: 1 | W823: RMBE | X823: 12211000 | Y823: Stk of Prj Mat-Dom | Z823: 46188 | AA823: D | AB823: 1.00000 | AC823: 2026 | AD823: 0 | AE823: 9922139723 | AF823: OIL STORAGE TANK | AG823: 3 | AH823: H-63WF | AI823: 1 | AJ823: 6190 | AK823: INR | AL823: WBS element | AM823: WBS | AN823: 3080000 | AO823: 3080000 | AP823: 3080000 | AQ823: P | AR823: INR | AS823: 3080000 | AT823: 3080000 | AU823: 22 | AV823: 0
D824: H-63WD-08-01-02 | H824: H-63WD-08-01-02 | I824: =J824*4129564.5 -> 3.4399272e+08 | J824: 83.3 | L824: 28 | M824: 7280000 | N824: 28 | O824: INR | P824: 7280000 | Q824: EA | R824: Stock of Project Material-Domestic | T824: 254496 | U824: WF-BATCH | V824: 1 | W824: RMBE | X824: 12211000 | Y824: Stk of Prj Mat-Dom | Z824: 46188 | AA824: D | AB824: 1.00000 | AC824: 2026 | AD824: 0 | AE824: 9922139723 | AF824: OIL STORAGE TANK | AG824: 3 | AH824: H-63WD | AI824: 1 | AJ824: 6190 | AK824: INR | AL824: WBS element | AM824: WBS | AN824: 7280000 | AO824: 7280000 | AP824: 7280000 | AQ824: P | AR824: INR | AS824: 7280000 | AT824: 7280000 | AU824: 22 | AV824: 0
D825: H-63A1-08-01-02 | H825: H-63A1-08-01-02 | I825: =J825*4129564.5 -> 3.4440568e+08 | J825: 83.4 | L825: 18 | M825: 4680000 | N825: 6 | O825: INR | P825: 1560000 | Q825: EA | R825: Stock of Project Material-Domestic | T825: 254496 | U825: AUTO10039 | V825: 1 | W825: RMBE | X825: 12211000 | Y825: Stk of Prj Mat-Dom | Z825: 46188 | AA825: D | AB825: 1.00000 | AC825: 2026 | AD825: 0 | AE825: 9922139723 | AF825: OIL STORAGE TANK | AG825: 3 | AH825: H-63A1 | AI825: 1 | AJ825: 6190 | AK825: INR | AL825: WBS element | AM825: WBS | AN825: 4680000 | AO825: 4680000 | AP825: 4680000 | AQ825: P | AR825: INR | AS825: 1560000 | AT825: 1560000 | AU825: 22 | AV825: 0
D826: H-63A2-08-01-02 | H826: H-63A2-08-01-02 | I826: =J826*4129564.5 -> 3.4481864e+08 | J826: 83.5 | L826: 23 | M826: 5980000 | N826: 14 | O826: INR | P826: 3640000 | Q826: EA | R826: Stock of Project Material-Domestic | T826: 254496 | U826: AUTO10039 | V826: 1 | W826: RMBE | X826: 12211000 | Y826: Stk of Prj Mat-Dom | Z826: 46188 | AA826: D | AB826: 1.00000 | AC826: 2026 | AD826: 0 | AE826: 9922139723 | AF826: OIL STORAGE TANK | AG826: 3 | AH826: H-63A2 | AI826: 1 | AJ826: 6190 | AK826: INR | AL826: WBS element | AM826: WBS | AN826: 5980000 | AO826: 5980000 | AP826: 5980000 | AQ826: P | AR826: INR | AS826: 3640000 | AT826: 3640000 | AU826: 22 | AV826: 0
D827: H-5XA1-06-02 | H827: H-5XA1-06-02 | I827: =J827*4129564.5 -> 3.4523159e+08 | J827: 83.6 | L827: 100000 | M827: 47500000 | N827: 83392 | O827: INR | P827: 39611200 | Q827: M | R827: Stock of Project Material-Domestic | T827: 109921 | U827: NEEC211121 | V827: 1 | W827: RMBE | X827: 12211000 | Y827: Stk of Prj Mat-Dom | Z827: 46203 | AA827: D | AB827: 1.00000 | AC827: 2026 | AD827: 0 | AE827: 6843021273 | AF827: CABLE,ELE,ARMRD,3.3KV,AL,XLPE,1C,400MM2 | AG827: 3 | AH827: H-5XA1 | AI827: 2 | AJ827: 6877 | AK827: INR | AL827: WBS element | AM827: WBS | AN827: 47500000 | AO827: 47500000 | AP827: 47500000 | AQ827: P | AR827: INR | AS827: 39611200 | AT827: 39611200 | AU827: 22 | AV827: 0
D828: H-5XA1-06-02 | H828: H-5XA1-06-02 | I828: =J828*4129564.5 -> 3.4564455e+08 | J828: 83.7 | L828: 200000 | M828: 95000000 | N828: 200000 | O828: INR | P828: 95000000 | Q828: M | R828: Stock of Project Material-Domestic | T828: 109921 | U828: NEEC211121 | V828: 1 | W828: RMBE | X828: 12211000 | Y828: Stk of Prj Mat-Dom | Z828: 46203 | AA828: D | AB828: 1.00000 | AC828: 2026 | AD828: 0 | AE828: 6843021273 | AF828: CABLE,ELE,ARMRD,3.3KV,AL,XLPE,1C,400MM2 | AG828: 3 | AH828: H-5XA1 | AI828: 3 | AJ828: 6877 | AK828: INR | AL828: WBS element | AM828: WBS | AN828: 95000000 | AO828: 95000000 | AP828: 95000000 | AQ828: P | AR828: INR | AS828: 95000000 | AT828: 95000000 | AU828: 22 | AV828: 0
D829: H-5XA1-06-02 | H829: H-5XA1-06-02 | I829: =J829*4129564.5 -> 3.4605751e+08 | J829: 83.8 | L829: 200000 | M829: 95000000 | N829: 200000 | O829: INR | P829: 95000000 | Q829: M | R829: Stock of Project Material-Domestic | T829: 109921 | U829: NEEC211121 | V829: 1 | W829: RMBE | X829: 12211000 | Y829: Stk of Prj Mat-Dom | Z829: 46203 | AA829: D | AB829: 1.00000 | AC829: 2026 | AD829: 0 | AE829: 6843021273 | AF829: CABLE,ELE,ARMRD,3.3KV,AL,XLPE,1C,400MM2 | AG829: 3 | AH829: H-5XA1 | AI829: 4 | AJ829: 6877 | AK829: INR | AL829: WBS element | AM829: WBS | AN829: 95000000 | AO829: 95000000 | AP829: 95000000 | AQ829: P | AR829: INR | AS829: 95000000 | AT829: 95000000 | AU829: 22 | AV829: 0
D830: H-5XA1-06-02 | H830: H-5XA1-06-02 | I830: =J830*4129564.5 -> 3.4647046e+08 | J830: 83.9 | L830: 25000 | M830: 29775000 | N830: 11801 | O830: INR | P830: 14054991 | Q830: M | R830: Stock of Project Material-Domestic | T830: 109921 | U830: NEEC211121 | V830: 1 | W830: RMBE | X830: 12211000 | Y830: Stk of Prj Mat-Dom | Z830: 46203 | AA830: D | AB830: 1.00000 | AC830: 2026 | AD830: 0 | AE830: 6843021663 | AF830: CABLE,1.1KV,3.5CX300MM2,AL,XLPE,A2XFY | AG830: 3 | AH830: H-5XA1 | AI830: 2 | AJ830: 6877 | AK830: INR | AL830: WBS element | AM830: WBS | AN830: 29775000 | AO830: 29775000 | AP830: 29775000 | AQ830: P | AR830: INR | AS830: 14054991 | AT830: 14054991 | AU830: 22 | AV830: 0
D831: H-5XA1-06-02 | H831: H-5XA1-06-02 | I831: =J831*4129564.5 -> 3.4688342e+08 | J831: 84 | L831: 12000 | M831: 3012000 | N831: 12000 | O831: INR | P831: 3012000 | Q831: M | R831: Stock of Project Material-Domestic | T831: 109921 | U831: WF-BATCH | V831: 1 | W831: RMBE | X831: 12211000 | Y831: Stk of Prj Mat-Dom | Z831: 46203 | AA831: D | AB831: 1.00000 | AC831: 2026 | AD831: 0 | AE831: 6843021663 | AF831: CABLE,1.1KV,3.5CX300MM2,AL,XLPE,A2XFY | AG831: 3 | AH831: H-5XA1 | AI831: 1 | AJ831: 6877 | AK831: INR | AL831: WBS element | AM831: WBS | AN831: 3012000 | AO831: 3012000 | AP831: 3012000 | AQ831: P | AR831: INR | AS831: 3012000 | AT831: 3012000 | AU831: 22 | AV831: 0
D832: H-5XA1-06-02 | H832: H-5XA1-06-02 | I832: =J832*4129564.5 -> 3.4729637e+08 | J832: 84.1 | L832: 10000 | M832: 2510000 | N832: 10000 | O832: INR | P832: 2510000 | Q832: M | R832: Stock of Project Material-Domestic | T832: 109921 | U832: WF-BATCH | V832: 1 | W832: RMBE | X832: 12211000 | Y832: Stk of Prj Mat-Dom | Z832: 46203 | AA832: D | AB832: 1.00000 | AC832: 2026 | AD832: 0 | AE832: 6843021663 | AF832: CABLE,1.1KV,3.5CX300MM2,AL,XLPE,A2XFY | AG832: 3 | AH832: H-5XA1 | AI832: 2 | AJ832: 6877 | AK832: INR | AL832: WBS element | AM832: WBS | AN832: 2510000 | AO832: 2510000 | AP832: 2510000 | AQ832: P | AR832: INR | AS832: 2510000 | AT832: 2510000 | AU832: 22 | AV832: 0
D833: H-5XWF-06-02 | H833: H-5XWF-06-02 | I833: =J833*4129564.5 -> 3.4770933e+08 | J833: 84.2 | L833: 60000 | M833: 28500000 | N833: 60000 | O833: INR | P833: 28500000 | Q833: M | R833: Stock of Project Material-Domestic | T833: 109921 | U833: 30133704 | V833: 1 | W833: RMBE | X833: 12211000 | Y833: Stk of Prj Mat-Dom | Z833: 46203 | AA833: D | AB833: 1.00000 | AC833: 2026 | AD833: 0 | AE833: 6843021273 | AF833: CABLE,ELE,ARMRD,3.3KV,AL,XLPE,1C,400MM2 | AG833: 3 | AH833: H-5XWF | AI833: 1 | AJ833: 6877 | AK833: INR | AL833: WBS element | AM833: WBS | AN833: 28500000 | AO833: 28500000 | AP833: 28500000 | AQ833: P | AR833: INR | AS833: 28500000 | AT833: 28500000 | AU833: 22 | AV833: 0
... D839: H-5XA2-06-02 | H839: H-5XA2-06-02 | I839: =J839*4129564.5 -> 3.5018707e+08 | J839: 84.8 | L839: 9000 | M839: 2259000 | N839: 9000 | O839: INR | P839: 2259000 | Q839: M | R839: Stock of Project Material-Domestic | T839: 109921 | U839: 30133704 | V839: 1 | W839: RMBE | X839: 12211000 | Y839: Stk of Prj Mat-Dom | Z839: 46203 | AA839: D | AB839: 1.00000 | AC839: 2026 | AD839: 0 | AE839: 6843021663 | AF839: CABLE,1.1KV,3.5CX300MM2,AL,XLPE,A2XFY | AG839: 3 | AH839: H-5XA2 | AI839: 2 | AJ839: 6877 | AK839: INR | AL839: WBS element | AM839: WBS | AN839: 2259000 | AO839: 2259000 | AP839: 2259000 | AQ839: P | AR839: INR | AS839: 2259000 | AT839: 2259000 | AU839: 22 | AV839: 0
D840: H-51X9-06-04 | H840: H-51X9-06-04 | I840: =J840*4129564.5 -> 3.5060003e+08 | J840: 84.9 | L840: 119974 | M840: 8878076 | N840: 119974 | O840: INR | P840: 8878076 | Q840: EA | R840: Stock of Project Material-Domestic | T840: 111618 | U840: WF-BATCH | V840: 1 | W840: RMBE | X840: 12211000 | Y840: Stk of Prj Mat-Dom | Z840: 46234 | AA840: D | AB840: 1.00000 | AC840: 2026 | AD840: 0 | AE840: 6964901143 | AF840: CABLE CLAMP | AG840: 4 | AH840: H-51X9 | AI840: 1 | AJ840: 6964 | AK840: INR | AL840: WBS element | AM840: WBS | AN840: 8878076 | AO840: 8878076 | AP840: 8878076 | AQ840: P | AR840: INR | AS840: 8878076 | AT840: 8878076 | AU840: 22 | AV840: 0 | AW840: 58P0
D841: H-51X9-06-04 | H841: H-51X9-06-04 | I841: =J841*4129564.5 -> 3.5101298e+08 | J841: 85 | L841: 1575 | M841: 51975 | N841: 1575 | O841: INR | P841: 51975 | Q841: SET | R841: Stock of Project Material-Domestic | T841: 111618 | U841: WF-BATCH | V841: 1 | W841: RMBE | X841: 12211000 | Y841: Stk of Prj Mat-Dom | Z841: 46234 | AA841: D | AB841: 1.00000 | AC841: 2026 | AD841: 0 | AE841: 9922310697 | AF841: HARDWARE | AG841: 4 | AH841: H-51X9 | AI841: 1 | AJ841: 9922 | AK841: INR | AL841: WBS element | AM841: WBS | AN841: 51975 | AO841: 51975 | AP841: 51975 | AQ841: P | AR841: INR | AS841: 51975 | AT841: 51975 | AU841: 22 | AV841: 0 | AW841: 58P0
D842: H-51X9-06-04 | H842: H-51X9-06-04 | I842: =J842*4129564.5 -> 3.5142594e+08 | J842: 85.1 | L842: 12 | M842: 1228890 | N842: 12 | O842: INR | P842: 1228890 | Q842: MT | R842: Stock of Project Material-Domestic | T842: 111618 | U842: WF-BATCH | V842: 1 | W842: RMBE | X842: 12211000 | Y842: Stk of Prj Mat-Dom | Z842: 46234 | AA842: D | AB842: 1.00000 | AC842: 2026 | AD842: 0 | AE842: 9922540112 | AF842: PREFABRICATED STRUCTURE | AG842: 4 | AH842: H-51X9 | AI842: 1 | AJ842: 6889 | AK842: INR | AL842: WBS element | AM842: WBS | AN842: 1228890 | AO842: 1228890 | AP842: 1228890 | AQ842: P | AR842: INR | AS842: 1228890 | AT842: 1228890 | AU842: 22 | AV842: 0 | AW842: 58P0
D843: H-51X9-06-04 | H843: H-51X9-06-04 | I843: =J843*4129564.5 -> 3.518389e+08 | J843: 85.2 | L843: 1500 | M843: 60855 | N843: 60 | O843: INR | P843: 2434.2 | Q843: M | R843: Stock of Project Material-Domestic | T843: 111618 | U843: WF-BATCH | V843: 1 | W843: RMBE | X843: 12211000 | Y843: Stk of Prj Mat-Dom | Z843: 46234 | AA843: D | AB843: 1.00000 | AC843: 2026 | AD843: 0 | AE843: 6801730523 | AF843: WIRE,ELE,CU,1CX4MM2 | AG843: 4 | AH843: H-51X9 | AI843: 1 | AJ843: 6877 | AK843: INR | AL843: WBS element | AM843: WBS | AN843: 60855 | AO843: 60855 | AP843: 60855 | AQ843: P | AR843: INR | AS843: 2434.2 | AT843: 2434.2 | AU843: 22 | AV843: 0 | AW843: 58P0
D844: H-51X9-06-04 | H844: H-51X9-06-04 | I844: =J844*4129564.5 -> 3.5225185e+08 | J844: 85.3 | L844: 1500 | M844: 38220 | N844: 60 | O844: INR | P844: 1528.8 | Q844: M | R844: Stock of Project Material-Domestic | T844: 111618 | U844: WF-BATCH | V844: 1 | W844: RMBE | X844: 12211000 | Y844: Stk of Prj Mat-Dom | Z844: 46234 | AA844: D | AB844: 1.00000 | AC844: 2026 | AD844: 0 | AE844: 6843907255 | AF844: WIRE,CU FLEXIBLE PVC 2.5MM2 | AG844: 4 | AH844: H-51X9 | AI844: 1 | AJ844: 6843 | AK844: INR | AL844: WBS element | AM844: WBS | AN844: 38220 | AO844: 38220 | AP844: 38220 | AQ844: P | AR844: INR | AS844: 1528.8 | AT844: 1528.8 | AU844: 22 | AV844: 0 | AW844: 58P0
D845: H-51X9-06-04 | H845: H-51X9-06-04 | I845: =J845*4129564.5 -> 3.5266481e+08 | J845: 85.4 | L845: 2600 | M845: 40898 | N845: 80 | O845: INR | P845: 1258.4 | Q845: M | R845: Stock of Project Material-Domestic | T845: 111618 | U845: WF-BATCH | V845: 1 | W845: RMBE | X845: 12211000 | Y845: Stk of Prj Mat-Dom | Z845: 46234 | AA845: D | AB845: 1.00000 | AC845: 2026 | AD845: 0 | AE845: 6801730533 | AF845: WIRE,ELE,CU,1CX1.5MM2 | AG845: 4 | AH845: H-51X9 | AI845: 1 | AJ845: 6877 | AK845: INR | AL845: WBS element | AM845: WBS | AN845: 40898 | AO845: 40898 | AP845: 40898 | AQ845: P | AR845: INR | AS845: 1258.4 | AT845: 1258.4 | AU845: 22 | AV845: 0 | AW845: 58P0
D846: H-51X9-06-04 | H846: H-51X9-06-04 | I846: =J846*4129564.5 -> 3.5307776e+08 | J846: 85.5 | L846: 12096 | M846: 7644672 | N846: 12096 | O846: INR | P846: 7644672 | Q846: EA | R846: Stock of Project Material-Domestic | T846: 111618 | U846: WF-BATCH | V846: 1 | W846: RMBE | X846: 12211000 | Y846: Stk of Prj Mat-Dom | Z846: 46234 | AA846: D | AB846: 1.00000 | AC846: 2026 | AD846: 0 | AE846: 6877160135 | AF846: GLAND,CABLE,DOUBLE COMP,12MM | AG846: 4 | AH846: H-51X9 | AI846: 1 | AJ846: 6877 | AK846: INR | AL846: WBS element | AM846: WBS | AN846: 7644672 | AO846: 7644672 | AP846: 7644672 | AQ846: P | AR846: INR | AS846: 7644672 | AT846: 7644672 | AU846: 22 | AV846: 0 | AW846: 58P0
D847: H-51X9-06-04 | H847: H-51X9-06-04 | I847: =J847*4129564.5 -> 3.5349072e+08 | J847: 85.6 | L847: 12096 | M847: 7777728 | N847: 12096 | O847: INR | P847: 7777728 | Q847: EA | R847: Stock of Project Material-Domestic | T847: 111618 | U847: WF-BATCH | V847: 1 | W847: RMBE | X847: 12211000 | Y847: Stk of Prj Mat-Dom | Z847: 46234 | AA847: D | AB847: 1.00000 | AC847: 2026 | AD847: 0 | AE847: 6877200236 | AF847: LUG,RING,BI-METAL,M12,55MM | AG847: 4 | AH847: H-51X9 | AI847: 1 | AJ847: 6877 | AK847: INR | AL847: WBS element | AM847: WBS | AN847: 7777728 | AO847: 7777728 | AP847: 7777728 | AQ847: P | AR847: INR | AS847: 7777728 | AT847: 7777728 | AU847: 22 | AV847: 0 | AW847: 58P0
D848: H-51X9-06-04 | H848: H-51X9-06-04 | I848: =J848*4129564.5 -> 3.5390368e+08 | J848: 85.7 | L848: 504 | M848: 685440 | N848: 504 | O848: INR | P848: 685440 | Q848: EA | R848: Stock of Project Material-Domestic | T848: 111618 | U848: WF-BATCH | V848: 1 | W848: RMBE | X848: 12211000 | Y848: Stk of Prj Mat-Dom | Z848: 46234 | AA848: D | AB848: 1.00000 | AC848: 2026 | AD848: 0 | AE848: 6877150713 | AF848: CABLE,GLAND,3.5CX300MM2,AL XLPE | AG848: 4 | AH848: H-51X9 | AI848: 1 | AJ848: 6877 | AK848: INR | AL848: WBS element | AM848: WBS | AN848: 685440 | AO848: 685440 | AP848: 685440 | AQ848: P | AR848: INR | AS848: 685440 | AT848: 685440 | AU848: 22 | AV848: 0 | AW848: 58P0
D849: H-51X9-06-04 | H849: H-51X9-06-04 | I849: =J849*4129564.5 -> 3.5431663e+08 | J849: 85.8 | L849: 1512 | M849: 813456 | N849: 1512 | O849: INR | P849: 813456 | Q849: EA | R849: Stock of Project Material-Domestic | T849: 111618 | U849: WF-BATCH | V849: 1 | W849: RMBE | X849: 12211000 | Y849: Stk of Prj Mat-Dom | Z849: 46234 | AA849: D | AB849: 1.00000 | AC849: 2026 | AD849: 0 | AE849: 6877200236 | AF849: LUG,RING,BI-METAL,M12,55MM | AG849: 4 | AH849: H-51X9 | AI849: 1 | AJ849: 6877 | AK849: INR | AL849: WBS element | AM849: WBS | AN849: 813456 | AO849: 813456 | AP849: 813456 | AQ849: P | AR849: INR | AS849: 813456 | AT849: 813456 | AU849: 22 | AV849: 0 | AW849: 58P0
D850: H-51X9-06-04 | H850: H-51X9-06-04 | I850: =J850*4129564.5 -> 3.5472959e+08 | J850: 85.9 | L850: 504 | M850: 166320 | N850: 504 | O850: INR | P850: 166320 | Q850: EA | R850: Stock of Project Material-Domestic | T850: 111618 | U850: WF-BATCH | V850: 1 | W850: RMBE | X850: 12211000 | Y850: Stk of Prj Mat-Dom | Z850: 46234 | AA850: D | AB850: 1.00000 | AC850: 2026 | AD850: 0 | AE850: 6877200236 | AF850: LUG,RING,BI-METAL,M12,55MM | AG850: 4 | AH850: H-51X9 | AI850: 1 | AJ850: 6877 | AK850: INR | AL850: WBS element | AM850: WBS | AN850: 166320 | AO850: 166320 | AP850: 166320 | AQ850: P | AR850: INR | AS850: 166320 | AT850: 166320 | AU850: 22 | AV850: 0 | AW850: 58P0
D851: H-51X9-06-04 | H851: H-51X9-06-04 | I851: =J851*4129564.5 -> 3.5514255e+08 | J851: 86 | L851: 504 | M851: 186480 | N851: 504 | O851: INR | P851: 186480 | Q851: EA | R851: Stock of Project Material-Domestic | T851: 111618 | U851: WF-BATCH | V851: 1 | W851: RMBE | X851: 12211000 | Y851: Stk of Prj Mat-Dom | Z851: 46234 | AA851: D | AB851: 1.00000 | AC851: 2026 | AD851: 0 | AE851: 6877160753 | AF851: CABLE GLAND,BI-MET LUG,SOCKET,3.5CX50MM2 | AG851: 4 | AH851: H-51X9 | AI851: 1 | AJ851: 6877 | AK851: INR | AL851: WBS element | AM851: WBS | AN851: 186480 | AO851: 186480 | AP851: 186480 | AQ851: P | AR851: INR | AS851: 186480 | AT851: 186480 | AU851: 22 | AV851: 0 | AW851: 58P0
... D900: H-5XA2-06-04 | H900: H-5XA2-06-04 | I900: =J900*4129564.5 -> 3.7537741e+08 | J900: 90.9 | L900: 70 | M900: 840 | N900: 70 | O900: INR | P900: 840 | Q900: EA | R900: Stock of Project Material-Domestic | T900: 111618 | U900: WF-BATCH | V900: 1 | W900: RMBE | X900: 12211000 | Y900: Stk of Prj Mat-Dom | Z900: 46234 | AA900: D | AB900: 1.00000 | AC900: 2026 | AD900: 0 | AE900: 6877200028 | AF900: LUG,CABLE,TUBULAR,CU,6MM2,F/EARTHING | AG900: 4 | AH900: H-5XA2 | AI900: 1 | AJ900: 6877 | AK900: INR | AL900: WBS element | AM900: WBS | AN900: 840 | AO900: 840 | AP900: 840 | AQ900: P | AR900: INR | AS900: 840 | AT900: 840 | AU900: 22 | AV900: 0 | AW900: 58P0
D901: H-5XA1-06-04 | H901: H-5XA1-06-04 | I901: =J901*4129564.5 -> 3.7579037e+08 | J901: 91 | L901: 215954 | M901: 15980596 | N901: 189704 | O901: INR | P901: 14038096 | Q901: EA | R901: Stock of Project Material-Domestic | T901: 227140 | U901: AUTO10039 | V901: 1 | W901: RMBE | X901: 12211000 | Y901: Stk of Prj Mat-Dom | Z901: 46234 | AA901: D | AB901: 1.00000 | AC901: 2026 | AD901: 0 | AE901: 6964901143 | AF901: CABLE CLAMP | AG901: 4 | AH901: H-5XA1 | AI901: 1 | AJ901: 6964 | AK901: INR | AL901: WBS element | AM901: WBS | AN901: 15980596 | AO901: 15980596 | AP901: 15980596 | AQ901: P | AR901: INR | AS901: 14038096 | AT901: 14038096 | AU901: 22 | AV901: 0
D902: H-5XA1-06-04 | H902: H-5XA1-06-04 | I902: =J902*4129564.5 -> 3.7620333e+08 | J902: 91.1 | L902: 2835 | M902: 93555 | N902: 2835 | O902: INR | P902: 93555 | Q902: SET | R902: Stock of Project Material-Domestic | T902: 227140 | U902: WF-BATCH | V902: 1 | W902: RMBE | X902: 12211000 | Y902: Stk of Prj Mat-Dom | Z902: 46234 | AA902: D | AB902: 1.00000 | AC902: 2026 | AD902: 0 | AE902: 9922310697 | AF902: HARDWARE | AG902: 4 | AH902: H-5XA1 | AI902: 1 | AJ902: 9922 | AK902: INR | AL902: WBS element | AM902: WBS | AN902: 93555 | AO902: 93555 | AP902: 93555 | AQ902: P | AR902: INR | AS902: 93555 | AT902: 93555 | AU902: 22 | AV902: 0
D903: H-5XA1-06-04 | H903: H-5XA1-06-04 | I903: =J903*4129564.5 -> 3.7661628e+08 | J903: 91.2 | L903: 2700 | M903: 109539 | N903: 2700 | O903: INR | P903: 109539 | Q903: M | R903: Stock of Project Material-Domestic | T903: 227140 | U903: WF-BATCH | V903: 1 | W903: RMBE | X903: 12211000 | Y903: Stk of Prj Mat-Dom | Z903: 46234 | AA903: D | AB903: 1.00000 | AC903: 2026 | AD903: 0 | AE903: 6801730523 | AF903: WIRE,ELE,CU,1CX4MM2 | AG903: 4 | AH903: H-5XA1 | AI903: 1 | AJ903: 6877 | AK903: INR | AL903: WBS element | AM903: WBS | AN903: 109539 | AO903: 109539 | AP903: 109539 | AQ903: P | AR903: INR | AS903: 109539 | AT903: 109539 | AU903: 22 | AV903: 0
D904: H-5XA1-06-04 | H904: H-5XA1-06-04 | I904: =J904*4129564.5 -> 3.7702924e+08 | J904: 91.3 | L904: 2700 | M904: 68796 | N904: 2700 | O904: INR | P904: 68796 | Q904: M | R904: Stock of Project Material-Domestic | T904: 227140 | U904: WF-BATCH | V904: 1 | W904: RMBE | X904: 12211000 | Y904: Stk of Prj Mat-Dom | Z904: 46234 | AA904: D | AB904: 1.00000 | AC904: 2026 | AD904: 0 | AE904: 6843907255 | AF904: WIRE,CU FLEXIBLE PVC 2.5MM2 | AG904: 4 | AH904: H-5XA1 | AI904: 1 | AJ904: 6843 | AK904: INR | AL904: WBS element | AM904: WBS | AN904: 68796 | AO904: 68796 | AP904: 68796 | AQ904: P | AR904: INR | AS904: 68796 | AT904: 68796 | AU904: 22 | AV904: 0
D905: H-5XA1-06-04 | H905: H-5XA1-06-04 | I905: =J905*4129564.5 -> 3.774422e+08 | J905: 91.4 | L905: 4680 | M905: 73616.4 | N905: 4680 | O905: INR | P905: 73616.4 | Q905: M | R905: Stock of Project Material-Domestic | T905: 227140 | U905: WF-BATCH | V905: 1 | W905: RMBE | X905: 12211000 | Y905: Stk of Prj Mat-Dom | Z905: 46234 | AA905: D | AB905: 1.00000 | AC905: 2026 | AD905: 0 | AE905: 6801730533 | AF905: WIRE,ELE,CU,1CX1.5MM2 | AG905: 4 | AH905: H-5XA1 | AI905: 1 | AJ905: 6877 | AK905: INR | AL905: WBS element | AM905: WBS | AN905: 73616.4 | AO905: 73616.4 | AP905: 73616.4 | AQ905: P | AR905: INR | AS905: 73616.4 | AT905: 73616.4 | AU905: 22 | AV905: 0
D906: H-5XA1-06-04 | H906: H-5XA1-06-04 | I906: =J906*4129564.5 -> 3.7785515e+08 | J906: 91.5 | L906: 21773 | M906: 13760536 | N906: 21773 | O906: INR | P906: 13760536 | Q906: EA | R906: Stock of Project Material-Domestic | T906: 227140 | U906: WF-BATCH | V906: 1 | W906: RMBE | X906: 12211000 | Y906: Stk of Prj Mat-Dom | Z906: 46234 | AA906: D | AB906: 1.00000 | AC906: 2026 | AD906: 0 | AE906: 6877160135 | AF906: GLAND,CABLE,DOUBLE COMP,12MM | AG906: 4 | AH906: H-5XA1 | AI906: 1 | AJ906: 6877 | AK906: INR | AL906: WBS element | AM906: WBS | AN906: 13760536 | AO906: 13760536 | AP906: 13760536 | AQ906: P | AR906: INR | AS906: 13760536 | AT906: 13760536 | AU906: 22 | AV906: 0
D907: H-5XA1-06-04 | H907: H-5XA1-06-04 | I907: =J907*4129564.5 -> 3.7826811e+08 | J907: 91.6 | L907: 21773 | M907: 14000039 | N907: 14573 | O907: INR | P907: 9370439 | Q907: EA | R907: Stock of Project Material-Domestic | T907: 227140 | U907: 30146385 | V907: 1 | W907: RMBE | X907: 12211000 | Y907: Stk of Prj Mat-Dom | Z907: 46234 | AA907: D | AB907: 1.00000 | AC907: 2026 | AD907: 0 | AE907: 6877200236 | AF907: LUG,RING,BI-METAL,M12,55MM | AG907: 4 | AH907: H-5XA1 | AI907: 1 | AJ907: 6877 | AK907: INR | AL907: WBS element | AM907: WBS | AN907: 14000039 | AO907: 14000039 | AP907: 14000039 | AQ907: P | AR907: INR | AS907: 9370439 | AT907: 9370439 | AU907: 22 | AV907: 0
D908: H-5XA1-06-04 | H908: H-5XA1-06-04 | I908: =J908*4129564.5 -> 3.7868106e+08 | J908: 91.7 | L908: 908 | M908: 1234880 | N908: 908 | O908: INR | P908: 1234880 | Q908: EA | R908: Stock of Project Material-Domestic | T908: 227140 | U908: WF-BATCH | V908: 1 | W908: RMBE | X908: 12211000 | Y908: Stk of Prj Mat-Dom | Z908: 46234 | AA908: D | AB908: 1.00000 | AC908: 2026 | AD908: 0 | AE908: 6877150713 | AF908: CABLE,GLAND,3.5CX300MM2,AL XLPE | AG908: 4 | AH908: H-5XA1 | AI908: 1 | AJ908: 6877 | AK908: INR | AL908: WBS element | AM908: WBS | AN908: 1234880 | AO908: 1234880 | AP908: 1234880 | AQ908: P | AR908: INR | AS908: 1234880 | AT908: 1234880 | AU908: 22 | AV908: 0
D909: H-5XA1-06-04 | H909: H-5XA1-06-04 | I909: =J909*4129564.5 -> 3.7909402e+08 | J909: 91.8 | L909: 2722 | M909: 1464436 | N909: 2722 | O909: INR | P909: 1464436 | Q909: EA | R909: Stock of Project Material-Domestic | T909: 227140 | U909: WF-BATCH | V909: 1 | W909: RMBE | X909: 12211000 | Y909: Stk of Prj Mat-Dom | Z909: 46234 | AA909: D | AB909: 1.00000 | AC909: 2026 | AD909: 0 | AE909: 6877200236 | AF909: LUG,RING,BI-METAL,M12,55MM | AG909: 4 | AH909: H-5XA1 | AI909: 1 | AJ909: 6877 | AK909: INR | AL909: WBS element | AM909: WBS | AN909: 1464436 | AO909: 1464436 | AP909: 1464436 | AQ909: P | AR909: INR | AS909: 1464436 | AT909: 1464436 | AU909: 22 | AV909: 0
D910: H-5XA1-06-04 | H910: H-5XA1-06-04 | I910: =J910*4129564.5 -> 3.7950698e+08 | J910: 91.9 | L910: 907 | M910: 299310 | N910: 907 | O910: INR | P910: 299310 | Q910: EA | R910: Stock of Project Material-Domestic | T910: 227140 | U910: WF-BATCH | V910: 1 | W910: RMBE | X910: 12211000 | Y910: Stk of Prj Mat-Dom | Z910: 46234 | AA910: D | AB910: 1.00000 | AC910: 2026 | AD910: 0 | AE910: 6877200236 | AF910: LUG,RING,BI-METAL,M12,55MM | AG910: 4 | AH910: H-5XA1 | AI910: 1 | AJ910: 6877 | AK910: INR | AL910: WBS element | AM910: WBS | AN910: 299310 | AO910: 299310 | AP910: 299310 | AQ910: P | AR910: INR | AS910: 299310 | AT910: 299310 | AU910: 22 | AV910: 0
D911: H-5XA1-06-04 | H911: H-5XA1-06-04 | I911: =J911*4129564.5 -> 3.7991993e+08 | J911: 92 | L911: 908 | M911: 335960 | N911: 908 | O911: INR | P911: 335960 | Q911: EA | R911: Stock of Project Material-Domestic | T911: 227140 | U911: WF-BATCH | V911: 1 | W911: RMBE | X911: 12211000 | Y911: Stk of Prj Mat-Dom | Z911: 46234 | AA911: D | AB911: 1.00000 | AC911: 2026 | AD911: 0 | AE911: 6877160753 | AF911: CABLE GLAND,BI-MET LUG,SOCKET,3.5CX50MM2 | AG911: 4 | AH911: H-5XA1 | AI911: 1 | AJ911: 6877 | AK911: INR | AL911: WBS element | AM911: WBS | AN911: 335960 | AO911: 335960 | AP911: 335960 | AQ911: P | AR911: INR | AS911: 335960 | AT911: 335960 | AU911: 22 | AV911: 0
D912: H-5XA1-06-04 | H912: H-5XA1-06-04 | I912: =J912*4129564.5 -> 3.8033289e+08 | J912: 92.1 | L912: 397 | M912: 264402 | N912: 397 | O912: INR | P912: 264402 | Q912: EA | R912: Stock of Project Material-Domestic | T912: 227140 | U912: WF-BATCH | V912: 1 | W912: RMBE | X912: 12211000 | Y912: Stk of Prj Mat-Dom | Z912: 46234 | AA912: D | AB912: 1.00000 | AC912: 2026 | AD912: 0 | AE912: 6877200231 | AF912: LUG,CABLE,RING,BI-METALLIC,300MM2,M16 | AG912: 4 | AH912: H-5XA1 | AI912: 1 | AJ912: 6877 | AK912: INR | AL912: WBS element | AM912: WBS | AN912: 264402 | AO912: 264402 | AP912: 264402 | AQ912: P | AR912: INR | AS912: 264402 | AT912: 264402 | AU912: 22 | AV912: 0
... D976: H-63A2-08-01-01 | H976: H-63A2-08-01-01 | I976: =J976*4129564.5 -> 4.067621e+08 | J976: 98.5 | L976: 384 | M976: 11939328 | N976: 384 | O976: INR | P976: 11939328 | Q976: EA | R976: Stock of Project Material-Domestic | T976: 254711 | U976: IBMI200014 | V976: 1 | W976: RMBE | X976: 12211000 | Y976: Stk of Prj Mat-Dom | Z976: 46188 | AA976: D | AB976: 1.00000 | AC976: 2026 | AD976: 0 | AE976: 9922540001 | AF976: PERFORATED PRECAST SQUARE COVER | AG976: 3 | AH976: H-63A2 | AI976: 1 | AJ976: 8080 | AK976: INR | AL976: WBS element | AM976: WBS | AN976: 11939328 | AO976: 11939328 | AP976: 11939328 | AQ976: P | AR976: INR | AS976: 11939328 | AT976: 11939328 | AU976: 22 | AV976: 0
D977: H-63X9-08-01-01 | H977: H-63X9-08-01-01 | I977: =J977*4129564.5 -> 4.0717506e+08 | J977: 98.6 | L977: 240 | M977: 8975760 | N977: 240 | O977: INR | P977: 8975760 | Q977: EA | R977: Stock of Project Material-Domestic | T977: 265604 | U977: RCSL10061 | V977: 1 | W977: RMBE | X977: 12211000 | Y977: Stk of Prj Mat-Dom | Z977: 46218 | AA977: D | AB977: 1.00000 | AC977: 2026 | AD977: 0 | AE977: 9922540001 | AF977: PERFORATED PRECAST SQUARE COVER | AG977: 4 | AH977: H-63X9 | AI977: 1 | AJ977: 8080 | AK977: INR | AL977: WBS element | AM977: WBS | AN977: 8975760 | AO977: 8975760 | AP977: 8975760 | AQ977: P | AR977: INR | AS977: 8975760 | AT977: 8975760 | AU977: 22 | AV977: 0 | AW977: 58C0
D978: H-63WG-08-01-02 | H978: H-63WG-08-01-02 | I978: =J978*4129564.5 -> 4.0758802e+08 | J978: 98.7 | L978: 54 | M978: 1036530 | N978: 1 | O978: INR | P978: 19195 | Q978: EA | R978: Stock of Project Material-Domestic | T978: 265604 | U978: 30213786 | V978: 1 | W978: RMBE | X978: 12211000 | Y978: Stk of Prj Mat-Dom | Z978: 46218 | AA978: D | AB978: 1.00000 | AC978: 2026 | AD978: 0 | AE978: 9922390669 | AF978: FOUNDATION ITEMS | AG978: 4 | AH978: H-63WG | AI978: 1 | AJ978: 9922 | AK978: INR | AL978: WBS element | AM978: WBS | AN978: 1036530 | AO978: 1036530 | AP978: 1036530 | AQ978: P | AR978: INR | AS978: 19195 | AT978: 19195 | AU978: 22 | AV978: 0 | AW978: 58C0
D979: H-63WG-08-01-01 | H979: H-63WG-08-01-01 | I979: =J979*4129564.5 -> 4.0800097e+08 | J979: 98.8 | L979: 432 | M979: 16156368 | N979: 432 | O979: INR | P979: 16156368 | Q979: EA | R979: Stock of Project Material-Domestic | T979: 265604 | U979: RCSL10061 | V979: 1 | W979: RMBE | X979: 12211000 | Y979: Stk of Prj Mat-Dom | Z979: 46218 | AA979: D | AB979: 1.00000 | AC979: 2026 | AD979: 0 | AE979: 9922540001 | AF979: PERFORATED PRECAST SQUARE COVER | AG979: 4 | AH979: H-63WG | AI979: 1 | AJ979: 8080 | AK979: INR | AL979: WBS element | AM979: WBS | AN979: 16156368 | AO979: 16156368 | AP979: 16156368 | AQ979: P | AR979: INR | AS979: 16156368 | AT979: 16156368 | AU979: 22 | AV979: 0 | AW979: 58C0
D980: H-63WD-08-01-01 | H980: H-63WD-08-01-01 | I980: =J980*4129564.5 -> 4.0841393e+08 | J980: 98.9 | L980: 448 | M980: 16754752 | N980: 448 | O980: INR | P980: 16754752 | Q980: EA | R980: Stock of Project Material-Domestic | T980: 265604 | U980: RCSL10061 | V980: 1 | W980: RMBE | X980: 12211000 | Y980: Stk of Prj Mat-Dom | Z980: 46218 | AA980: D | AB980: 1.00000 | AC980: 2026 | AD980: 0 | AE980: 9922540001 | AF980: PERFORATED PRECAST SQUARE COVER | AG980: 4 | AH980: H-63WD | AI980: 1 | AJ980: 8080 | AK980: INR | AL980: WBS element | AM980: WBS | AN980: 16754752 | AO980: 16754752 | AP980: 16754752 | AQ980: P | AR980: INR | AS980: 16754752 | AT980: 16754752 | AU980: 22 | AV980: 0 | AW980: 58C0
D981: H-63WD-08-01-02 | H981: H-63WD-08-01-02 | I981: =J981*4129564.5 -> 4.0882689e+08 | J981: 99 | L981: 56 | M981: 1074920 | N981: 45 | O981: INR | P981: 863775 | Q981: EA | R981: Stock of Project Material-Domestic | T981: 265604 | U981: RCSL10061 | V981: 1 | W981: RMBE | X981: 12211000 | Y981: Stk of Prj Mat-Dom | Z981: 46218 | AA981: D | AB981: 1.00000 | AC981: 2026 | AD981: 0 | AE981: 9922390669 | AF981: FOUNDATION ITEMS | AG981: 4 | AH981: H-63WD | AI981: 1 | AJ981: 9922 | AK981: INR | AL981: WBS element | AM981: WBS | AN981: 1074920 | AO981: 1074920 | AP981: 1074920 | AQ981: P | AR981: INR | AS981: 863775 | AT981: 863775 | AU981: 22 | AV981: 0 | AW981: 58C0
D982: H-63A1-08-01-03-01 | H982: H-63A1-08-01-03-01 | I982: =J982*4129564.5 -> 4.0923984e+08 | J982: 99.1 | L982: 54 | M982: 2700000 | N982: 54 | O982: INR | P982: 2700000 | Q982: EA | R982: Stock of Project Material-Domestic | T982: 254496 | U982: IBMI200014 | V982: 1 | W982: RMBE | X982: 12211000 | Y982: Stk of Prj Mat-Dom | Z982: 46188 | AA982: D | AB982: 1.00000 | AC982: 2026 | AD982: 0 | AE982: 9922540001 | AF982: PERFORATED PRECAST SQUARE COVER | AG982: 3 | AH982: H-63A1 | AI982: 1 | AJ982: 8080 | AK982: INR | AL982: WBS element | AM982: WBS | AN982: 2700000 | AO982: 2700000 | AP982: 2700000 | AQ982: P | AR982: INR | AS982: 2700000 | AT982: 2700000 | AU982: 22 | AV982: 0
D983: H-63A1-08-01-06-01 | H983: H-63A1-08-01-06-01 | I983: =J983*4129564.5 -> 4.096528e+08 | J983: 99.2 | L983: 9 | M983: 450000 | N983: 9 | O983: INR | P983: 450000 | Q983: EA | R983: Stock of Project Material-Domestic | T983: 254496 | U983: IBMI200014 | V983: 1 | W983: RMBE | X983: 12211000 | Y983: Stk of Prj Mat-Dom | Z983: 46188 | AA983: D | AB983: 1.00000 | AC983: 2026 | AD983: 0 | AE983: 9922540001 | AF983: PERFORATED PRECAST SQUARE COVER | AG983: 3 | AH983: H-63A1 | AI983: 1 | AJ983: 8080 | AK983: INR | AL983: WBS element | AM983: WBS | AN983: 450000 | AO983: 450000 | AP983: 450000 | AQ983: P | AR983: INR | AS983: 450000 | AT983: 450000 | AU983: 22 | AV983: 0
D984: H-63A2-08-01-03-01 | H984: H-63A2-08-01-03-01 | I984: =J984*4129564.5 -> 4.1006575e+08 | J984: 99.3 | L984: 48 | M984: 2400000 | N984: 48 | O984: INR | P984: 2400000 | Q984: EA | R984: Stock of Project Material-Domestic | T984: 254496 | U984: IBMI200014 | V984: 1 | W984: RMBE | X984: 12211000 | Y984: Stk of Prj Mat-Dom | Z984: 46188 | AA984: D | AB984: 1.00000 | AC984: 2026 | AD984: 0 | AE984: 9922540001 | AF984: PERFORATED PRECAST SQUARE COVER | AG984: 3 | AH984: H-63A2 | AI984: 1 | AJ984: 8080 | AK984: INR | AL984: WBS element | AM984: WBS | AN984: 2400000 | AO984: 2400000 | AP984: 2400000 | AQ984: P | AR984: INR | AS984: 2400000 | AT984: 2400000 | AU984: 22 | AV984: 0
D985: H-63A2-08-01-06-01 | H985: H-63A2-08-01-06-01 | I985: =J985*4129564.5 -> 4.1047871e+08 | J985: 99.4 | L985: 8 | M985: 400000 | N985: 8 | O985: INR | P985: 400000 | Q985: EA | R985: Stock of Project Material-Domestic | T985: 254496 | U985: IBMI200014 | V985: 1 | W985: RMBE | X985: 12211000 | Y985: Stk of Prj Mat-Dom | Z985: 46188 | AA985: D | AB985: 1.00000 | AC985: 2026 | AD985: 0 | AE985: 9922540001 | AF985: PERFORATED PRECAST SQUARE COVER | AG985: 3 | AH985: H-63A2 | AI985: 1 | AJ985: 8080 | AK985: INR | AL985: WBS element | AM985: WBS | AN985: 400000 | AO985: 400000 | AP985: 400000 | AQ985: P | AR985: INR | AS985: 400000 | AT985: 400000 | AU985: 22 | AV985: 0
D986: H-63X9-08-01-03-01 | H986: H-63X9-08-01-03-01 | I986: =J986*4129564.5 -> 4.1089167e+08 | J986: 99.5 | L986: 30 | M986: 1500000 | N986: 30 | O986: INR | P986: 1500000 | Q986: EA | R986: Stock of Project Material-Domestic | T986: 254496 | U986: IBMI200014 | V986: 1 | W986: RMBE | X986: 12211000 | Y986: Stk of Prj Mat-Dom | Z986: 46188 | AA986: D | AB986: 1.00000 | AC986: 2026 | AD986: 0 | AE986: 9922540001 | AF986: PERFORATED PRECAST SQUARE COVER | AG986: 3 | AH986: H-63X9 | AI986: 1 | AJ986: 8080 | AK986: INR | AL986: WBS element | AM986: WBS | AN986: 1500000 | AO986: 1500000 | AP986: 1500000 | AQ986: P | AR986: INR | AS986: 1500000 | AT986: 1500000 | AU986: 22 | AV986: 0
D987: H-63X9-08-01-06-01 | H987: H-63X9-08-01-06-01 | I987: =J987*4129564.5 -> 4.1130462e+08 | J987: 99.6 | L987: 5 | M987: 250000 | N987: 5 | O987: INR | P987: 250000 | Q987: EA | R987: Stock of Project Material-Domestic | T987: 254496 | U987: IBMI200014 | V987: 1 | W987: RMBE | X987: 12211000 | Y987: Stk of Prj Mat-Dom | Z987: 46188 | AA987: D | AB987: 1.00000 | AC987: 2026 | AD987: 0 | AE987: 9922540001 | AF987: PERFORATED PRECAST SQUARE COVER | AG987: 3 | AH987: H-63X9 | AI987: 1 | AJ987: 8080 | AK987: INR | AL987: WBS element | AM987: WBS | AN987: 250000 | AO987: 250000 | AP987: 250000 | AQ987: P | AR987: INR | AS987: 250000 | AT987: 250000 | AU987: 22 | AV987: 0
D988: H-63WG-08-01-03-01 | H988: H-63WG-08-01-03-01 | I988: =J988*4129564.5 -> 4.1171758e+08 | J988: 99.7 | L988: 54 | M988: 2700000 | N988: 54 | O988: INR | P988: 2700000 | Q988: EA | R988: Stock of Project Material-Domestic | T988: 254496 | U988: IBMI200014 | V988: 1 | W988: RMBE | X988: 12211000 | Y988: Stk of Prj Mat-Dom | Z988: 46188 | AA988: D | AB988: 1.00000 | AC988: 2026 | AD988: 0 | AE988: 9922540001 | AF988: PERFORATED PRECAST SQUARE COVER | AG988: 3 | AH988: H-63WG | AI988: 1 | AJ988: 8080 | AK988: INR | AL988: WBS element | AM988: WBS | AN988: 2700000 | AO988: 2700000 | AP988: 2700000 | AQ988: P | AR988: INR | AS988: 2700000 | AT988: 2700000 | AU988: 22 | AV988: 0
D989: H-63WG-08-01-06-01 | H989: H-63WG-08-01-06-01 | I989: =J989*4129564.5 -> 4.1213054e+08 | J989: 99.8 | L989: 9 | M989: 450000 | N989: 9 | O989: INR | P989: 450000 | Q989: EA | R989: Stock of Project Material-Domestic | T989: 254496 | U989: IBMI200014 | V989: 1 | W989: RMBE | X989: 12211000 | Y989: Stk of Prj Mat-Dom | Z989: 46188 | AA989: D | AB989: 1.00000 | AC989: 2026 | AD989: 0 | AE989: 9922540001 | AF989: PERFORATED PRECAST SQUARE COVER | AG989: 3 | AH989: H-63WG | AI989: 1 | AJ989: 8080 | AK989: INR | AL989: WBS element | AM989: WBS | AN989: 450000 | AO989: 450000 | AP989: 450000 | AQ989: P | AR989: INR | AS989: 450000 | AT989: 450000 | AU989: 22 | AV989: 0
D990: H-63WD-08-01-03-01 | H990: H-63WD-08-01-03-01 | I990: =J990*4129564.5 -> 4.1254349e+08 | J990: 99.9 | L990: 56 | M990: 2800000 | N990: 56 | O990: INR | P990: 2800000 | Q990: EA | R990: Stock of Project Material-Domestic | T990: 254496 | U990: IBMI200014 | V990: 1 | W990: RMBE | X990: 12211000 | Y990: Stk of Prj Mat-Dom | Z990: 46188 | AA990: D | AB990: 1.00000 | AC990: 2026 | AD990: 0 | AE990: 9922540001 | AF990: PERFORATED PRECAST SQUARE COVER | AG990: 3 | AH990: H-63WD | AI990: 1 | AJ990: 8080 | AK990: INR | AL990: WBS element | AM990: WBS | AN990: 2800000 | AO990: 2800000 | AP990: 2800000 | AQ990: P | AR990: INR | AS990: 2800000 | AT990: 2800000 | AU990: 22 | AV990: 0
D991: H-63WD-08-01-06-01 | H991: H-63WD-08-01-06-01 | I991: =J991*4129564.5 -> 4.1295645e+08 | J991: 100 | L991: 10 | M991: 500000 | N991: 10 | O991: INR | P991: 500000 | Q991: EA | R991: Stock of Project Material-Domestic | T991: 254496 | U991: IBMI200014 | V991: 1 | W991: RMBE | X991: 12211000 | Y991: Stk of Prj Mat-Dom | Z991: 46188 | AA991: D | AB991: 1.00000 | AC991: 2026 | AD991: 0 | AE991: 9922540001 | AF991: PERFORATED PRECAST SQUARE COVER | AG991: 3 | AH991: H-63WD | AI991: 1 | AJ991: 8080 | AK991: INR | AL991: WBS element | AM991: WBS | AN991: 500000 | AO991: 500000 | AP991: 500000 | AQ991: P | AR991: INR | AS991: 500000 | AT991: 500000 | AU991: 22 | AV991: 0
D992: H-63WD-08-01-05-02 | H992: H-63WD-08-01-05-02 | I992: =J992*4129564.5 -> 4.1336941e+08 | J992: 100.1 | L992: 16 | M992: 16 | N992: 16 | O992: INR | P992: 16 | Q992: MT | R992: Stock of Project Material-Domestic | T992: 234734 | U992: 30094000 | V992: 1 | W992: RMBE | X992: 12211000 | Y992: Stk of Prj Mat-Dom | Z992: 46233 | AA992: D | AB992: 1.00000 | AC992: 2026 | AD992: 0 | AE992: 9922290767 | AF992: PRIMARY,MEMBERS,AS,PER,SPEC | AG992: 4 | AH992: H-63WD | AI992: 1 | AJ992: 9922 | AK992: INR | AL992: WBS element | AM992: WBS | AN992: 16 | AO992: 16 | AP992: 16 | AQ992: P | AR992: INR | AS992: 16 | AT992: 16 | AU992: 22 | AV992: 0
D993: H-63WD-08-01-06-02 | H993: H-63WD-08-01-06-02 | I993: =J993*4129564.5 -> 4.1378236e+08 | J993: 100.2 | L993: 1 | M993: 101372 | N993: 1 | O993: INR | P993: 101372 | Q993: MT | R993: Stock of Project Material-Domestic | T993: 234734 | U993: WF-BATCH | V993: 1 | W993: RMBE | X993: 12211000 | Y993: Stk of Prj Mat-Dom | Z993: 46233 | AA993: D | AB993: 1.00000 | AC993: 2026 | AD993: 0 | AE993: 9922290767 | AF993: PRIMARY,MEMBERS,AS,PER,SPEC | AG993: 4 | AH993: H-63WD | AI993: 1 | AJ993: 9922 | AK993: INR | AL993: WBS element | AM993: WBS | AN993: 101372 | AO993: 101372 | AP993: 101372 | AQ993: P | AR993: INR | AS993: 101372 | AT993: 101372 | AU993: 22 | AV993: 0
... D1064: H-63WG-08-01-03-02 | H1064: H-63WG-08-01-03-02 | I1064: =J1064*4129564.5 -> 4.4310227e+08 | J1064: 107.3 | L1064: 19.872 | M1064: 2503872 | N1064: 19.872 | O1064: INR | P1064: 2503872 | Q1064: MT | R1064: Stock of Project Material-Domestic | T1064: 234734 | U1064: WF-BATCH | V1064: 1 | W1064: RMBE | X1064: 12211000 | Y1064: Stk of Prj Mat-Dom | Z1064: 46233 | AA1064: D | AB1064: 1.00000 | AC1064: 2026 | AD1064: 0 | AE1064: 9922540605 | AF1064: PIPE HANDRAILS,MS | AG1064: 4 | AH1064: H-63WG | AI1064: 1 | AJ1064: 9922 | AK1064: INR | AL1064: WBS element | AM1064: WBS | AN1064: 2503872 | AO1064: 2503872 | AP1064: 2503872 | AQ1064: P | AR1064: INR | AS1064: 2503872 | AT1064: 2503872 | AU1064: 22 | AV1064: 0
D1065: H-5XWG-06-04 | H1065: H-5XWG-06-04 | I1065: =J1065*4129564.5 -> 4.4351523e+08 | J1065: 107.4 | L1065: 2835 | M1065: 93555 | N1065: 2835 | O1065: INR | P1065: 93555 | Q1065: SET | R1065: Stock of Project Material-Domestic | T1065: 111618 | U1065: WF-BATCH | V1065: 1 | W1065: RMBE | X1065: 12211000 | Y1065: Stk of Prj Mat-Dom | Z1065: 46234 | AA1065: D | AB1065: 1.00000 | AC1065: 2026 | AD1065: 0 | AE1065: 9922310697 | AF1065: HARDWARE | AG1065: 4 | AH1065: H-5XWG | AI1065: 1 | AJ1065: 9922 | AK1065: INR | AL1065: WBS element | AM1065: WBS | AN1065: 93555 | AO1065: 93555 | AP1065: 93555 | AQ1065: P | AR1065: INR | AS1065: 93555 | AT1065: 93555 | AU1065: 22 | AV1065: 0 | AW1065: 58P0
D1066: H-5XWG-06-04 | H1066: H-5XWG-06-04 | I1066: =J1066*4129564.5 -> 4.4392818e+08 | J1066: 107.5 | L1066: 215954 | M1066: 15980596 | N1066: 215954 | O1066: INR | P1066: 15980596 | Q1066: EA | R1066: Stock of Project Material-Domestic | T1066: 111618 | U1066: WF-BATCH | V1066: 1 | W1066: RMBE | X1066: 12211000 | Y1066: Stk of Prj Mat-Dom | Z1066: 46234 | AA1066: D | AB1066: 1.00000 | AC1066: 2026 | AD1066: 0 | AE1066: 6964901143 | AF1066: CABLE CLAMP | AG1066: 4 | AH1066: H-5XWG | AI1066: 1 | AJ1066: 6964 | AK1066: INR | AL1066: WBS element | AM1066: WBS | AN1066: 15980596 | AO1066: 15980596 | AP1066: 15980596 | AQ1066: P | AR1066: INR | AS1066: 15980596 | AT1066: 15980596 | AU1066: 22 | AV1066: 0 | AW1066: 58P0
D1067: H-5XWG-06-04 | H1067: H-5XWG-06-04 | I1067: =J1067*4129564.5 -> 4.4434114e+08 | J1067: 107.6 | L1067: 414 | M1067: 9428436 | N1067: 275 | O1067: INR | P1067: 6262849.5 | Q1067: EA | R1067: Stock of Project Material-Domestic | T1067: 111618 | U1067: 30215701 | V1067: 1 | W1067: RMBE | X1067: 12211000 | Y1067: Stk of Prj Mat-Dom | Z1067: 46234 | AA1067: D | AB1067: 1.00000 | AC1067: 2026 | AD1067: 0 | AE1067: 6964210683 | AF1067: LIGHTING POLE,PN:BSGPE09,BAJAJ | AG1067: 4 | AH1067: H-5XWG | AI1067: 1 | AJ1067: 6964 | AK1067: INR | AL1067: WBS element | AM1067: WBS | AN1067: 9428436 | AO1067: 9428436 | AP1067: 9428436 | AQ1067: P | AR1067: INR | AS1067: 6262849.5 | AT1067: 6262849.5 | AU1067: 22 | AV1067: 0 | AW1067: 58P0
D1068: H-5XWG-06-04 | H1068: H-5XWG-06-04 | I1068: =J1068*4129564.5 -> 4.447541e+08 | J1068: 107.7 | L1068: 22 | M1068: 2252965 | N1068: 22 | O1068: INR | P1068: 2252965 | Q1068: MT | R1068: Stock of Project Material-Domestic | T1068: 111618 | U1068: WF-BATCH | V1068: 1 | W1068: RMBE | X1068: 12211000 | Y1068: Stk of Prj Mat-Dom | Z1068: 46234 | AA1068: D | AB1068: 1.00000 | AC1068: 2026 | AD1068: 0 | AE1068: 9922540112 | AF1068: PREFABRICATED STRUCTURE | AG1068: 4 | AH1068: H-5XWG | AI1068: 1 | AJ1068: 6889 | AK1068: INR | AL1068: WBS element | AM1068: WBS | AN1068: 2252965 | AO1068: 2252965 | AP1068: 2252965 | AQ1068: P | AR1068: INR | AS1068: 2252965 | AT1068: 2252965 | AU1068: 22 | AV1068: 0 | AW1068: 58P0
D1069: H-5XWG-06-04 | H1069: H-5XWG-06-04 | I1069: =J1069*4129564.5 -> 4.4516705e+08 | J1069: 107.8 | L1069: 21773 | M1069: 13760536 | N1069: 21773 | O1069: INR | P1069: 13760536 | Q1069: EA | R1069: Stock of Project Material-Domestic | T1069: 111618 | U1069: WF-BATCH | V1069: 1 | W1069: RMBE | X1069: 12211000 | Y1069: Stk of Prj Mat-Dom | Z1069: 46234 | AA1069: D | AB1069: 1.00000 | AC1069: 2026 | AD1069: 0 | AE1069: 6877160135 | AF1069: GLAND,CABLE,DOUBLE COMP,12MM | AG1069: 4 | AH1069: H-5XWG | AI1069: 1 | AJ1069: 6877 | AK1069: INR | AL1069: WBS element | AM1069: WBS | AN1069: 13760536 | AO1069: 13760536 | AP1069: 13760536 | AQ1069: P | AR1069: INR | AS1069: 13760536 | AT1069: 13760536 | AU1069: 22 | AV1069: 0 | AW1069: 58P0
D1070: H-5XWG-06-04 | H1070: H-5XWG-06-04 | I1070: =J1070*4129564.5 -> 4.4558001e+08 | J1070: 107.9 | L1070: 21773 | M1070: 14000039 | N1070: 21773 | O1070: INR | P1070: 14000039 | Q1070: EA | R1070: Stock of Project Material-Domestic | T1070: 111618 | U1070: WF-BATCH | V1070: 1 | W1070: RMBE | X1070: 12211000 | Y1070: Stk of Prj Mat-Dom | Z1070: 46234 | AA1070: D | AB1070: 1.00000 | AC1070: 2026 | AD1070: 0 | AE1070: 6877200236 | AF1070: LUG,RING,BI-METAL,M12,55MM | AG1070: 4 | AH1070: H-5XWG | AI1070: 1 | AJ1070: 6877 | AK1070: INR | AL1070: WBS element | AM1070: WBS | AN1070: 14000039 | AO1070: 14000039 | AP1070: 14000039 | AQ1070: P | AR1070: INR | AS1070: 14000039 | AT1070: 14000039 | AU1070: 22 | AV1070: 0 | AW1070: 58P0
D1071: H-5XWG-06-04 | H1071: H-5XWG-06-04 | I1071: =J1071*4129564.5 -> 445992966 | J1071: 108 | L1071: 908 | M1071: 1234880 | N1071: 908 | O1071: INR | P1071: 1234880 | Q1071: EA | R1071: Stock of Project Material-Domestic | T1071: 111618 | U1071: WF-BATCH | V1071: 1 | W1071: RMBE | X1071: 12211000 | Y1071: Stk of Prj Mat-Dom | Z1071: 46234 | AA1071: D | AB1071: 1.00000 | AC1071: 2026 | AD1071: 0 | AE1071: 6877150713 | AF1071: CABLE,GLAND,3.5CX300MM2,AL XLPE | AG1071: 4 | AH1071: H-5XWG | AI1071: 1 | AJ1071: 6877 | AK1071: INR | AL1071: WBS element | AM1071: WBS | AN1071: 1234880 | AO1071: 1234880 | AP1071: 1234880 | AQ1071: P | AR1071: INR | AS1071: 1234880 | AT1071: 1234880 | AU1071: 22 | AV1071: 0 | AW1071: 58P0
D1072: H-5XWG-06-04 | H1072: H-5XWG-06-04 | I1072: =J1072*4129564.5 -> 4.4640592e+08 | J1072: 108.1 | L1072: 2722 | M1072: 1464436 | N1072: 2722 | O1072: INR | P1072: 1464436 | Q1072: EA | R1072: Stock of Project Material-Domestic | T1072: 111618 | U1072: WF-BATCH | V1072: 1 | W1072: RMBE | X1072: 12211000 | Y1072: Stk of Prj Mat-Dom | Z1072: 46234 | AA1072: D | AB1072: 1.00000 | AC1072: 2026 | AD1072: 0 | AE1072: 6877200236 | AF1072: LUG,RING,BI-METAL,M12,55MM | AG1072: 4 | AH1072: H-5XWG | AI1072: 1 | AJ1072: 6877 | AK1072: INR | AL1072: WBS element | AM1072: WBS | AN1072: 1464436 | AO1072: 1464436 | AP1072: 1464436 | AQ1072: P | AR1072: INR | AS1072: 1464436 | AT1072: 1464436 | AU1072: 22 | AV1072: 0 | AW1072: 58P0
D1073: H-5XWG-06-04 | H1073: H-5XWG-06-04 | I1073: =J1073*4129564.5 -> 4.4681888e+08 | J1073: 108.2 | L1073: 907 | M1073: 299310 | N1073: 907 | O1073: INR | P1073: 299310 | Q1073: EA | R1073: Stock of Project Material-Domestic | T1073: 111618 | U1073: WF-BATCH | V1073: 1 | W1073: RMBE | X1073: 12211000 | Y1073: Stk of Prj Mat-Dom | Z1073: 46234 | AA1073: D | AB1073: 1.00000 | AC1073: 2026 | AD1073: 0 | AE1073: 6877200236 | AF1073: LUG,RING,BI-METAL,M12,55MM | AG1073: 4 | AH1073: H-5XWG | AI1073: 1 | AJ1073: 6877 | AK1073: INR | AL1073: WBS element | AM1073: WBS | AN1073: 299310 | AO1073: 299310 | AP1073: 299310 | AQ1073: P | AR1073: INR | AS1073: 299310 | AT1073: 299310 | AU1073: 22 | AV1073: 0 | AW1073: 58P0
D1074: H-5XWG-06-04 | H1074: H-5XWG-06-04 | I1074: =J1074*4129564.5 -> 4.4723184e+08 | J1074: 108.3 | L1074: 908 | M1074: 335960 | N1074: 908 | O1074: INR | P1074: 335960 | Q1074: EA | R1074: Stock of Project Material-Domestic | T1074: 111618 | U1074: WF-BATCH | V1074: 1 | W1074: RMBE | X1074: 12211000 | Y1074: Stk of Prj Mat-Dom | Z1074: 46234 | AA1074: D | AB1074: 1.00000 | AC1074: 2026 | AD1074: 0 | AE1074: 6877160753 | AF1074: CABLE GLAND,BI-MET LUG,SOCKET,3.5CX50MM2 | AG1074: 4 | AH1074: H-5XWG | AI1074: 1 | AJ1074: 6877 | AK1074: INR | AL1074: WBS element | AM1074: WBS | AN1074: 335960 | AO1074: 335960 | AP1074: 335960 | AQ1074: P | AR1074: INR | AS1074: 335960 | AT1074: 335960 | AU1074: 22 | AV1074: 0 | AW1074: 58P0
D1075: H-5XWG-06-04 | H1075: H-5XWG-06-04 | I1075: =J1075*4129564.5 -> 4.4764479e+08 | J1075: 108.4 | L1075: 2722 | M1075: 571620 | N1075: 2722 | O1075: INR | P1075: 571620 | Q1075: EA | R1075: Stock of Project Material-Domestic | T1075: 111618 | U1075: WF-BATCH | V1075: 1 | W1075: RMBE | X1075: 12211000 | Y1075: Stk of Prj Mat-Dom | Z1075: 46234 | AA1075: D | AB1075: 1.00000 | AC1075: 2026 | AD1075: 0 | AE1075: 6877170283 | AF1075: JNT/TERM KIT,ST,1.1KV,AR-XLPE,3.5CX50MM2 | AG1075: 4 | AH1075: H-5XWG | AI1075: 1 | AJ1075: 6877 | AK1075: INR | AL1075: WBS element | AM1075: WBS | AN1075: 571620 | AO1075: 571620 | AP1075: 571620 | AQ1075: P | AR1075: INR | AS1075: 571620 | AT1075: 571620 | AU1075: 22 | AV1075: 0 | AW1075: 58P0
D1076: H-5XWG-06-04 | H1076: H-5XWG-06-04 | I1076: =J1076*4129564.5 -> 4.4805775e+08 | J1076: 108.5 | L1076: 907 | M1076: 132422 | N1076: 907 | O1076: INR | P1076: 132422 | Q1076: EA | R1076: Stock of Project Material-Domestic | T1076: 111618 | U1076: WF-BATCH | V1076: 1 | W1076: RMBE | X1076: 12211000 | Y1076: Stk of Prj Mat-Dom | Z1076: 46234 | AA1076: D | AB1076: 1.00000 | AC1076: 2026 | AD1076: 0 | AE1076: 6877170283 | AF1076: JNT/TERM KIT,ST,1.1KV,AR-XLPE,3.5CX50MM2 | AG1076: 4 | AH1076: H-5XWG | AI1076: 1 | AJ1076: 6877 | AK1076: INR | AL1076: WBS element | AM1076: WBS | AN1076: 132422 | AO1076: 132422 | AP1076: 132422 | AQ1076: P | AR1076: INR | AS1076: 132422 | AT1076: 132422 | AU1076: 22 | AV1076: 0 | AW1076: 58P0
...

Sheet PSS 12_CAPEX 
A1: PSS-12: 960 MW/ 1926 MWH (Installed DC)/ 865 MWH (Dispatchable AC)
A2: Capex NFA Summary
A3: Sr No | B3: Description | C3: Proposed Capex Cost for PSS-12 | H3: Remarks (All costs provided below are on basis of MWH dispatchable AC)
C4: DC Installed MW | D4: DC Dispatchable MW | E4: AC Dispatachble MWH | F4: DC Installed MWH | G4: AC Dispatachble MWH
C5: 960 | D5: 982.4019 | E5: 1964.8038 | F5: 2167.4035 | G5: 1964.8038
C6: (INR-Cr) Individual Basic Value | D6: (INR-Cr) Individual Basic Value | E6: Rs. Lacs/ MWH | F6: Rs. Lacs/ MWH | G6: USD/kWh
A7: 1 | B7: Battery Containers (2 Hour system) | C7: 1538.6691 | D7: 1.5662318 | E7: 78.31159 | F7: 70.991354 | G7: 84.203661 | H7: Total Capacity 960 MW/1926MWh- 384 Nos of Container > Basic Cost USD 55/KWh (Present regulation of 9% Export VAT refund in China to BESS OEMs is expected to be withdrawn from 01-Jan-2026. This could result in corresponding increase in BESS prices). > Logistics Cost: USD 0.95/kWh > BCD Cost @ 8.25% as per PIR >Oversizing considerd is 1.11X as against 1.14X considered for Projects in FY25-26 >Forex as on 30-May-2025: 85.7; Forex as on 04-Nov-25: 88.64 (assumption: further 1.5% depreciation considered by the time of balance payments) > Forex rate of 91.29 considered for PSS-12Capex estimates
A8: 2 | B8: PCS (2 Hour system) | C8: 110.9897 | D8: 0.1129779 | E8: 5.6488949 | F8: 5.1208601 | G8: 6.0739111 | H8: Total 384 Nos of PCS >Basic Cost USD 32,000/Number > Logistics Cost: USD 240/Number > BCD Cost @ 8.25% >Forex as on 30-May-2025: 85.7; Forex as on 04-Nov-25: 88.64 (assumption: further 1.5% depreciation considered by the time of balance payments) > Forex rate of 91.29 considered for PSS-11 Capex estimates
A9: 3 | B9: EMS (2 Hour system) | C9: 19.695183 | D9: 0.02004799 | E9: 1.0023995 | F9: 0.90869943 | G9: 1.0778188 | H9: > EMS: USD 1.25/kWh > Cost of Battery Operating Servers, Data Twin-Edge servers and Servers for Arbitrage Analytics considered
A10: 3.1 | B10: Battery + PCS + EMS | C10: 1669.354 | D10: 1.6992577 | E10: 84.962885 | F10: 77.020913 | G10: 91.355391 | H10: > 69.7 Lac / MWh
A11: 4 | B11: Transformer & NIFPS | C11: 86.269844 | D11: 0.087815225 | E11: 4.3907613 | F11: 3.9803314 | G11: 4.7211169 | H11: > Trafo (18/20MVA ONAN/ONAF) 48 Nos. @ Rs. 2.02 Cr/Nos. > Additional 1 Nos Trafo considered in Spare cost (Refer Sr. No. 8)
A12: 5 | B12: BOS Elec | C12: 125.85017 | D12: 0.12810457 | E12: 6.4052285 | F12: 5.8064948 | G12: 6.8871503 | H12: >7.27 Lac/MWh
A13: 5.1 | B13: HT Panel | C13: 13.064 | D13: 0.01329802 | E13: 0.664901 | F13: 0.60274886 | G13: 0.71492736 | H13: > 0.75 Lac/MWh >Increase in cost since one spare feeder considered in each panel to cater to future augmentation/ re-powering
A14: 5.2 | B14: DC LT Cable | C14: 52.85121 | D14: 0.053797952 | E14: 2.6898976 | F14: 2.4384573 | G14: 2.8922823 | H14: >3.05 Lac/MWh >Increase in cost since Armoured & watertight cables are being considered.
A15: 5.3 | B15: HT Cable | C15: 15.960389 | D15: 0.016246293 | E15: 0.81231466 | F15: 0.73638291 | G15: 0.87343225 | H15: >0.92 Lac/MWh >HT Cable length has increased in view of 3 land parcels and increased price of HT Cables
A16: 5.4 | B16: Scada Cable & FO | C16: 2.3869572 | D16: 0.0024297156 | E16: 0.12148578 | F16: 0.1101298 | G16: 0.13062623 | H16: >0.14 Lac/MWh > As per updated BoQ, spread over 2 land parcels
A17: 5.5 | B17: ACDC/ Electrical Erection | C17: 41.587616 | D17: 0.042332589 | E17: 2.1166294 | F17: 1.9187759 | G17: 2.2758821 | H17: >2.40 Lac/MWh > Price reduction is on account of descoping of below items: a. LT Panels: Rs 5.3 Cr b. Cable Tray: Rs 1.4 Cr > Price increase on account of higher Rating of CSS (3.15 MVA as against 2.5 MVA presently used) > Cost of High Masts included
A18: 6 | B18: Installation and Comissioning | C18: 16.284051 | D18: 0.016575752 | E18: 0.82878762 | F18: 0.75131605 | G18: 0.89114461 | H18: >0.94 Lac/Mwh > he weighted average for Installation and Commissioning activities for Projects of FY 2025-26 is 2.3 USD per KWh [2.5 USD for PSS 5, 10 and 1,5 USD for PSS 8]. For PSS 11, we have considered 0.66 USD per KWh > Rs 5.1 Cr considerd as hiring cost of 3 nos. 160/180 T Crane for handling Battery Containers.
A19: 7 | B19: BOP Civil | C19: 60.105884 | D19: 0.061182582 | E19: 3.0591291 | F19: 2.7731746 | G19: 3.2892943 | H19: > 3.47 Lac/MWh > Foundations of all structures considerd on DCIS Piling basis.
A20: 7.1 | B20: Battery container Precast | C20: 23.830014 | D20: 0.02425689 | E20: 1.2128445 | F20: 1.0994729 | G20: 1.3040975
A21: 7.2 | B21: Transformer (Precast) | C21: 7.7443241 | D21: 0.0078830508 | E21: 0.39415254 | F21: 0.35730883 | G21: 0.42380811
A22: 7.3 | B22: BOT (Precast) | C22: 0.8805624 | D22: 0.00089633622 | E22: 0.044816811 | F22: 0.040627525 | G22: 0.048188775
A23: 7.4 | B23: Nifps (Precast) | C23: 0.19225776 | D23: 0.00019570174 | E23: 0.009785087 | F23: 0.0088704184 | G23: 0.010521305
A24: 7.5 | B24: Cable rack support (Precast) | C24: 0.60669 | D24: 0.00061755785 | E24: 0.030877892 | F24: 0.027991557 | G24: 0.033201108
A25: 7.6 | B25: PCS & Panel Foundation | C25: 18.745555 | D25: 0.019081351 | E25: 0.95406754 | F25: 0.86488534 | G25: 1.0258504
A26: 7.7 | B26: CSS FOUNDATION | C26: 1.08706 | D26: 0.0011065329 | E26: 0.055326644 | F26: 0.050154943 | G26: 0.059489355
A27: 7.8 | B27: Control Room | C27: 1.5325312 | D27: 0.001559984 | E27: 0.077999198 | F27: 0.070708162 | G27: 0.083867765
A28: 7.9 | B28: SGR Panel | C28: 1.5020532 | D28: 0.00152896 | E28: 0.076448 | F28: 0.069301964 | G28: 0.082199857
A29: 7.10 | B29: Earthen Drain | C29: 0.238446 | D29: 0.00024271737 | E29: 0.012135868 | F29: 0.011001459 | G29: 0.013048957
A30: 7.11 | B30: Security container | C30: 0.32721 | D30: 0.00033307143 | E30: 0.016653571 | F30: 0.015096866 | G30: 0.017906566
A31: 7.12 | B31: Bund | C31: 0.217111 | D31: 0.00022100018 | E31: 0.011050009 | F31: 0.010017101 | G31: 0.011881399
A32: 7.13 | B32: Road & Drain | C32: 2.155923 | D32: 0.0021945428
A34: 7.14 | B34: Fencing | C34: 1.046146 | D34: 0.0010648859 | E34: 0.053244297 | F34: 0.048267245 | G34: 0.057250335
A35: 8 | B35: Spares | C35: 13.430602 | D35: 0.013671189 | E35: 0.68355947 | F35: 0.61966321 | G35: 0.73498967 | H35: >0.78 Lac/MWh > Includes OEM recommended Spares of BESS, PCS, EMS and other equipment > Complete set as a spare being ordered : Battery Container - 1, PCS - 4, Trafo - 1 and CSS - 2. > In addition, Tools and Tackles + 1 Reach Stacker considered
A36: 9 | B36: Consultancy Charges | C36: 2.72 | D36: 0.0027687243 | E36: 0.13843621 | F36: 0.12549578 | G36: 0.14885199 | H36: >0.16 Lac/MWh >Engineering Consultancy, Grid Study Consultancy, Consultancy for PIR
A37: 10 | B37: ISA | C37: 184.52849 | D37: 0.18783401 | E37: 9.3917007 | F37: 8.5138042 | G37: 10.098321 | H37: PSS-11 (SRPL Park Land Area): > Khavda RE Park ESIA charges (@19 lakhs/MW) > Khavda RE Park ISA charges (@0.07 lakh/MW) > Connectivity at 950 MW Lease charges (annual) for PSS 12 Till 31st July 2026 - Rs 19250 + GST (per hectare) After 1st Aug 2026 - Rs 21837 + GST (per hectare) Total Area considered for PSS12: 62.61 Acres or 25.34 Hectare
A38: 11 | B38: Taxes & Duties | C38: 388.53774 | D38: 0.39549775 | E38: 19.774888 | F38: 17.926415 | G38: 21.262727 | H38: > 18% GST on Sr. No. 1 to 10
A39: A. Total Hard Cost | C39: 2547.0808 | D39: 2.5927075 | E39: 129.63538 | F39: 117.51761 | G39: 139.38899 | H39: > 116.1 Lacs/ Mwh
A40: 12 | B40: Pre Ops | C40: 44.889455 | D40: 0.045693575 | E40: 2.2846788 | F40: 2.0711167 | G40: 2.4565753 | H40: Preops: Rs.2.54 Lakh/MWh
A41: 12.1 | B41: Pre Ops | C41: 10.375683 | D41: 0.010561546 | E41: 0.5280773 | F41: 0.47871487 | G41: 0.56780921
A42: 12.2 | B42: Salary (including Corporate Charge) | C42: 30.336 | D42: 0.030879419 | E42: 1.543971 | F42: 1.3996471 | G42: 1.6601375
A43: 12.3 | B43: Insurance | C43: 4.1777723 | D43: 0.0042526102 | E43: 0.21263051 | F43: 0.19275471 | G43: 0.22862858
A44: 13 | B44: Financing & IDC | C44: 75.055505 | D44: 0.0764 | E44: 3.82 | F44: 3.4629225 | G44: 4.1074123
A45: 13.1 | B45: Financing | C45: 25.149489 | D45: 0.0256 | E45: 1.28 | F45: 1.160351 | G45: 1.3763057
A46: 13.2 | B46: IDC | C46: 49.906016 | D46: 0.0508 | E46: 2.54 | F46: 2.3025715 | G46: 2.7311066
A47: 14 | B47: PMC Fees | C47: 234.91348 | D47: 0.23912156 | E47: 11.956078 | F47: 10.838474 | G47: 12.855639 | H47: > 13.57 Lacs/ MWh > 12.5% PMC Fee on Hard Cost (Except Land Cost) Basic Hard Cost (excl Land)*12.5% + 18% GST
A48: 15 | B48: Contingency | C48: 70.157338 | D48: 0.07141409 | E48: 3.5707045 | F48: 3.2369301 | G48: 3.8393601 | H48: > 4.05 Lacs/ MWh > 3% of the Over all Cost
A49: B. Total Cost | B49: B. Total Cost | C49: 2972.0965 | D49: 3.0253367 | E49: 151.26684 | F49: 137.12705 | G49: 162.64797 | H49: > 139 Lacs/ MWh

Sheet PSS 10_CAPEX
A1: PSS-10: 600 MW/ 1204 MWH (Installed DC)/ 1073 MWH (Dispatchable AC)
A3: Sr No | B3: TPC (Total Proposed Cost) | C3: Details Included in TPC | D3: Responsible Team | E3: Proposed Capex Cost for PSS-10 | K3: Remarks (All costs provided below are on basis of MWH dispatchable AC)
E4: DC Installed MW | F4: DC Installed Cr/MW | G4: DC Dispatchable MW | H4: AC Dispatachble MWH | I4: DC Installed MWH | J4: AC Dispatachble MWH
E5: 600 | F5: 600 | G5: 536.515 | H5: 1073.03 | I5: 1203.84 | J5: 1073.03
E6: (INR-Cr) Individual Basic Value | F6: (INR-Cr) Individual Basic Value | G6: INR Cr/ MW | H6: Rs. Lacs/ MWH | I6: Rs. Lacs/ MWH | J6: USD/kWh
A7: 1 | B7: Battery Containers (2 Hour system) | E7: 823.47469 | F7: 1.3724578 | G7: 1.5348587 | H7: 76.742933 | I7: 68.403998 | J7: 82.51698 | K7: Total Capacity 1204 MWh / 240 Nos of Containers > Basic Cost USD 55/KWh (Present regulation of 9% Export VAT refund in China to BESS OEMs is expected to be withdrawn from 01-Jan-2026. This could result in corresponding increase in BESS prices). > Logistics Cost: USD 0.95/kWh > BCD Cost @ 8.25% as per PIR >>Oversizing considerd is 1.11X as against 1.14X considered for Projects in FY25-26 >Forex as on 30-May-2025: 85.7; Forex as on 04-Nov-25: 88.64 (assumption: further 1.5% depreciation considered by the time of balance payments) > Forex rate of 91.29 considered for PSS-11 Capex estimates
A8: 2 | B8: PCS (2 Hour system) | C8: Logistics Order Currency Mandatorty spares BCD & Fwd rate | D8: TC team | E8: 69.368563 | F8: 0.11561427 | G8: 0.12929473 | H8: 6.4647366 | I8: 5.7622743 | J8: 6.9511358 | K8: Total 240 Nos of PCS >Basic Cost USD 32,000/Number > Logistics Cost: USD 240/Number > BCD Cost @ 8.25% >Forex as on 30-May-2025: 85.7; Forex as on 04-Nov-25: 88.64 (assumption: further 1.5% depreciation considered by the time of balance payments) > Forex rate of 91.29 considered for PSS-11 Capex estimates
A9: 3 | B9: EMS (2 Hour system) | C9: Mandatorty spares Logic/ Arcitecture scope FIT/FAT Requirement | D9: TC team/ Technology Team | E9: 12.30949 | F9: 0.020515816 | G9: 0.022943421 | H9: 1.1471711 | I9: 1.0225187 | J9: 1.2334829 | K9: > EMS: USD 1.25/kWh > Cost of Battery Operating Servers, Data Twin-Edge servers and Servers for Arbitrage Analytics considered
A10: 3.1 | B10: Battery + PCS + EMS | E10: 905.15274 | F10: 1.5085879 | G10: 1.6870968 | H10: 84.354841 | I10: 75.188791 | J10: 90.701599 | K10: >69.7 Lac/MWh
A11: 4 | B11: Transformer & NIFPS | C11: Capacity Nos. Initial estimates Type test charges if required | D11: Engg/TC Team | E11: 54.068652 | F11: 0.090114421 | G11: 0.10077752 | H11: 5.0388761 | I11: 4.4913487 | J11: 5.4179952 | K11: > Trafo (18/20MVA ONAN/ONAF) 30 Nos. @ Rs. 2.02 Cr/Nos.
A12: 5 | B12: BOS Elec | C12: Basic Layout and Cable lengths from Engg to get initial estimates from TC team | E12: 87.745251 | F12: 0.14624208 | G12: 0.16354669 | H12: 8.1773344 | I12: 7.2887801 | J12: 8.7925873 | K12: >8.14 Lac/MWH
A13: 5.1 | B13: HT Panel | C13: Nos and Capacity ABT & CT meter requirements | E13: 8.165 | F13: 0.013608333 | G13: 0.015218587 | H13: 0.76092933 | I13: 0.67824628 | J13: 0.81818075 | K13: > 0.76 Lac/MWh >Increase in cost since one spare feeder considered in each panel to cater to future augmentation/ re-powering
A14: 5.2 | B14: DC LT Cable | C14: Length & type | E14: 33.13593 | F14: 0.055226549 | G14: 0.061761423 | H14: 3.0880711 | I14: 2.7525194 | J14: 3.320414 | K14: >3.06 Lac/MWh >Increase in cost since Armoured & watertight cables are being considered.
A15: 5.3 | B15: HT Cable | C15: Length & type | E15: 15.960389 | F15: 0.026600649 | G15: 0.029748263 | H15: 1.4874131 | I15: 1.3257899 | J15: 1.5993243 | K15: >1.48 Lac/MWh
A16: 5.4 | B16: Scada Cable & FO | C16: Length & type | E16: 2.3271924 | F16: 0.003878654 | G16: 0.0043376092 | H16: 0.21688046 | I16: 0.19331409 | J16: 0.23319829 | K16: >0.22 Lac/MWh
A17: 5.5 | B17: ACDC/ Electrical Erection | C17: BoQ and Components considerations from Engg. | E17: 28.156739 | F17: 0.046927899 | G17: 0.052480806 | H17: 2.6240403 | I17: 2.3389104 | J17: 2.82147 | K17: >2.61 Lac/MWh > Price reduction is on account of descoping of below items: a. LT Panels: Rs 5.3 Cr b. Cable Tray: Rs 1.4 Cr > Price increase on account of higher Rating of CSS (3.15 MVA as against 2.5 MVA presently used) > Cost of High Masts included
A18: 6 | B18: Installation and Comissioning | C18: Based on FY 25-26 Requirements the estimates to be made | E18: 9.953431 | F18: 0.016589052 | G18: 0.018552009 | H18: 0.92760044 | I18: 0.8268068 | J18: 0.997392 | K18: >0.92 Lac/Mwh > Rs2.26 Cr considerd for hiring cost of 3 nos. 160/180 T Crane for handling Battery Containers.
A19: 7 | B19: BOP Civil | E19: 37.803917 | F19: 0.063006529 | G19: 0.070461996 | H19: 3.5230998 | I19: 3.1402776 | J19: 3.7881736 | K19: > 3.51 Lac/MWh > Foundations of all structures considerd on DCIS Piling basis.
A20: 7.1 | B20: Battery container | E20: 14.824332 | H20: 1.3815394 | I20: 1.2314205 | J20: 1.4854848
A21: 7.2 | B21: Transformer | E21: 4.8402025 | H21: 0.45107803 | I21: 0.40206361 | J21: 0.4850166
A22: 7.3 | B22: BOT | E22: 0.5503515 | H22: 0.051289479 | I22: 0.045716333 | J22: 0.055148439
A23: 7.4 | B23: Aux. Trafo | E23: 0.6794125 | H23: 0.063317195 | I23: 0.05643711 | J23: 0.068081106
A24: 7.5 | B24: Nifps | E24: 0.1201611 | H24: 0.011198298 | I24: 0.0099814843 | J24: 0.012040845
A25: 7.6 | B25: Cable rack support | E25: 0.3314325 | H25: 0.030887534 | I25: 0.027531275 | J25: 0.033211475
A26: 7.7 | B26: PCS & Panel Foundation | E26: 11.737347 | H26: 1.0938508 | I26: 0.97499227 | J26: 1.1761508
A27: 7.8 | B27: Control Room | E27: 0.978466 | H27: 0.091187199 | I27: 0.081278741 | J27: 0.098048016
A28: 7.9 | B28: SGR Panel | E28: 1.0651233 | H28: 0.099263138 | I28: 0.088477144 | J28: 0.10673158
A29: 7.10 | B29: Earthen Drain | E29: 0.14902875 | H29: 0.013888591 | I29: 0.012379448 | J29: 0.014933552
A30: 7.11 | B30: Security Container | E30: 0.163605 | H30: 0.015247011 | I30: 0.013590261 | J30: 0.016394178
A31: 7.12 | B31: Bund | E31: 0.2414025 | H31: 0.022497274 | I31: 0.020052706 | J31: 0.024189942
A32: 7.13 | B32: Road Works | E32: 1.3474519 | H32: 0.12557448 | I32: 0.11192948 | J32: 0.13502256
A34: 7.14 | B34: Fencing Works | E34: 0.77560087 | H34: 0.072281379 | I34: 0.064427239 | J34: 0.077719744
A35: 8 | B35: Spares | C35: Trafo CSS Cables ACDC Battery PCS EMS | E35: 5.5942534 | F35: 0.0093237557 | G35: 0.010427022 | H35: 0.52135108 | I35: 0.46470074 | J35: 0.56057691 | K35: >0.52 Lac/MWh > Includes OEM recommended Spares of BESS, PCS, EMS and other equipment > 1 spare Battery container, 4 PCS considered. > Tools and Tackles + 1 Reach Stacker considered
A36: 9 | B36: Consultancy Charges | E36: 2.72 | F36: 0.0045333333 | G36: 0.0050697558 | H36: 0.25348779 | I36: 0.22594365 | J36: 0.27255991 | K36: >0.25 Lac/MWh >Engineering Consultancy, Grid Study Consultancy, Consultancy for PIR
A37: 10 | B37: ISA | C37: ISA Contract and Per MW Value | D37: BD | E37: 115.84337 | F37: 0.19307229 | G37: 0.21591824 | H37: 10.795912 | I37: 9.6228213 | J37: 11.608183 | K37: PSS-10 (SRPL Park Land Area): > Khavda RE Park ESIA charges (@19 lakhs/MW) > Khavda RE Park ISA charges (@0.07 lakh/MW) > Connectivity at 600 MW Lease charges for PSS 10: Till 31st July 2026 - Rs 19250 + GST (per hectare) After 1st Aug 2026 - Rs 21837 + GST (per hectare) Total Area considered for PSS10: 39.04 Acres or15.8 Hectare
A38: 11 | B38: Taxes & Duties | E38: 219.39869 | F38: 0.36566449 | G38: 0.40893301 | H38: 20.44665 | I38: 18.224905 | J38: 21.985032 | K38: > 18% GST on Sr. No. 1 to 10
A39: A. Total Hard Cost | E39: 1438.2803 | F39: 2.3971339 | G39: 2.680783 | H39: 134.03915 | I39: 119.47437 | J39: 144.1241 | K39: > 117.47 Lacs/ Mwh
A40: 12 | B40: Pre Ops | D40: Site Wise/ Projects Wise requirements of below: | E40: 27.915118 | F40: 0.046525197 | G40: 0.052030453 | H40: 2.6015227 | I40: 2.3188396 | J40: 2.7972581 | K40: Preops: Rs.2.64 Lakh/MWh.
A41: 12.1 | B41: Pre Ops | E41: 6.1812676 | G41: 0.011521146 | H41: 0.5760573 | I41: 0.51346255 | J41: 0.61939917
A42: 12.2 | B42: Salary (including Corporate Charge) | E42: 18.96 | G42: 0.03533918 | H42: 1.766959 | I42: 1.5749601 | J42: 1.8999029
A43: 12.3 | B43: Insurance | E43: 2.7738508 | G43: 0.0051701273 | H43: 0.25850636 | I43: 0.2304169 | J43: 0.27795608
A44: 13 | B44: Financing & IDC | E44: 31.600733 | F44: 0.052667889 | G44: 0.0589 | H44: 2.945 | I44: 2.6249945 | J44: 3.1665783
A45: 13.1 | B45: Financing | D45: IDC | E45: 14.432253 | F45: 0.024053756 | G45: 0.0269 | H45: 1.345 | I45: 1.1988515 | J45: 1.4461962
A46: 13.2 | B46: IDC | D46: Financing Charges | E46: 17.16848 | F46: 0.028614133 | G46: 0.032 | H46: 1.6 | I46: 1.426143 | J46: 1.7203821
A47: 14 | B47: PMC Fees | C47: As per the RPT approval (12.5 % of Hard Cost) | D47: Finance/ TC | E47: 148.07295 | F47: 0.24678824 | G47: 0.27599032 | H47: 13.799516 | I47: 12.300052 | J47: 14.837775 | K47: > 13.72 Lacs/ MWh > 12.5% PMC Fee on Hard Cost (Except Land Cost) Basic Hard Cost (excl Land)*12.5% + 18% GST
A48: 15 | B48: Contingency | D48: As per Finance | E48: 45.01396 | F48: 0.075023266 | G48: 0.083900655 | H48: 4.1950327 | I48: 3.7391979 | J48: 4.510662 | K48: > 4.10 Lacs/ MWh > 3% of the Over all Cost
A49: B. Total Cost | B49: B. Total Cost | E49: 1690.8831 | F49: 2.8181384 | G49: 3.1516045 | H49: 157.58022 | I49: 140.45746 | J49: 169.43637 | K49: > 140.74 Lacs/ MWh
E63: 46.71936
E64: 49.376073

Sheet SAP Working
D1: Sr No | E1: Level | F1: Description | G1: AGEL | H1: AGE6L | I1: SPV
B2: Project Name | C2: SPV | D2: 1 | E2: 0 | F2: AGE27BL-Khavda-BESS-PSS-11- 1080 MW/ 2167 MWH | G2: H-5XA1 | H2: H-63A1 | I2: H-6074 | K2: Over All | Q2: AGEL | W2: AG6L | AC2: SPV
B3: Khavda- PSS 11 | C3: AGE27BL | D3: 2 | E3: 1 | F3: AGE27BL-Khavda-BESS-PSS-11- 1080 MW/ 2167 MWH | G3: H-5XA1 | H3: H-63A1 | I3: H-6074 | K3: Total SAP Budget | L3: Total Actual | M3: Total Commitement | N3: Total Assigned | O3: Total Available | Q3: SAP Budget | R3: Actual | S3: Commitement | T3: Assigned | U3: Available | W3: SAP Budget | X3: Actual | Y3: Commitement | Z3: Assigned | AA3: Available | AC3: SAP Budget | AD3: Actual | AE3: Commitement | AF3: Assigned | AG3: Available
A4: 1 | B4: Khavda- PSS 11 | C4: AGE27BL | D4: 3 | E4: 2 | F4: BESS Package | G4: H-5XA1-01 | H4: H-63A1-01 | I4: H-6074-01 | J4: H-5XA1* | K4: =Q4 -> 15424113969 | L4: =R4 -> 24214800 | M4: =S4 -> 1.2809909e+09 | N4: =M4+L4 -> 1.3052057e+09 | O4: =K4-N4 -> 1.4118908e+10 | Q4: =SUM(Q5:Q7) -> 15424113969 | R4: =SUM(R5:R7) -> 24214800 | S4: =SUM(S5:S7) -> 1.2809909e+09 | T4: =SUM(T5:T7) -> 1.3052057e+09 | U4: =SUM(U5:U7) -> 1.4118908e+10 | W4: =SUM(W5:W7) -> 0 | X4: =SUM(X5:X7) -> 0 | Y4: =SUM(Y5:Y7) -> 0 | Z4: =SUM(Z5:Z7) -> 0 | AA4: =SUM(AA5:AA7) -> 0 | AC4: =SUM(AC5:AC7) -> 17946171840 | AD4: =SUM(AD5:AD7) -> 6813600 | AE4: =SUM(AE5:AE7) -> 1.0597288e+10 | AF4: =SUM(AF5:AF7) -> 1.0604102e+10 | AG4: =SUM(AG5:AG7) -> 7.3420698e+09
B5: Khavda- PSS 11 | C5: AGE27BL | D5: 4 | E5: 3 | F5: BESS Containers | G5: H-5XA1-01-01 | H5: H-63A1-01-01 | I5: H-6074-01-01 | J5: H-63A1* | K5: =Q5 -> 15422501597 | L5: =R5 -> 24214800 | M5: =S5 -> 5.7153173e+08 | N5: =M5+L5 -> 5.9574653e+08 | O5: =K5-N5 -> 1.4826755e+10 | Q5: =SUMIF(Budgeted_01jun!U:U,'SAP Working'!G5,Budgeted_01jun!R:R) -> 15422501597 | R5: =SUMIF('Actual_30 jun'!I:I,'SAP Working'!G5,'Actual_30 jun'!K:K) -> 24214800 | S5: =SUMIF('Commited_30 Jun'!H:H,'SAP Working'!G5,'Commited_30 Jun'!I:I) -> 5.7153173e+08 | T5: =S5+R5 -> 5.9574653e+08 | U5: =Q5-T5 -> 1.4826755e+10 | W5: =SUMIF(Budgeted_01jun!$U:$U,H5,Budgeted_01jun!$R:$R) -> 0 | X5: =SUMIF('Actual_30 jun'!$I:$I,'SAP Working'!H5,'Actual_30 jun'!$K:$K) -> 0 | Y5: =SUMIF('Commited_30 Jun'!$H:$H,'SAP Working'!H5,'Commited_30 Jun'!$I:$I) -> 0 | Z5: =Y5+X5 -> 0 | AA5: =W5-Z5 -> 0 | AC5: =SUMIF(Budgeted_01jun!$U:$U,'SAP Working'!I5,Budgeted_01jun!$R:$R) -> 17946171840 | AD5: =SUMIF('Actual_30 jun'!$I:$I,'SAP Working'!I5,'Actual_30 jun'!$K:$K) -> 6813600 | AE5: =SUMIF('Commited_30 Jun'!$H:$H,'SAP Working'!I5,'Commited_30 Jun'!$I:$I) -> 1.0597288e+10 | AF5: =AE5+AD5 -> 1.0604102e+10 | AG5: =AC5-AF5 -> 7.3420698e+09
B6: Khavda- PSS 11 | C6: AGE27BL | D6: 5 | E6: 3 | F6: BESS CNT. Logistics | G6: H-5XA1-01-02 | H6: H-63A1-01-02 | I6: H-6074-01-02 | J6: H-6074* | K6: =Q6 -> 1612372 | L6: =R6 -> 0 | M6: =S6 -> 7.0945918e+08 | N6: =M6+L6 -> 7.0945918e+08 | O6: =K6-N6 -> -7.0784681e+08 | Q6: =SUMIF(Budgeted_01jun!U:U,'SAP Working'!G6,Budgeted_01jun!R:R) -> 1612372 | S6: =SUMIF('Commited_30 Jun'!H:H,'SAP Working'!G6,'Commited_30 Jun'!I:I) -> 7.0945918e+08 | T6: =S6+R6 -> 7.0945918e+08 | U6: =Q6-T6 -> -7.0784681e+08 | W6: =SUMIF(Budgeted_01jun!$U:$U,H6,Budgeted_01jun!$R:$R) -> 0 | X6: =SUMIF('Actual_30 jun'!$I:$I,'SAP Working'!H6,'Actual_30 jun'!$K:$K) -> 0 | Y6: =SUMIF('Commited_30 Jun'!$H:$H,'SAP Working'!H6,'Commited_30 Jun'!$I:$I) -> 0 | Z6: =Y6+X6 -> 0 | AA6: =W6-Z6 -> 0 | AC6: =SUMIF(Budgeted_01jun!$U:$U,'SAP Working'!I6,Budgeted_01jun!$R:$R) -> 0 | AD6: =SUMIF('Actual_30 jun'!$I:$I,'SAP Working'!I6,'Actual_30 jun'!$K:$K) -> 0 | AE6: =SUMIF('Commited_30 Jun'!$H:$H,'SAP Working'!I6,'Commited_30 Jun'!$I:$I) -> 0 | AF6: =AE6+AD6 -> 0 | AG6: =AC6-AF6 -> 0
B7: Khavda- PSS 11 | C7: AGE27BL | D7: 6 | E7: 3 | F7: Commissioning Support | G7: H-5XA1-01-03 | H7: H-63A1-01-03 | I7: H-6074-01-03 | J7: H-5XA2* | N7: =M7+L7 -> 0 | O7: =K7-N7 -> 0 | Q7: =SUMIF(Budgeted_01jun!U:U,'SAP Working'!G7,Budgeted_01jun!R:R) -> 0 | R7: =SUMIF('Actual_30 jun'!I:I,'SAP Working'!G7,'Actual_30 jun'!K:K) -> 0 | S7: =SUMIF('Commited_30 Jun'!H:H,'SAP Working'!G7,'Commited_30 Jun'!I:I) -> 0 | T7: =S7+R7 -> 0 | U7: =Q7-T7 -> 0 | W7: =SUMIF(Budgeted_01jun!$U:$U,H7,Budgeted_01jun!$R:$R) -> 0 | X7: =SUMIF('Actual_30 jun'!$I:$I,'SAP Working'!H7,'Actual_30 jun'!$K:$K) -> 0 | Y7: =SUMIF('Commited_30 Jun'!$H:$H,'SAP Working'!H7,'Commited_30 Jun'!$I:$I) -> 0 | Z7: =Y7+X7 -> 0 | AA7: =W7-Z7 -> 0 | AC7: =SUMIF(Budgeted_01jun!$U:$U,'SAP Working'!I7,Budgeted_01jun!$R:$R) -> 0 | AD7: =SUMIF('Actual_30 jun'!$I:$I,'SAP Working'!I7,'Actual_30 jun'!$K:$K) -> 0 | AE7: =SUMIF('Commited_30 Jun'!$H:$H,'SAP Working'!I7,'Commited_30 Jun'!$I:$I) -> 0 | AF7: =AE7+AD7 -> 0 | AG7: =AC7-AF7 -> 0
A8: 2 | B8: Khavda- PSS 11 | C8: AGE27BL | D8: =D7+1 -> 7 | E8: 2 | F8: PCS Package | G8: H-5XA1-02 | H8: H-63A1-02 | I8: H-6074-02 | J8: H-63A2* | K8: =Q8 -> 1.108616e+09 | L8: =R8 -> 3688830 | M8: =S8 -> 3.3168662e+09 | N8: =M8+L8 -> 3.320555e+09 | O8: =K8-N8 -> -2.2119391e+09 | Q8: =SUM(Q9:Q10) -> 1.108616e+09 | R8: =SUM(R9:R10) -> 3688830 | S8: =SUM(S9:S10) -> 3.3168662e+09 | T8: =SUM(T9:T10) -> 3.320555e+09 | U8: =SUM(U9:U10) -> -2.2119391e+09 | W8: =SUM(W9:W10) -> 0 | X8: =SUMIF('Actual_30 jun'!$I:$I,'SAP Working'!H8,'Actual_30 jun'!$K:$K) -> 0 | Y8: =SUMIF('Commited_30 Jun'!$H:$H,'SAP Working'!H8,'Commited_30 Jun'!$I:$I) -> 0 | Z8: =SUM(Z9:Z10) -> 0 | AA8: =SUM(AA9:AA10) -> 0 | AC8: =SUM(AC9:AC10) -> 1254575958 | AD8: =SUM(AD9:AD10) -> 0 | AE8: =SUM(AE9:AE10) -> 1.0092656e+09 | AF8: =SUM(AF9:AF10) -> 1.0092656e+09 | AG8: =SUM(AG9:AG10) -> 2.4531039e+08
B9: Khavda- PSS 11 | C9: AGE27BL | D9: =D8+1 -> 8 | E9: 3 | F9: PCS Supply | G9: H-5XA1-02-01 | H9: H-63A1-02-01 | I9: H-6074-02-01 | J9: H-6764* | K9: =Q9 -> 1.1070036e+09 | L9: =R9 -> 3688830 | M9: =S9 -> 5.6905399e+08 | N9: =M9+L9 -> 5.7274282e+08 | O9: =K9-N9 -> 5.3426077e+08 | Q9: =SUMIF(Budgeted_01jun!U:U,'SAP Working'!G9,Budgeted_01jun!R:R) -> 1.1070036e+09 | R9: =SUMIF('Actual_30 jun'!I:I,'SAP Working'!G9,'Actual_30 jun'!K:K) -> 3688830 | S9: =SUMIF('Commited_30 Jun'!H:H,'SAP Working'!G9,'Commited_30 Jun'!I:I) -> 5.6905399e+08 | T9: =S9+R9 -> 5.7274282e+08 | U9: =Q9-T9 -> 5.3426077e+08 | W9: =SUMIF(Budgeted_01jun!$U:$U,H9,Budgeted_01jun!$R:$R) -> 0 | X9: =SUMIF('Actual_30 jun'!$I:$I,'SAP Working'!H9,'Actual_30 jun'!$K:$K) -> 0 | Y9: =SUMIF('Commited_30 Jun'!$H:$H,'SAP Working'!H9,'Commited_30 Jun'!$I:$I) -> 0 | Z9: =Y9+X9 -> 0 | AA9: =W9-Z9 -> 0 | AC9: =SUMIF(Budgeted_01jun!$U:$U,'SAP Working'!I9,Budgeted_01jun!$R:$R) -> 1254575958 | AD9: =SUMIF('Actual_30 jun'!$I:$I,'SAP Working'!I9,'Actual_30 jun'!$K:$K) -> 0 | AE9: =SUMIF('Commited_30 Jun'!$H:$H,'SAP Working'!I9,'Commited_30 Jun'!$I:$I) -> 1.0092656e+09 | AF9: =AE9+AD9 -> 1.0092656e+09 | AG9: =AC9-AF9 -> 2.4531039e+08
B10: Khavda- PSS 11 | C10: AGE27BL | D10: =D9+1 -> 9 | E10: 3 | F10: PCS Cnt. Logistics | G10: H-5XA1-02-02 | H10: H-63A1-02-02 | I10: H-6074-02-02 | J10: H-51X9* | K10: =Q10 -> 1612372 | L10: =R10 -> 0 | M10: =S10 -> 2.7478122e+09 | N10: =M10+L10 -> 2.7478122e+09 | O10: =K10-N10 -> -2.7461998e+09 | Q10: =SUMIF(Budgeted_01jun!U:U,'SAP Working'!G10,Budgeted_01jun!R:R) -> 1612372 | R10: =SUMIF('Actual_30 jun'!I:I,'SAP Working'!G10,'Actual_30 jun'!K:K) -> 0 | S10: =SUMIF('Commited_30 Jun'!H:H,'SAP Working'!G10,'Commited_30 Jun'!I:I) -> 2.7478122e+09 | T10: =S10+R10 -> 2.7478122e+09 | U10: =Q10-T10 -> -2.7461998e+09 | W10: =SUMIF(Budgeted_01jun!$U:$U,H10,Budgeted_01jun!$R:$R) -> 0 | X10: =SUMIF('Actual_30 jun'!$I:$I,'SAP Working'!H10,'Actual_30 jun'!$K:$K) -> 0 | Y10: =SUMIF('Commited_30 Jun'!$H:$H,'SAP Working'!H10,'Commited_30 Jun'!$I:$I) -> 0 | Z10: =Y10+X10 -> 0 | AA10: =W10-Z10 -> 0 | AC10: =SUMIF(Budgeted_01jun!$U:$U,'SAP Working'!I10,Budgeted_01jun!$R:$R) -> 0 | AD10: =SUMIF('Actual_30 jun'!$I:$I,'SAP Working'!I10,'Actual_30 jun'!$K:$K) -> 0 | AE10: =SUMIF('Commited_30 Jun'!$H:$H,'SAP Working'!I10,'Commited_30 Jun'!$I:$I) -> 0 | AF10: =AE10+AD10 -> 0 | AG10: =AC10-AF10 -> 0
A11: 3 | B11: Khavda- PSS 11 | C11: AGE27BL | D11: =D10+1 -> 10 | E11: 2 | F11: EMS Package | G11: H-5XA1-03 | H11: H-63A1-03 | I11: H-6074-03 | J11: H-63X9* | K11: =Q11 -> 125000000 | L11: =R11 -> 2921790 | M11: =S11 -> 1.9780614e+08 | N11: =M11+L11 -> 2.0072793e+08 | O11: =K11-N11 -> -75727930 | Q11: =SUM(Q12:Q13) -> 125000000 | R11: =SUM(R12:R13) -> 2921790 | S11: =SUM(S12:S13) -> 1.9780614e+08 | T11: =SUM(T12:T13) -> 2.0072793e+08 | U11: =SUM(U12:U13) -> -75727930 | W11: =SUM(W12:W13) -> 0 | X11: =SUMIF('Actual_30 jun'!$I:$I,'SAP Working'!H11,'Actual_30 jun'!$K:$K) -> 0 | Y11: =SUMIF('Commited_30 Jun'!$H:$H,'SAP Working'!H11,'Commited_30 Jun'!$I:$I) -> 0 | Z11: =SUM(Z12:Z13) -> 0 | AA11: =SUM(AA12:AA13) -> 0 | AC11: =SUM(AC12:AC13) -> 0 | AD11: =SUM(AD12:AD13) -> 0 | AE11: =SUM(AE12:AE13) -> 0 | AF11: =SUM(AF12:AF13) -> 0 | AG11: =SUM(AG12:AG13) -> 0
B12: Khavda- PSS 11 | C12: AGE27BL | D12: =D11+1 -> 11 | E12: 3 | F12: EMS Supply | G12: H-5XA1-03-01 | H12: H-63A1-03-01 | I12: H-6074-03-01 | J12: H-51N2* | K12: =Q12 -> 125000000 | L12: =R12 -> 2921790 | M12: =S12 -> 1.9780614e+08 | N12: =M12+L12 -> 2.0072793e+08 | O12: =K12-N12 -> -75727930 | Q12: =SUMIF(Budgeted_01jun!U:U,'SAP Working'!G12,Budgeted_01jun!R:R) -> 125000000 | R12: =SUMIF('Actual_30 jun'!I:I,'SAP Working'!G12,'Actual_30 jun'!K:K) -> 2921790 | S12: =SUMIF('Commited_30 Jun'!H:H,'SAP Working'!G12,'Commited_30 Jun'!I:I) -> 1.9780614e+08 | T12: =S12+R12 -> 2.0072793e+08 | U12: =Q12-T12 -> -75727930 | W12: =SUMIF(Budgeted_01jun!$U:$U,H12,Budgeted_01jun!$R:$R) -> 0 | X12: =SUMIF('Actual_30 jun'!$I:$I,'SAP Working'!H12,'Actual_30 jun'!$K:$K) -> 0 | Y12: =SUMIF('Commited_30 Jun'!$H:$H,'SAP Working'!H12,'Commited_30 Jun'!$I:$I) -> 0 | Z12: =Y12+X12 -> 0 | AA12: =W12-Z12 -> 0 | AC12: =SUMIF(Budgeted_01jun!$U:$U,'SAP Working'!I12,Budgeted_01jun!$R:$R) -> 0 | AD12: =SUMIF('Actual_30 jun'!$I:$I,'SAP Working'!I12,'Actual_30 jun'!$K:$K) -> 0 | AE12: =SUMIF('Commited_30 Jun'!$H:$H,'SAP Working'!I12,'Commited_30 Jun'!$I:$I) -> 0 | AF12: =AE12+AD12 -> 0 | AG12: =AC12-AF12 -> 0
B13: Khavda- PSS 11 | C13: AGE27BL | D13: =D12+1 -> 12 | E13: 3 | F13: EMS Logistics | G13: H-5XA1-03-02 | H13: H-63A1-03-02 | I13: H-6074-03-02 | J13: H-5XWG* | K13: =Q13 -> 0 | L13: =R13 -> 0 | M13: =S13 -> 0 | N13: =M13+L13 -> 0 | O13: =K13-N13 -> 0 | Q13: =SUMIF(Budgeted_01jun!U:U,'SAP Working'!G13,Budgeted_01jun!R:R) -> 0 | R13: =SUMIF('Actual_30 jun'!I:I,'SAP Working'!G13,'Actual_30 jun'!K:K) -> 0 | S13: =SUMIF('Commited_30 Jun'!H:H,'SAP Working'!G13,'Commited_30 Jun'!I:I) -> 0 | T13: =S13+R13 -> 0 | U13: =Q13-T13 -> 0 | W13: =SUMIF(Budgeted_01jun!$U:$U,H13,Budgeted_01jun!$R:$R) -> 0 | X13: =SUMIF('Actual_30 jun'!$I:$I,'SAP Working'!H13,'Actual_30 jun'!$K:$K) -> 0 | Y13: =SUMIF('Commited_30 Jun'!$H:$H,'SAP Working'!H13,'Commited_30 Jun'!$I:$I) -> 0 | Z13: =Y13+X13 -> 0 | AA13: =W13-Z13 -> 0 | AC13: =SUMIF(Budgeted_01jun!$U:$U,'SAP Working'!I13,Budgeted_01jun!$R:$R) -> 0 | AD13: =SUMIF('Actual_30 jun'!$I:$I,'SAP Working'!I13,'Actual_30 jun'!$K:$K) -> 0 | AE13: =SUMIF('Commited_30 Jun'!$H:$H,'SAP Working'!I13,'Commited_30 Jun'!$I:$I) -> 0 | AF13: =AE13+AD13 -> 0 | AG13: =AC13-AF13 -> 0
A14: 4 | B14: Khavda- PSS 11 | C14: AGE27BL | D14: =D13+1 -> 13 | E14: 2 | F14: IDT Transformer Supply | G14: H-5XA1-04 | H14: H-63A1-04 | I14: H-6074-04 | J14: H-63WG* | K14: =Q14+W14 -> 979795453 | L14: =R14+X14 -> 163337700 | M14: =S14+Y14 -> 1.4057038e+09 | N14: =M14+L14 -> 1.5690415e+09 | O14: =K14-N14 -> -5.89246e+08 | Q14: =SUMIF(Budgeted_01jun!U:U,'SAP Working'!G14,Budgeted_01jun!R:R) -> 956571053 | R14: =SUMIF('Actual_30 jun'!I:I,'SAP Working'!G14,'Actual_30 jun'!K:K) -> 159804930 | S14: =SUMIF('Commited_30 Jun'!H:H,'SAP Working'!G14,'Commited_30 Jun'!I:I) -> 0 | T14: =S14+R14 -> 159804930 | U14: =Q14-T14 -> 796766123 | W14: =SUMIF(Budgeted_01jun!$U:$U,H14,Budgeted_01jun!$R:$R) -> 23224400 | X14: =SUMIF('Actual_30 jun'!$I:$I,'SAP Working'!H14,'Actual_30 jun'!$K:$K) -> 3532770 | Y14: =SUMIF('Commited_30 Jun'!$H:$H,'SAP Working'!H14,'Commited_30 Jun'!$I:$I) -> 1.4057038e+09 | Z14: =Y14+X14 -> 1.4092365e+09 | AA14: =W14-Z14 -> -1.3860121e+09 | AC14: =SUMIF(Budgeted_01jun!$U:$U,'SAP Working'!I14,Budgeted_01jun!$R:$R) -> 9.2907344e+08 | AD14: =SUMIF('Actual_30 jun'!$I:$I,'SAP Working'!I14,'Actual_30 jun'!$K:$K) -> 8570550 | AE14: =SUMIF('Commited_30 Jun'!$H:$H,'SAP Working'!I14,'Commited_30 Jun'!$I:$I) -> 0 | AF14: =AE14+AD14 -> 8570550 | AG14: =AC14-AF14 -> 9.2050289e+08
A15: 6 | B15: Khavda- PSS 11 | C15: AGE27BL | D15: =D14+1 -> 14 | E15: 2 | F15: Installation, Integration & Commissioning DC Side | G15: H-5XA1-05 | H15: H-63A1-05 | I15: H-6074-05 | J15: H-6497* | K15: =W15 -> 119657314 | L15: =X15 -> 0 | M15: =Y15 -> 3.0587684e+09 | N15: =M15+L15 -> 3.0587684e+09 | O15: =K15-N15 -> -2.9391111e+09 | Q15: =SUM(Q16:Q18) -> 0 | R15: =SUM(R16:R18) -> 0 | S15: =SUM(S16:S18) -> 0 | T15: =SUM(T16:T18) -> 0 | U15: =SUM(U16:U18) -> 0 | W15: =SUM(W16:W18) -> 119657314 | X15: =SUM(X16:X18) -> 0 | Y15: =SUM(Y16:Y18) -> 3.0587684e+09 | Z15: =SUM(Z16:Z18) -> 3.0587684e+09 | AA15: =SUM(AA16:AA18) -> -2.9391111e+09 | AC15: =SUM(AC16:AC18) -> 0 | AD15: =SUM(AD16:AD18) -> 0 | AE15: =SUM(AE16:AE18) -> 0 | AF15: =SUM(AF16:AF18) -> 0 | AG15: =SUM(AG16:AG18) -> 0
B16: Khavda- PSS 11 | C16: AGE27BL | D16: =D15+1 -> 15 | E16: 3 | F16: Installation Manpower | G16: H-5XA1-05-01 | H16: H-63A1-05-01 | I16: H-6074-05-01 | J16: H-5XWD* | K16: =W16 -> 69610050 | L16: =X16 -> 0 | M16: =Y16 -> 1.5518903e+09 | N16: =M16+L16 -> 1.5518903e+09 | O16: =K16-N16 -> -1.4822803e+09 | Q16: =SUMIF(Budgeted_01jun!U:U,'SAP Working'!G16,Budgeted_01jun!R:R) -> 0 | R16: =SUMIF('Actual_30 jun'!I:I,'SAP Working'!G16,'Actual_30 jun'!K:K) -> 0 | S16: =SUMIF('Commited_30 Jun'!H:H,'SAP Working'!G16,'Commited_30 Jun'!I:I) -> 0 | T16: =S16+R16 -> 0 | U16: =Q16-T16 -> 0 | W16: =SUMIF(Budgeted_01jun!$U:$U,H16,Budgeted_01jun!$R:$R) -> 69610050 | X16: =SUMIF('Actual_30 jun'!$I:$I,'SAP Working'!H16,'Actual_30 jun'!$K:$K) -> 0 | Y16: =SUMIF('Commited_30 Jun'!$H:$H,'SAP Working'!H16,'Commited_30 Jun'!$I:$I) -> 1.5518903e+09 | Z16: =Y16+X16 -> 1.5518903e+09 | AA16: =W16-Z16 -> -1.4822803e+09 | AC16: =SUMIF(Budgeted_01jun!$U:$U,'SAP Working'!I16,Budgeted_01jun!$R:$R) -> 0 | AD16: =SUMIF('Actual_30 jun'!$I:$I,'SAP Working'!I16,'Actual_30 jun'!$K:$K) -> 0 | AE16: =SUMIF('Commited_30 Jun'!$H:$H,'SAP Working'!I16,'Commited_30 Jun'!$I:$I) -> 0 | AF16: =AE16+AD16 -> 0 | AG16: =AC16-AF16 -> 0
B17: Khavda- PSS 11 | C17: AGE27BL | D17: =D16+1 -> 16 | E17: 3 | F17: Installation Machinery | G17: H-5XA1-05-02 | H17: H-63A1-05-02 | I17: H-6074-05-02 | J17: H-63WD* | K17: =W17 -> 25876000 | L17: =X17 -> 0 | M17: =Y17 -> 7.3217179e+08 | N17: =M17+L17 -> 7.3217179e+08 | O17: =K17-N17 -> -7.0629579e+08 | Q17: =SUMIF(Budgeted_01jun!U:U,'SAP Working'!G17,Budgeted_01jun!R:R) -> 0 | R17: =SUMIF('Actual_30 jun'!I:I,'SAP Working'!G17,'Actual_30 jun'!K:K) -> 0 | S17: =SUMIF('Commited_30 Jun'!H:H,'SAP Working'!G17,'Commited_30 Jun'!I:I) -> 0 | T17: =S17+R17 -> 0 | U17: =Q17-T17 -> 0 | W17: =SUMIF(Budgeted_01jun!$U:$U,H17,Budgeted_01jun!$R:$R) -> 25876000 | X17: =SUMIF('Actual_30 jun'!$I:$I,'SAP Working'!H17,'Actual_30 jun'!$K:$K) -> 0 | Y17: =SUMIF('Commited_30 Jun'!$H:$H,'SAP Working'!H17,'Commited_30 Jun'!$I:$I) -> 7.3217179e+08 | Z17: =Y17+X17 -> 7.3217179e+08 | AA17: =W17-Z17 -> -7.0629579e+08 | AC17: =SUMIF(Budgeted_01jun!$U:$U,'SAP Working'!I17,Budgeted_01jun!$R:$R) -> 0 | AD17: =SUMIF('Actual_30 jun'!$I:$I,'SAP Working'!I17,'Actual_30 jun'!$K:$K) -> 0 | AE17: =SUMIF('Commited_30 Jun'!$H:$H,'SAP Working'!I17,'Commited_30 Jun'!$I:$I) -> 0 | AF17: =AE17+AD17 -> 0 | AG17: =AC17-AF17 -> 0
B18: Khavda- PSS 11 | C18: AGE27BL | D18: =D17+1 -> 17 | E18: 3 | F18: Installation Consultancy | G18: H-5XA1-05-03 | H18: H-63A1-05-03 | I18: H-6074-05-03 | J18: H-51I4* | K18: =W18 -> 24171264 | L18: =X18 -> 0 | M18: =Y18 -> 7.747063e+08 | N18: =M18+L18 -> 7.747063e+08 | O18: =K18-N18 -> -7.5053504e+08 | Q18: =SUMIF(Budgeted_01jun!U:U,'SAP Working'!G18,Budgeted_01jun!R:R) -> 0 | R18: =SUMIF('Actual_30 jun'!I:I,'SAP Working'!G18,'Actual_30 jun'!K:K) -> 0 | S18: =SUMIF('Commited_30 Jun'!H:H,'SAP Working'!G18,'Commited_30 Jun'!I:I) -> 0 | T18: =S18+R18 -> 0 | U18: =Q18-T18 -> 0 | W18: =SUMIF(Budgeted_01jun!$U:$U,H18,Budgeted_01jun!$R:$R) -> 24171264 | X18: =SUMIF('Actual_30 jun'!$I:$I,'SAP Working'!H18,'Actual_30 jun'!$K:$K) -> 0 | Y18: =SUMIF('Commited_30 Jun'!$H:$H,'SAP Working'!H18,'Commited_30 Jun'!$I:$I) -> 7.747063e+08 | Z18: =Y18+X18 -> 7.747063e+08 | AA18: =W18-Z18 -> -7.5053504e+08 | AC18: =SUMIF(Budgeted_01jun!$U:$U,'SAP Working'!I18,Budgeted_01jun!$R:$R) -> 0 | AD18: =SUMIF('Actual_30 jun'!$I:$I,'SAP Working'!I18,'Actual_30 jun'!$K:$K) -> 0 | AE18: =SUMIF('Commited_30 Jun'!$H:$H,'SAP Working'!I18,'Commited_30 Jun'!$I:$I) -> 0 | AF18: =AE18+AD18 -> 0 | AG18: =AC18-AF18 -> 0
A19: 5 | B19: Khavda- PSS 11 | C19: AGE27BL | D19: =D15+1 -> 15 | E19: 2 | F19: BOS Electrical Package | G19: H-5XA1-06 | H19: H-63A1-06 | I19: H-6074-06 | J19: H-5XWF* | K19: =Q19+W19 -> 1.3513175e+09 | L19: =R19+X19 -> 306189720 | M19: =S19+Y19 -> 3.5653834e+10 | N19: =M19+L19 -> 3.5960024e+10 | O19: =K19-N19 -> -3.4608706e+10 | Q19: =SUM(Q20:Q25) -> 1.2102294e+09 | R19: =SUM(R20:R25) -> 304788750 | S19: =SUM(S20:S25) -> 1.928424e+10 | T19: =SUM(T20:T25) -> 1.9589029e+10 | U19: =SUM(U20:U25) -> -1.83788e+10 | W19: =SUM(W20:W25) -> 1.4108808e+08 | X19: =SUM(X20:X25) -> 1400970 | Y19: =SUM(Y20:Y25) -> 1.6369594e+10 | Z19: =SUM(Z20:Z25) -> 1.6370995e+10 | AA19: =SUM(AA20:AA25) -> -1.6229907e+10 | AC19: =SUM(AC20:AC25) -> 0 | AD19: =SUM(AD20:AD25) -> 0 | AE19: =SUM(AE20:AE25) -> 0 | AF19: =SUM(AF20:AF25) -> 0 | AG19: =SUM(AG20:AG25) -> 0
A20: 5.1 | B20: Khavda- PSS 11 | C20: AGE27BL | D20: =D19+1 -> 16 | E20: 3 | F20: HT Panel Supply | G20: H-5XA1-06-01 | H20: H-63A1-06-01 | I20: H-6074-06-01 | J20: H-63WF* | K20: =Q20+W20 -> 143188450 | L20: =R20+X20 -> 81125700 | M20: =S20+Y20 -> 9.95638e+08 | N20: =M20+L20 -> 1.0767637e+09 | O20: =K20-N20 -> -9.3357525e+08 | Q20: =SUMIF(Budgeted_01jun!U:U,'SAP Working'!G20,Budgeted_01jun!R:R) -> 141118450 | R20: =SUMIF('Actual_30 jun'!I:I,'SAP Working'!G20,'Actual_30 jun'!K:K) -> 81125700 | S20: =SUMIF('Commited_30 Jun'!H:H,'SAP Working'!G20,'Commited_30 Jun'!I:I) -> 2.1886692e+08 | T20: =S20+R20 -> 2.9999262e+08 | U20: =Q20-T20 -> -1.5887417e+08 | W20: =SUMIF(Budgeted_01jun!$U:$U,H20,Budgeted_01jun!$R:$R) -> 2070000 | X20: =SUMIF('Actual_30 jun'!$I:$I,'SAP Working'!H20,'Actual_30 jun'!$K:$K) -> 0 | Y20: =SUMIF('Commited_30 Jun'!$H:$H,'SAP Working'!H20,'Commited_30 Jun'!$I:$I) -> 7.7677108e+08 | Z20: =Y20+X20 -> 7.7677108e+08 | AA20: =W20-Z20 -> -7.7470108e+08 | AC20: =SUMIF(Budgeted_01jun!$U:$U,'SAP Working'!I20,Budgeted_01jun!$R:$R) -> 0 | AD20: =SUMIF('Actual_30 jun'!$I:$I,'SAP Working'!I20,'Actual_30 jun'!$K:$K) -> 0 | AE20: =SUMIF('Commited_30 Jun'!$H:$H,'SAP Working'!I20,'Commited_30 Jun'!$I:$I) -> 0 | AF20: =AE20+AD20 -> 0 | AG20: =AC20-AF20 -> 0
A21: 5.2 | B21: Khavda- PSS 11 | C21: AGE27BL | D21: =D20+1 -> 17 | E21: 3 | F21: DC Cable & LT Cable Supply | G21: H-5XA1-06-02 | H21: H-63A1-06-02 | I21: H-6074-06-02 | J21: H-51N3* | K21: =Q21+W21 -> 5.133485e+08 | L21: =R21+X21 -> 64039680 | M21: =S21+Y21 -> 2.920841e+09 | N21: =M21+L21 -> 2.9848807e+09 | O21: =K21-N21 -> -2.4715321e+09 | Q21: =SUMIF(Budgeted_01jun!U:U,'SAP Working'!G21,Budgeted_01jun!R:R) -> 4.7082359e+08 | R21: =SUMIF('Actual_30 jun'!I:I,'SAP Working'!G21,'Actual_30 jun'!K:K) -> 64039680 | S21: =SUMIF('Commited_30 Jun'!H:H,'SAP Working'!G21,'Commited_30 Jun'!I:I) -> 2.1436569e+09 | T21: =S21+R21 -> 2.2076966e+09 | U21: =Q21-T21 -> -1.736873e+09 | W21: =SUMIF(Budgeted_01jun!$U:$U,H21,Budgeted_01jun!$R:$R) -> 42524910 | X21: =SUMIF('Actual_30 jun'!$I:$I,'SAP Working'!H21,'Actual_30 jun'!$K:$K) -> 0 | Y21: =SUMIF('Commited_30 Jun'!$H:$H,'SAP Working'!H21,'Commited_30 Jun'!$I:$I) -> 7.7718404e+08 | Z21: =Y21+X21 -> 7.7718404e+08 | AA21: =W21-Z21 -> -7.3465913e+08 | AC21: =SUMIF(Budgeted_01jun!$U:$U,'SAP Working'!I21,Budgeted_01jun!$R:$R) -> 0 | AD21: =SUMIF('Actual_30 jun'!$I:$I,'SAP Working'!I21,'Actual_30 jun'!$K:$K) -> 0 | AE21: =SUMIF('Commited_30 Jun'!$H:$H,'SAP Working'!I21,'Commited_30 Jun'!$I:$I) -> 0 | AF21: =AE21+AD21 -> 0 | AG21: =AC21-AF21 -> 0
A22: 5.3 | B22: Khavda- PSS 11 | C22: AGE27BL | D22: =D21+1 -> 18 | E22: 3 | F22: HT Cable Supply | G22: H-5XA1-06-03 | H22: H-63A1-06-03 | I22: H-6074-06-03 | K22: =Q22+W22 -> 182834244 | L22: =R22+X22 -> 53440350 | M22: =S22+Y22 -> 6.4503797e+08 | N22: =M22+L22 -> 6.9847832e+08 | O22: =K22-N22 -> -5.1564408e+08 | Q22: =SUMIF(Budgeted_01jun!U:U,'SAP Working'!G22,Budgeted_01jun!R:R) -> 174272175 | R22: =SUMIF('Actual_30 jun'!I:I,'SAP Working'!G22,'Actual_30 jun'!K:K) -> 53440350 | S22: =SUMIF('Commited_30 Jun'!H:H,'SAP Working'!G22,'Commited_30 Jun'!I:I) -> 0 | T22: =S22+R22 -> 53440350 | U22: =Q22-T22 -> 120831825 | W22: =SUMIF(Budgeted_01jun!$U:$U,H22,Budgeted_01jun!$R:$R) -> 8562069 | X22: =SUMIF('Actual_30 jun'!$I:$I,'SAP Working'!H22,'Actual_30 jun'!$K:$K) -> 0 | Y22: =SUMIF('Commited_30 Jun'!$H:$H,'SAP Working'!H22,'Commited_30 Jun'!$I:$I) -> 6.4503797e+08 | Z22: =Y22+X22 -> 6.4503797e+08 | AA22: =W22-Z22 -> -6.3647591e+08 | AC22: =SUMIF(Budgeted_01jun!$U:$U,'SAP Working'!I22,Budgeted_01jun!$R:$R) -> 0 | AD22: =SUMIF('Actual_30 jun'!$I:$I,'SAP Working'!I22,'Actual_30 jun'!$K:$K) -> 0 | AE22: =SUMIF('Commited_30 Jun'!$H:$H,'SAP Working'!I22,'Commited_30 Jun'!$I:$I) -> 0 | AF22: =AE22+AD22 -> 0 | AG22: =AC22-AF22 -> 0
A23: 5.5 | B23: Khavda- PSS 11 | C23: AGE27BL | D23: =D22+1 -> 19 | E23: 3 | F23: Electrical Erection | G23: H-5XA1-06-04 | H23: H-63A1-06-04 | I23: H-6074-06-04 | K23: =Q23+W23 -> 4.549755e+08 | L23: =R23+X23 -> 81224130 | M23: =S23+Y23 -> 1.730494e+10 | N23: =M23+L23 -> 1.7386164e+10 | O23: =K23-N23 -> -1.6931189e+10 | Q23: =SUMIF(Budgeted_01jun!U:U,'SAP Working'!G23,Budgeted_01jun!R:R) -> 3.879944e+08 | R23: =SUMIF('Actual_30 jun'!I:I,'SAP Working'!G23,'Actual_30 jun'!K:K) -> 81224130 | S23: =SUMIF('Commited_30 Jun'!H:H,'SAP Working'!G23,'Commited_30 Jun'!I:I) -> 1.5486693e+10 | T23: =S23+R23 -> 1.5567917e+10 | U23: =Q23-T23 -> -1.5179923e+10 | W23: =SUMIF(Budgeted_01jun!$U:$U,H23,Budgeted_01jun!$R:$R) -> 66981101 | X23: =SUMIF('Actual_30 jun'!$I:$I,'SAP Working'!H23,'Actual_30 jun'!$K:$K) -> 0 | Y23: =SUMIF('Commited_30 Jun'!$H:$H,'SAP Working'!H23,'Commited_30 Jun'!$I:$I) -> 1.8182472e+09 | Z23: =Y23+X23 -> 1.8182472e+09 | AA23: =W23-Z23 -> -1.7512661e+09 | AC23: =SUMIF(Budgeted_01jun!$U:$U,'SAP Working'!I23,Budgeted_01jun!$R:$R) -> 0 | AD23: =SUMIF('Actual_30 jun'!$I:$I,'SAP Working'!I23,'Actual_30 jun'!$K:$K) -> 0 | AE23: =SUMIF('Commited_30 Jun'!$H:$H,'SAP Working'!I23,'Commited_30 Jun'!$I:$I) -> 0 | AF23: =AE23+AD23 -> 0 | AG23: =AC23-AF23 -> 0
A24: 5.4 | B24: Khavda- PSS 11 | C24: AGE27BL | D24: =D23+1 -> 20 | E24: 3 | F24: SCADA & FO Cable Supply | G24: H-5XA1-06-05 | H24: H-63A1-06-05 | I24: H-6074-06-05 | J24: H-5XA1-06 | K24: =Q24+W24 -> 43116806 | L24: =R24+X24 -> 24958890 | M24: =S24+Y24 -> 2.2138595e+09 | N24: =M24+L24 -> 2.2388184e+09 | O24: =K24-N24 -> -2.1957016e+09 | Q24: =SUMIF(Budgeted_01jun!U:U,'SAP Working'!G24,Budgeted_01jun!R:R) -> 36020823 | R24: =SUMIF('Actual_30 jun'!I:I,'SAP Working'!G24,'Actual_30 jun'!K:K) -> 24958890 | S24: =SUMIF('Commited_30 Jun'!H:H,'SAP Working'!G24,'Commited_30 Jun'!I:I) -> 1.4350237e+09 | T24: =S24+R24 -> 1.4599826e+09 | U24: =Q24-T24 -> -1.4239617e+09 | W24: =SUMIF(Budgeted_01jun!$U:$U,H24,Budgeted_01jun!$R:$R) -> 7095983 | X24: =SUMIF('Actual_30 jun'!$I:$I,'SAP Working'!H24,'Actual_30 jun'!$K:$K) -> 0 | Y24: =SUMIF('Commited_30 Jun'!$H:$H,'SAP Working'!H24,'Commited_30 Jun'!$I:$I) -> 7.7883586e+08 | Z24: =Y24+X24 -> 7.7883586e+08 | AA24: =W24-Z24 -> -7.7173988e+08 | AC24: =SUMIF(Budgeted_01jun!$U:$U,'SAP Working'!I24,Budgeted_01jun!$R:$R) -> 0 | AD24: =SUMIF('Actual_30 jun'!$I:$I,'SAP Working'!I24,'Actual_30 jun'!$K:$K) -> 0 | AE24: =SUMIF('Commited_30 Jun'!$H:$H,'SAP Working'!I24,'Commited_30 Jun'!$I:$I) -> 0 | AF24: =AE24+AD24 -> 0 | AG24: =AC24-AF24 -> 0
B25: Khavda- PSS 11 | C25: AGE27BL | D25: =D24+1 -> 21 | E25: 3 | F25: Underground Cable Work | G25: H-5XA1-06-06 | H25: H-63A1-06-06 | I25: H-6074-06-06 | J25: H-63A1-06 | K25: =Q25+W25 -> 13854020 | L25: =R25+X25 -> 1400970 | M25: =S25+Y25 -> 1.1573517e+10 | N25: =M25+L25 -> 1.1574918e+10 | O25: =K25-N25 -> -1.1561064e+10 | Q25: =SUMIF(Budgeted_01jun!U:U,'SAP Working'!G25,Budgeted_01jun!R:R) -> 0 | R25: =SUMIF('Actual_30 jun'!I:I,'SAP Working'!G25,'Actual_30 jun'!K:K) -> 0 | S25: =SUMIF('Commited_30 Jun'!H:H,'SAP Working'!G25,'Commited_30 Jun'!I:I) -> 0 | T25: =S25+R25 -> 0 | U25: =Q25-T25 -> 0 | W25: =SUMIF(Budgeted_01jun!$U:$U,H25,Budgeted_01jun!$R:$R) -> 13854020 | X25: =SUMIF('Actual_30 jun'!$I:$I,'SAP Working'!H25,'Actual_30 jun'!$K:$K) -> 1400970 | Y25: =SUMIF('Commited_30 Jun'!$H:$H,'SAP Working'!H25,'Commited_30 Jun'!$I:$I) -> 1.1573517e+10 | Z25: =Y25+X25 -> 1.1574918e+10 | AA25: =W25-Z25 -> -1.1561064e+10 | AC25: =SUMIF(Budgeted_01jun!$U:$U,'SAP Working'!I25,Budgeted_01jun!$R:$R) -> 0 | AD25: =SUMIF('Actual_30 jun'!$I:$I,'SAP Working'!I25,'Actual_30 jun'!$K:$K) -> 0 | AE25: =SUMIF('Commited_30 Jun'!$H:$H,'SAP Working'!I25,'Commited_30 Jun'!$I:$I) -> 0 | AF25: =AE25+AD25 -> 0 | AG25: =AC25-AF25 -> 0
A26: 9 | B26: Khavda- PSS 11 | C26: AGE27BL | D26: =D25+1 -> 22 | E26: 2 | F26: Consultency Service | G26: H-5XA1-07 | H26: H-63A1-07 | I26: H-6074-07 | K26: =AC26 -> 27199501 | L26: =AD26 -> 11807520 | M26: =AE26 -> 9.8151489e+09 | N26: =M26+L26 -> 9.8269564e+09 | O26: =K26-N26 -> -9.7997569e+09 | Q26: =SUM(Q27:Q30) -> 0 | R26: =SUM(R27:R30) -> 0 | S26: =SUM(S27:S30) -> 0 | T26: =SUM(T27:T30) -> 0 | U26: =SUM(U27:U30) -> 0 | W26: =SUM(W27:W30) -> 0 | X26: =SUMIF('Actual_30 jun'!$I:$I,'SAP Working'!H26,'Actual_30 jun'!$K:$K) -> 0 | Y26: =SUMIF('Commited_30 Jun'!$H:$H,'SAP Working'!H26,'Commited_30 Jun'!$I:$I) -> 0 | Z26: =SUM(Z27:Z30) -> 0 | AA26: =SUM(AA27:AA30) -> 0 | AC26: =SUM(AC27:AC30) -> 27199501 | AD26: =SUM(AD27:AD30) -> 11807520 | AE26: =SUM(AE27:AE30) -> 9.8151489e+09 | AF26: =SUM(AF27:AF30) -> 9.8269564e+09 | AG26: =SUM(AG27:AG30) -> -9.7997569e+09
B27: Khavda- PSS 11 | C27: AGE27BL | D27: =D26+1 -> 23 | E27: 3 | F27: Engineering Consultancy | G27: H-5XA1-07-01 | H27: H-63A1-07-01 | I27: H-6074-07-01 | K27: =AC27 -> 17701000 | L27: =AD27 -> 4357950 | M27: =AE27 -> 2.9571811e+09 | N27: =M27+L27 -> 2.9615391e+09 | O27: =K27-N27 -> -2.9438381e+09 | Q27: =SUMIF(Budgeted_01jun!U:U,'SAP Working'!G27,Budgeted_01jun!R:R) -> 0 | R27: =SUMIF('Actual_30 jun'!I:I,'SAP Working'!G27,'Actual_30 jun'!K:K) -> 0 | S27: =SUMIF('Commited_30 Jun'!H:H,'SAP Working'!G27,'Commited_30 Jun'!I:I) -> 0 | T27: =S27+R27 -> 0 | U27: =Q27-T27 -> 0 | W27: =SUMIF(Budgeted_01jun!$U:$U,H27,Budgeted_01jun!$R:$R) -> 0 | X27: =SUMIF('Actual_30 jun'!$I:$I,'SAP Working'!H27,'Actual_30 jun'!$K:$K) -> 0 | Y27: =SUMIF('Commited_30 Jun'!$H:$H,'SAP Working'!H27,'Commited_30 Jun'!$I:$I) -> 0 | Z27: =Y27+X27 -> 0 | AA27: =W27-Z27 -> 0 | AC27: =SUMIF(Budgeted_01jun!$U:$U,'SAP Working'!I27,Budgeted_01jun!$R:$R) -> 17701000 | AD27: =SUMIF('Actual_30 jun'!$I:$I,'SAP Working'!I27,'Actual_30 jun'!$K:$K) -> 4357950 | AE27: =SUMIF('Commited_30 Jun'!$H:$H,'SAP Working'!I27,'Commited_30 Jun'!$I:$I) -> 2.9571811e+09 | AF27: =AE27+AD27 -> 2.9615391e+09 | AG27: =AC27-AF27 -> -2.9438381e+09
B28: Khavda- PSS 11 | C28: AGE27BL | D28: =D27+1 -> 24 | E28: 3 | F28: Grid Modelling | G28: H-5XA1-07-02 | H28: H-63A1-07-02 | I28: H-6074-07-02 | K28: =AC28 -> 5950000 | L28: =AD28 -> 2433720 | M28: =AE28 -> 6.7600971e+08 | N28: =M28+L28 -> 6.7844343e+08 | O28: =K28-N28 -> -6.7249343e+08 | Q28: =SUMIF(Budgeted_01jun!U:U,'SAP Working'!G28,Budgeted_01jun!R:R) -> 0 | R28: =SUMIF('Actual_30 jun'!I:I,'SAP Working'!G28,'Actual_30 jun'!K:K) -> 0 | S28: =SUMIF('Commited_30 Jun'!H:H,'SAP Working'!G28,'Commited_30 Jun'!I:I) -> 0 | T28: =S28+R28 -> 0 | U28: =Q28-T28 -> 0 | W28: =SUMIF(Budgeted_01jun!$U:$U,H28,Budgeted_01jun!$R:$R) -> 0 | X28: =SUMIF('Actual_30 jun'!$I:$I,'SAP Working'!H28,'Actual_30 jun'!$K:$K) -> 0 | Y28: =SUMIF('Commited_30 Jun'!$H:$H,'SAP Working'!H28,'Commited_30 Jun'!$I:$I) -> 0 | Z28: =Y28+X28 -> 0 | AA28: =W28-Z28 -> 0 | AC28: =SUMIF(Budgeted_01jun!$U:$U,'SAP Working'!I28,Budgeted_01jun!$R:$R) -> 5950000 | AD28: =SUMIF('Actual_30 jun'!$I:$I,'SAP Working'!I28,'Actual_30 jun'!$K:$K) -> 2433720 | AE28: =SUMIF('Commited_30 Jun'!$H:$H,'SAP Working'!I28,'Commited_30 Jun'!$I:$I) -> 6.7600971e+08 | AF28: =AE28+AD28 -> 6.7844343e+08 | AG28: =AC28-AF28 -> -6.7249343e+08
B29: Khavda- PSS 11 | C29: AGE27BL | D29: =D28+1 -> 25 | E29: 3 | F29: PIR Consultancy charges | G29: H-5XA1-07-03 | H29: H-63A1-07-03 | I29: H-6074-07-03 | K29: =AC29 -> 0 | L29: =AD29 -> 0 | M29: =AE29 -> 0 | N29: =M29+L29 -> 0 | O29: =K29-N29 -> 0 | Q29: =SUMIF(Budgeted_01jun!U:U,'SAP Working'!G29,Budgeted_01jun!R:R) -> 0 | R29: =SUMIF('Actual_30 jun'!I:I,'SAP Working'!G29,'Actual_30 jun'!K:K) -> 0 | S29: =SUMIF('Commited_30 Jun'!H:H,'SAP Working'!G29,'Commited_30 Jun'!I:I) -> 0 | T29: =S29+R29 -> 0 | U29: =Q29-T29 -> 0 | W29: =SUMIF(Budgeted_01jun!$U:$U,H29,Budgeted_01jun!$R:$R) -> 0 | X29: =SUMIF('Actual_30 jun'!$I:$I,'SAP Working'!H29,'Actual_30 jun'!$K:$K) -> 0 | Y29: =SUMIF('Commited_30 Jun'!$H:$H,'SAP Working'!H29,'Commited_30 Jun'!$I:$I) -> 0 | Z29: =Y29+X29 -> 0 | AA29: =W29-Z29 -> 0 | AC29: =SUMIF(Budgeted_01jun!$U:$U,'SAP Working'!I29,Budgeted_01jun!$R:$R) -> 0 | AD29: =SUMIF('Actual_30 jun'!$I:$I,'SAP Working'!I29,'Actual_30 jun'!$K:$K) -> 0 | AE29: =SUMIF('Commited_30 Jun'!$H:$H,'SAP Working'!I29,'Commited_30 Jun'!$I:$I) -> 0 | AF29: =AE29+AD29 -> 0 | AG29: =AC29-AF29 -> 0
B30: Khavda- PSS 11 | C30: AGE27BL | D30: =D29+1 -> 26 | E30: 3 | F30: Misc Consultency | G30: H-5XA1-07-04 | H30: H-63A1-07-04 | I30: H-6074-07-04 | K30: =AC30 -> 3548501 | L30: =AD30 -> 5015850 | M30: =AE30 -> 6.1819581e+09 | N30: =M30+L30 -> 6.1869739e+09 | O30: =K30-N30 -> -6.1834254e+09 | Q30: =SUMIF(Budgeted_01jun!U:U,'SAP Working'!G30,Budgeted_01jun!R:R) -> 0 | R30: =SUMIF('Actual_30 jun'!I:I,'SAP Working'!G30,'Actual_30 jun'!K:K) -> 0 | S30: =SUMIF('Commited_30 Jun'!H:H,'SAP Working'!G30,'Commited_30 Jun'!I:I) -> 0 | T30: =S30+R30 -> 0 | U30: =Q30-T30 -> 0 | W30: =SUMIF(Budgeted_01jun!$U:$U,H30,Budgeted_01jun!$R:$R) -> 0 | X30: =SUMIF('Actual_30 jun'!$I:$I,'SAP Working'!H30,'Actual_30 jun'!$K:$K) -> 0 | Y30: =SUMIF('Commited_30 Jun'!$H:$H,'SAP Working'!H30,'Commited_30 Jun'!$I:$I) -> 0 | Z30: =Y30+X30 -> 0 | AA30: =W30-Z30 -> 0 | AC30: =SUMIF(Budgeted_01jun!$U:$U,'SAP Working'!I30,Budgeted_01jun!$R:$R) -> 3548501 | AD30: =SUMIF('Actual_30 jun'!$I:$I,'SAP Working'!I30,'Actual_30 jun'!$K:$K) -> 5015850 | AE30: =SUMIF('Commited_30 Jun'!$H:$H,'SAP Working'!I30,'Commited_30 Jun'!$I:$I) -> 6.1819581e+09 | AF30: =AE30+AD30 -> 6.1869739e+09 | AG30: =AC30-AF30 -> -6.1834254e+09
A31: 7 | B31: Khavda- PSS 11 | C31: AGE27BL | D31: =D30+1 -> 27 | E31: 2 | F31: Civil Work | G31: H-5XA1-08 | H31: H-63A1-08 | I31: H-6074-08 | K31: =SUM(K32,K45,K48,K49,K50) -> 7.2567058e+08 | L31: =SUM(L32,L45,L48,L49,L50) -> 289872780 | M31: =SUM(M32,M45,M48,M49,M50) -> 2.7787014e+10 | N31: =M31+L31 -> 2.8076886e+10 | O31: =K31-N31 -> -2.7351216e+10 | Q31: =SUM(Q32,Q45,Q48,Q49,Q50) -> 0 | R31: =SUM(R32,R45,R48,R49,R50) -> 0 | S31: =SUM(S32,S45,S48,S49,S50) -> 0 | T31: =SUM(T32,T45,T48,T49,T50) -> 0 | U31: =SUM(U32,U45,U48,U49,U50) -> 0 | W31: =SUM(W32,W45,W48,W49,W50) -> 7.2567058e+08 | X31: =SUM(X32,X45,X48,X49,X50) -> 289872780 | Y31: =SUM(Y32,Y45,Y48,Y49,Y50) -> 2.7787014e+10 | Z31: =SUM(Z32,Z45,Z48,Z49,Z50) -> 2.8076886e+10 | AA31: =SUM(AA32,AA45,AA48,AA49,AA50) -> -2.7351216e+10 | AC31: =SUM(AC32,AC45,AC48,AC49,AC50) -> 0 | AD31: =SUM(AD32,AD45,AD48,AD49,AD50) -> 0 | AE31: =SUM(AE32,AE45,AE48,AE49,AE50) -> 0 | AF31: =SUM(AF32,AF45,AF48,AF49,AF50) -> 0 | AG31: =SUM(AG32,AG45,AG48,AG49,AG50) -> 0
A32: 7.1 | B32: Khavda- PSS 11 | C32: AGE27BL | D32: =D31+1 -> 28 | E32: 3 | F32: Equipment Foundation | G32: H-5XA1-08-01 | H32: H-63A1-08-01 | I32: H-6074-08-01 | K32: =W32 -> 6.8100968e+08 | L32: =X32 -> 289872780 | M32: =Y32 -> 2.5809778e+10 | N32: =M32+L32 -> 2.6099651e+10 | O32: =K32-N32 -> -2.5418641e+10 | Q32: =SUM(Q33,Q34,Q35,Q38,Q39,Q42) -> 0 | R32: =SUM(R33,R34,R35,R38,R39,R42) -> 0 | S32: =SUM(S33,S34,S35,S38,S39,S42) -> 0 | T32: =SUM(T33,T34,T35,T38,T39,T42) -> 0 | U32: =SUM(U33,U34,U35,U38,U39,U42) -> 0 | W32: =SUM(W33,W34,W35,W38,W39,W42) -> 6.8100968e+08 | X32: =SUM(X33,X34,X35,X38,X39,X42) -> 289872780 | Y32: =SUM(Y33,Y34,Y35,Y38,Y39,Y42) -> 2.5809778e+10 | Z32: =SUM(Z33,Z34,Z35,Z38,Z39,Z42) -> 2.6099651e+10 | AA32: =SUM(AA33,AA34,AA35,AA38,AA39,AA42) -> -2.5418641e+10 | AC32: =SUM(AC33,AC34,AC35,AC38,AC39,AC42) -> 0 | AD32: =SUM(AD33,AD34,AD35,AD38,AD39,AD42) -> 0 | AE32: =SUM(AE33,AE34,AE35,AE38,AE39,AE42) -> 0 | AF32: =SUM(AF33,AF34,AF35,AF38,AF39,AF42) -> 0 | AG32: =SUM(AG33,AG34,AG35,AG38,AG39,AG42) -> 0
B33: Khavda- PSS 11 | C33: AGE27BL | D33: =D32+1 -> 29 | E33: 4 | F33: Battery container | G33: H-5XA1-08-01-01 | H33: H-63A1-08-01-01 | I33: H-6074-08-01-01 | K33: =W33 -> 276817610 | L33: =X33 -> 48106770 | M33: =Y33 -> 3.3936761e+09 | N33: =M33+L33 -> 3.4417829e+09 | O33: =K33-N33 -> -3.1649653e+09 | Q33: =SUMIF(Budgeted_01jun!U:U,'SAP Working'!G33,Budgeted_01jun!R:R) -> 0 | R33: =SUMIF('Actual_30 jun'!I:I,'SAP Working'!G33,'Actual_30 jun'!K:K) -> 0 | S33: =SUMIF('Commited_30 Jun'!H:H,'SAP Working'!G33,'Commited_30 Jun'!I:I) -> 0 | T33: =S33+R33 -> 0 | U33: =Q33-T33 -> 0 | W33: =SUMIF(Budgeted_01jun!$U:$U,H33,Budgeted_01jun!$R:$R) -> 276817610 | X33: =SUMIF('Actual_30 jun'!$I:$I,'SAP Working'!H33,'Actual_30 jun'!$K:$K) -> 48106770 | Y33: =SUMIF('Commited_30 Jun'!$H:$H,'SAP Working'!H33,'Commited_30 Jun'!$I:$I) -> 3.3936761e+09 | Z33: =Y33+X33 -> 3.4417829e+09 | AA33: =W33-Z33 -> -3.1649653e+09 | AC33: =SUMIF(Budgeted_01jun!$U:$U,'SAP Working'!I33,Budgeted_01jun!$R:$R) -> 0 | AD33: =SUMIF('Actual_30 jun'!$I:$I,'SAP Working'!I33,'Actual_30 jun'!$K:$K) -> 0 | AE33: =SUMIF('Commited_30 Jun'!$H:$H,'SAP Working'!I33,'Commited_30 Jun'!$I:$I) -> 0 | AF33: =AE33+AD33 -> 0 | AG33: =AC33-AF33 -> 0
B34: Khavda- PSS 11 | C34: AGE27BL | D34: =D33+1 -> 30 | E34: 4 | F34: Transformer | G34: H-5XA1-08-01-02 | H34: H-63A1-08-01-02 | I34: H-6074-08-01-02 | K34: =W34 -> 86030908 | L34: =X34 -> 33083700 | M34: =Y34 -> 3.6187374e+09 | N34: =M34+L34 -> 3.6518211e+09 | O34: =K34-N34 -> -3.5657902e+09 | Q34: =SUMIF(Budgeted_01jun!U:U,'SAP Working'!G34,Budgeted_01jun!R:R) -> 0 | R34: =SUMIF('Actual_30 jun'!I:I,'SAP Working'!G34,'Actual_30 jun'!K:K) -> 0 | S34: =SUMIF('Commited_30 Jun'!H:H,'SAP Working'!G34,'Commited_30 Jun'!I:I) -> 0 | T34: =S34+R34 -> 0 | U34: =Q34-T34 -> 0 | W34: =SUMIF(Budgeted_01jun!$U:$U,H34,Budgeted_01jun!$R:$R) -> 86030908 | X34: =SUMIF('Actual_30 jun'!$I:$I,'SAP Working'!H34,'Actual_30 jun'!$K:$K) -> 33083700 | Y34: =SUMIF('Commited_30 Jun'!$H:$H,'SAP Working'!H34,'Commited_30 Jun'!$I:$I) -> 3.6187374e+09 | Z34: =Y34+X34 -> 3.6518211e+09 | AA34: =W34-Z34 -> -3.5657902e+09 | AC34: =SUMIF(Budgeted_01jun!$U:$U,'SAP Working'!I34,Budgeted_01jun!$R:$R) -> 0 | AD34: =SUMIF('Actual_30 jun'!$I:$I,'SAP Working'!I34,'Actual_30 jun'!$K:$K) -> 0 | AE34: =SUMIF('Commited_30 Jun'!$H:$H,'SAP Working'!I34,'Commited_30 Jun'!$I:$I) -> 0 | AF34: =AE34+AD34 -> 0 | AG34: =AC34-AF34 -> 0
B35: Khavda- PSS 11 | C35: AGE27BL | D35: =D34+1 -> 31 | E35: 4 | F35: PCS & Panel Foundation | G35: H-5XA1-08-01-03 | H35: H-63A1-08-01-03 | I35: H-6074-08-01-03 | K35: =W35 -> 2.4241537e+08 | L35: =X35 -> 148912860 | M35: =Y35 -> 7.339062e+09 | N35: =M35+L35 -> 7.4879749e+09 | O35: =K35-N35 -> -7.2455595e+09 | Q35: =SUM(Q36:Q37) -> 0 | R35: =SUM(R36:R37) -> 0 | S35: =SUM(S36:S37) -> 0 | T35: =SUM(T36:T37) -> 0 | U35: =SUM(U36:U37) -> 0 | W35: =SUM(W36:W37) -> 2.4241537e+08 | X35: =SUM(X36:X37) -> 148912860 | Y35: =SUM(Y36:Y37) -> 7.339062e+09 | Z35: =SUM(Z36:Z37) -> 7.4879749e+09 | AA35: =SUM(AA36:AA37) -> -7.2455595e+09 | AC35: =SUM(AC36:AC37) -> 0 | AD35: =SUM(AD36:AD37) -> 0 | AE35: =SUM(AE36:AE37) -> 0 | AF35: =SUM(AF36:AF37) -> 0 | AG35: =SUM(AG36:AG37) -> 0
B36: Khavda- PSS 11 | C36: AGE27BL | D36: =D35+1 -> 32 | E36: 5 | F36: Civil of PCS | G36: H-5XA1-08-01-03-01 | H36: H-63A1-08-01-03-01 | I36: H-6074-08-01-03-01 | K36: =W36 -> 169389169 | L36: =X36 -> 18759330 | M36: =Y36 -> 3.0121043e+09 | N36: =M36+L36 -> 3.0308637e+09 | O36: =K36-N36 -> -2.8614745e+09 | Q36: =SUMIF(Budgeted_01jun!U:U,'SAP Working'!G36,Budgeted_01jun!R:R) -> 0 | R36: =SUMIF('Actual_30 jun'!I:I,'SAP Working'!G36,'Actual_30 jun'!K:K) -> 0 | S36: =SUMIF('Commited_30 Jun'!H:H,'SAP Working'!G36,'Commited_30 Jun'!I:I) -> 0 | T36: =S36+R36 -> 0 | U36: =Q36-T36 -> 0 | W36: =SUMIF(Budgeted_01jun!$U:$U,H36,Budgeted_01jun!$R:$R) -> 169389169 | X36: =SUMIF('Actual_30 jun'!$I:$I,'SAP Working'!H36,'Actual_30 jun'!$K:$K) -> 18759330 | Y36: =SUMIF('Commited_30 Jun'!$H:$H,'SAP Working'!H36,'Commited_30 Jun'!$I:$I) -> 3.0121043e+09 | Z36: =Y36+X36 -> 3.0308637e+09 | AA36: =W36-Z36 -> -2.8614745e+09 | AC36: =SUMIF(Budgeted_01jun!$U:$U,'SAP Working'!I36,Budgeted_01jun!$R:$R) -> 0 | AD36: =SUMIF('Actual_30 jun'!$I:$I,'SAP Working'!I36,'Actual_30 jun'!$K:$K) -> 0 | AE36: =SUMIF('Commited_30 Jun'!$H:$H,'SAP Working'!I36,'Commited_30 Jun'!$I:$I) -> 0 | AF36: =AE36+AD36 -> 0 | AG36: =AC36-AF36 -> 0
B37: Khavda- PSS 11 | C37: AGE27BL | D37: =D36+1 -> 33 | E37: 5 | F37: Structure of PCS | G37: H-5XA1-08-01-03-02 | H37: H-63A1-08-01-03-02 | I37: H-6074-08-01-03-02 | K37: =W37 -> 73026206 | L37: =X37 -> 130153530 | M37: =Y37 -> 4.3269577e+09 | N37: =M37+L37 -> 4.4571112e+09 | O37: =K37-N37 -> -4.384085e+09 | Q37: =SUMIF(Budgeted_01jun!U:U,'SAP Working'!G37,Budgeted_01jun!R:R) -> 0 | R37: =SUMIF('Actual_30 jun'!I:I,'SAP Working'!G37,'Actual_30 jun'!K:K) -> 0 | S37: =SUMIF('Commited_30 Jun'!H:H,'SAP Working'!G37,'Commited_30 Jun'!I:I) -> 0 | T37: =S37+R37 -> 0 | U37: =Q37-T37 -> 0 | W37: =SUMIF(Budgeted_01jun!$U:$U,H37,Budgeted_01jun!$R:$R) -> 73026206 | X37: =SUMIF('Actual_30 jun'!$I:$I,'SAP Working'!H37,'Actual_30 jun'!$K:$K) -> 130153530 | Y37: =SUMIF('Commited_30 Jun'!$H:$H,'SAP Working'!H37,'Commited_30 Jun'!$I:$I) -> 4.3269577e+09 | Z37: =Y37+X37 -> 4.4571112e+09 | AA37: =W37-Z37 -> -4.384085e+09 | AC37: =SUMIF(Budgeted_01jun!$U:$U,'SAP Working'!I37,Budgeted_01jun!$R:$R) -> 0 | AD37: =SUMIF('Actual_30 jun'!$I:$I,'SAP Working'!I37,'Actual_30 jun'!$K:$K) -> 0 | AE37: =SUMIF('Commited_30 Jun'!$H:$H,'SAP Working'!I37,'Commited_30 Jun'!$I:$I) -> 0 | AF37: =AE37+AD37 -> 0 | AG37: =AC37-AF37 -> 0
B38: Khavda- PSS 11 | C38: AGE27BL | D38: =D37+1 -> 34 | E38: 4 | F38: CSS | G38: H-5XA1-08-01-04 | H38: H-63A1-08-01-04 | I38: H-6074-08-01-04 | K38: =W38 -> 15807100 | L38: =X38 -> 11314350 | M38: =Y38 -> 1.3284809e+09 | N38: =M38+L38 -> 1.3397952e+09 | O38: =K38-N38 -> -1.3239881e+09 | Q38: =SUMIF(Budgeted_01jun!U:U,'SAP Working'!G38,Budgeted_01jun!R:R) -> 0 | R38: =SUMIF('Actual_30 jun'!I:I,'SAP Working'!G38,'Actual_30 jun'!K:K) -> 0 | S38: =SUMIF('Commited_30 Jun'!H:H,'SAP Working'!G38,'Commited_30 Jun'!I:I) -> 0 | T38: =S38+R38 -> 0 | U38: =Q38-T38 -> 0 | W38: =SUMIF(Budgeted_01jun!$U:$U,H38,Budgeted_01jun!$R:$R) -> 15807100 | X38: =SUMIF('Actual_30 jun'!$I:$I,'SAP Working'!H38,'Actual_30 jun'!$K:$K) -> 11314350 | Y38: =SUMIF('Commited_30 Jun'!$H:$H,'SAP Working'!H38,'Commited_30 Jun'!$I:$I) -> 1.3284809e+09 | Z38: =Y38+X38 -> 1.3397952e+09 | AA38: =W38-Z38 -> -1.3239881e+09 | AC38: =SUMIF(Budgeted_01jun!$U:$U,'SAP Working'!I38,Budgeted_01jun!$R:$R) -> 0 | AD38: =SUMIF('Actual_30 jun'!$I:$I,'SAP Working'!I38,'Actual_30 jun'!$K:$K) -> 0 | AE38: =SUMIF('Commited_30 Jun'!$H:$H,'SAP Working'!I38,'Commited_30 Jun'!$I:$I) -> 0 | AF38: =AE38+AD38 -> 0 | AG38: =AC38-AF38 -> 0
B39: Khavda- PSS 11 | C39: AGE27BL | D39: =D38+1 -> 35 | E39: 4 | F39: Control Room | G39: H-5XA1-08-01-05 | H39: H-63A1-08-01-05 | I39: H-6074-08-01-05 | K39: =W39 -> 35931120 | L39: =X39 -> 15327030 | M39: =Y39 -> 2.9324038e+09 | N39: =M39+L39 -> 2.9477308e+09 | O39: =K39-N39 -> -2.9117997e+09 | Q39: =SUM(Q40:Q41) -> 0 | R39: =SUM(R40:R41) -> 0 | S39: =SUM(S40:S41) -> 0 | T39: =SUM(T40:T41) -> 0 | U39: =SUM(U40:U41) -> 0 | W39: =SUM(W40:W41) -> 35931120 | X39: =SUM(X40:X41) -> 15327030 | Y39: =SUM(Y40:Y41) -> 2.9324038e+09 | Z39: =SUM(Z40:Z41) -> 2.9477308e+09 | AA39: =SUM(AA40:AA41) -> -2.9117997e+09 | AC39: =SUM(AC40:AC41) -> 0 | AD39: =SUM(AD40:AD41) -> 0 | AE39: =SUM(AE40:AE41) -> 0 | AF39: =SUM(AF40:AF41) -> 0 | AG39: =SUM(AG40:AG41) -> 0
B40: Khavda- PSS 11 | C40: AGE27BL | D40: =D39+1 -> 36 | E40: 5 | F40: Civil of MCR | G40: H-5XA1-08-01-05-01 | H40: H-63A1-08-01-05-01 | I40: H-6074-08-01-05-01 | K40: =W40 -> 11550095 | L40: =X40 -> 14154540 | M40: =Y40 -> 2.0115109e+09 | N40: =M40+L40 -> 2.0256654e+09 | O40: =K40-N40 -> -2.0141153e+09 | Q40: =SUMIF(Budgeted_01jun!U:U,'SAP Working'!G40,Budgeted_01jun!R:R) -> 0 | R40: =SUMIF('Actual_30 jun'!I:I,'SAP Working'!G40,'Actual_30 jun'!K:K) -> 0 | S40: =SUMIF('Commited_30 Jun'!H:H,'SAP Working'!G40,'Commited_30 Jun'!I:I) -> 0 | T40: =S40+R40 -> 0 | U40: =Q40-T40 -> 0 | W40: =SUMIF(Budgeted_01jun!$U:$U,H40,Budgeted_01jun!$R:$R) -> 11550095 | X40: =SUMIF('Actual_30 jun'!$I:$I,'SAP Working'!H40,'Actual_30 jun'!$K:$K) -> 14154540 | Y40: =SUMIF('Commited_30 Jun'!$H:$H,'SAP Working'!H40,'Commited_30 Jun'!$I:$I) -> 2.0115109e+09 | Z40: =Y40+X40 -> 2.0256654e+09 | AA40: =W40-Z40 -> -2.0141153e+09 | AC40: =SUMIF(Budgeted_01jun!$U:$U,'SAP Working'!I40,Budgeted_01jun!$R:$R) -> 0 | AD40: =SUMIF('Actual_30 jun'!$I:$I,'SAP Working'!I40,'Actual_30 jun'!$K:$K) -> 0 | AE40: =SUMIF('Commited_30 Jun'!$H:$H,'SAP Working'!I40,'Commited_30 Jun'!$I:$I) -> 0 | AF40: =AE40+AD40 -> 0 | AG40: =AC40-AF40 -> 0
B41: Khavda- PSS 11 | C41: AGE27BL | D41: =D40+1 -> 37 | E41: 5 | F41: Structure of MCR | G41: H-5XA1-08-01-05-02 | H41: H-63A1-08-01-05-02 | I41: H-6074-08-01-05-02 | K41: =W41 -> 24381025 | L41: =X41 -> 1172490 | M41: =Y41 -> 9.2089288e+08 | N41: =M41+L41 -> 9.2206537e+08 | O41: =K41-N41 -> -8.9768435e+08 | Q41: =SUMIF(Budgeted_01jun!U:U,'SAP Working'!G41,Budgeted_01jun!R:R) -> 0 | R41: =SUMIF('Actual_30 jun'!I:I,'SAP Working'!G41,'Actual_30 jun'!K:K) -> 0 | S41: =SUMIF('Commited_30 Jun'!H:H,'SAP Working'!G41,'Commited_30 Jun'!I:I) -> 0 | T41: =S41+R41 -> 0 | U41: =Q41-T41 -> 0 | W41: =SUMIF(Budgeted_01jun!$U:$U,H41,Budgeted_01jun!$R:$R) -> 24381025 | X41: =SUMIF('Actual_30 jun'!$I:$I,'SAP Working'!H41,'Actual_30 jun'!$K:$K) -> 1172490 | Y41: =SUMIF('Commited_30 Jun'!$H:$H,'SAP Working'!H41,'Commited_30 Jun'!$I:$I) -> 9.2089288e+08 | Z41: =Y41+X41 -> 9.2206537e+08 | AA41: =W41-Z41 -> -8.9768435e+08 | AC41: =SUMIF(Budgeted_01jun!$U:$U,'SAP Working'!I41,Budgeted_01jun!$R:$R) -> 0 | AD41: =SUMIF('Actual_30 jun'!$I:$I,'SAP Working'!I41,'Actual_30 jun'!$K:$K) -> 0 | AE41: =SUMIF('Commited_30 Jun'!$H:$H,'SAP Working'!I41,'Commited_30 Jun'!$I:$I) -> 0 | AF41: =AE41+AD41 -> 0 | AG41: =AC41-AF41 -> 0
B42: Khavda- PSS 11 | C42: AGE27BL | D42: =D41+1 -> 38 | E42: 4 | F42: SGR Panel | G42: H-5XA1-08-01-06 | H42: H-63A1-08-01-06 | I42: H-6074-08-01-06 | K42: =W42 -> 24007572 | L42: =X42 -> 33128070 | M42: =Y42 -> 7.197418e+09 | N42: =M42+L42 -> 7.230546e+09 | O42: =K42-N42 -> -7.2065385e+09 | Q42: =SUM(Q43:Q44) -> 0 | R42: =SUM(R43:R44) -> 0 | S42: =SUM(S43:S44) -> 0 | T42: =SUM(T43:T44) -> 0 | U42: =SUM(U43:U44) -> 0 | W42: =SUM(W43:W44) -> 24007572 | X42: =SUM(X43:X44) -> 33128070 | Y42: =SUM(Y43:Y44) -> 7.197418e+09 | Z42: =SUM(Z43:Z44) -> 7.230546e+09 | AA42: =SUM(AA43:AA44) -> -7206538465 | AC42: =SUM(AC43:AC44) -> 0 | AD42: =SUM(AD43:AD44) -> 0 | AE42: =SUM(AE43:AE44) -> 0 | AF42: =SUM(AF43:AF44) -> 0 | AG42: =SUM(AG43:AG44) -> 0
B43: Khavda- PSS 11 | C43: AGE27BL | D43: =D42+1 -> 39 | E43: 5 | F43: Civil of SGR | G43: H-5XA1-08-01-06-01 | H43: H-63A1-08-01-06-01 | I43: H-6074-08-01-06-01 | K43: =W43 -> 17260070 | L43: =X43 -> 17789820 | M43: =Y43 -> 2.5372044e+09 | N43: =M43+L43 -> 2.5549942e+09 | O43: =K43-N43 -> -2.5377342e+09 | Q43: =SUMIF(Budgeted_01jun!U:U,'SAP Working'!G43,Budgeted_01jun!R:R) -> 0 | R43: =SUMIF('Actual_30 jun'!I:I,'SAP Working'!G43,'Actual_30 jun'!K:K) -> 0 | S43: =SUMIF('Commited_30 Jun'!H:H,'SAP Working'!G43,'Commited_30 Jun'!I:I) -> 0 | T43: =S43+R43 -> 0 | U43: =Q43-T43 -> 0 | W43: =SUMIF(Budgeted_01jun!$U:$U,H43,Budgeted_01jun!$R:$R) -> 17260070 | X43: =SUMIF('Actual_30 jun'!$I:$I,'SAP Working'!H43,'Actual_30 jun'!$K:$K) -> 17789820 | Y43: =SUMIF('Commited_30 Jun'!$H:$H,'SAP Working'!H43,'Commited_30 Jun'!$I:$I) -> 2.5372044e+09 | Z43: =Y43+X43 -> 2.5549942e+09 | AA43: =W43-Z43 -> -2.5377342e+09 | AC43: =SUMIF(Budgeted_01jun!$U:$U,'SAP Working'!I43,Budgeted_01jun!$R:$R) -> 0 | AD43: =SUMIF('Actual_30 jun'!$I:$I,'SAP Working'!I43,'Actual_30 jun'!$K:$K) -> 0 | AE43: =SUMIF('Commited_30 Jun'!$H:$H,'SAP Working'!I43,'Commited_30 Jun'!$I:$I) -> 0 | AF43: =AE43+AD43 -> 0 | AG43: =AC43-AF43 -> 0
B44: Khavda- PSS 11 | C44: AGE27BL | D44: =D43+1 -> 40 | E44: 5 | F44: Structure of SGR | G44: H-5XA1-08-01-06-02 | H44: H-63A1-08-01-06-02 | I44: H-6074-08-01-06-02 | K44: =W44 -> 6747502 | L44: =X44 -> 15338250 | M44: =Y44 -> 4.6602135e+09 | N44: =M44+L44 -> 4.6755518e+09 | O44: =K44-N44 -> -4.6688043e+09 | Q44: =SUMIF(Budgeted_01jun!U:U,'SAP Working'!G44,Budgeted_01jun!R:R) -> 0 | R44: =SUMIF('Actual_30 jun'!I:I,'SAP Working'!G44,'Actual_30 jun'!K:K) -> 0 | S44: =SUMIF('Commited_30 Jun'!H:H,'SAP Working'!G44,'Commited_30 Jun'!I:I) -> 0 | T44: =S44+R44 -> 0 | U44: =Q44-T44 -> 0 | W44: =SUMIF(Budgeted_01jun!$U:$U,H44,Budgeted_01jun!$R:$R) -> 6747502 | X44: =SUMIF('Actual_30 jun'!$I:$I,'SAP Working'!H44,'Actual_30 jun'!$K:$K) -> 15338250 | Y44: =SUMIF('Commited_30 Jun'!$H:$H,'SAP Working'!H44,'Commited_30 Jun'!$I:$I) -> 4.6602135e+09 | Z44: =Y44+X44 -> 4.6755518e+09 | AA44: =W44-Z44 -> -4.6688043e+09 | AC44: =SUMIF(Budgeted_01jun!$U:$U,'SAP Working'!I44,Budgeted_01jun!$R:$R) -> 0 | AD44: =SUMIF('Actual_30 jun'!$I:$I,'SAP Working'!I44,'Actual_30 jun'!$K:$K) -> 0 | AE44: =SUMIF('Commited_30 Jun'!$H:$H,'SAP Working'!I44,'Commited_30 Jun'!$I:$I) -> 0 | AF44: =AE44+AD44 -> 0 | AG44: =AC44-AF44 -> 0
B45: Khavda- PSS 11 | C45: AGE27BL | D45: =D44+1 -> 41 | E45: 3 | F45: Drainage System | G45: H-5XA1-08-02 | H45: H-63A1-08-02 | I45: H-6074-08-02 | K45: =W45 -> 4652800 | L45: =X45 -> 0 | M45: =Y45 -> 0 | N45: =M45+L45 -> 0 | O45: =K45-N45 -> 4652800 | Q45: =SUM(Q46:Q47) -> 0 | R45: =SUM(R46:R47) -> 0 | S45: =SUM(S46:S47) -> 0 | T45: =SUM(T46:T47) -> 0 | U45: =SUM(U46:U47) -> 0 | W45: =SUM(W46:W47) -> 4652800 | X45: =SUM(X46:X47) -> 0 | Y45: =SUM(Y46:Y47) -> 0 | Z45: =SUM(Z46:Z47) -> 0 | AA45: =SUM(AA46:AA47) -> 4652800 | AC45: =SUM(AC46:AC47) -> 0 | AD45: =SUM(AD46:AD47) -> 0 | AE45: =SUM(AE46:AE47) -> 0 | AF45: =SUM(AF46:AF47) -> 0 | AG45: =SUM(AG46:AG47) -> 0
B46: Khavda- PSS 11 | C46: AGE27BL | D46: =D45+1 -> 42 | E46: 4 | F46: Bund | G46: H-5XA1-08-02-01 | H46: H-63A1-08-02-01 | I46: H-6074-08-02-01 | K46: =W46 -> 1864700 | L46: =X46 -> 0 | M46: =Y46 -> 0 | N46: =M46+L46 -> 0 | O46: =K46-N46 -> 1864700 | Q46: =SUMIF(Budgeted_01jun!U:U,'SAP Working'!G46,Budgeted_01jun!R:R) -> 0 | R46: =SUMIF('Actual_30 jun'!I:I,'SAP Working'!G46,'Actual_30 jun'!K:K) -> 0 | S46: =SUMIF('Commited_30 Jun'!H:H,'SAP Working'!G46,'Commited_30 Jun'!I:I) -> 0 | T46: =S46+R46 -> 0 | U46: =Q46-T46 -> 0 | W46: =SUMIF(Budgeted_01jun!$U:$U,H46,Budgeted_01jun!$R:$R) -> 1864700 | X46: =SUMIF('Actual_30 jun'!$I:$I,'SAP Working'!H46,'Actual_30 jun'!$K:$K) -> 0 | Y46: =SUMIF('Commited_30 Jun'!$H:$H,'SAP Working'!H46,'Commited_30 Jun'!$I:$I) -> 0 | Z46: =Y46+X46 -> 0 | AA46: =W46-Z46 -> 1864700 | AC46: =SUMIF(Budgeted_01jun!$U:$U,'SAP Working'!I46,Budgeted_01jun!$R:$R) -> 0 | AD46: =SUMIF('Actual_30 jun'!$I:$I,'SAP Working'!I46,'Actual_30 jun'!$K:$K) -> 0 | AE46: =SUMIF('Commited_30 Jun'!$H:$H,'SAP Working'!I46,'Commited_30 Jun'!$I:$I) -> 0 | AF46: =AE46+AD46 -> 0 | AG46: =AC46-AF46 -> 0
B47: Khavda- PSS 11 | C47: AGE27BL | D47: =D46+1 -> 43 | E47: 4 | F47: Earth work | G47: H-5XA1-08-02-02 | H47: H-63A1-08-02-02 | I47: H-6074-08-02-02 | K47: =W47 -> 2788100 | L47: =X47 -> 0 | M47: =Y47 -> 0 | N47: =M47+L47 -> 0 | O47: =K47-N47 -> 2788100 | Q47: =SUMIF(Budgeted_01jun!U:U,'SAP Working'!G47,Budgeted_01jun!R:R) -> 0 | R47: =SUMIF('Actual_30 jun'!I:I,'SAP Working'!G47,'Actual_30 jun'!K:K) -> 0 | S47: =SUMIF('Commited_30 Jun'!H:H,'SAP Working'!G47,'Commited_30 Jun'!I:I) -> 0 | T47: =S47+R47 -> 0 | U47: =Q47-T47 -> 0 | W47: =SUMIF(Budgeted_01jun!$U:$U,H47,Budgeted_01jun!$R:$R) -> 2788100 | X47: =SUMIF('Actual_30 jun'!$I:$I,'SAP Working'!H47,'Actual_30 jun'!$K:$K) -> 0 | Y47: =SUMIF('Commited_30 Jun'!$H:$H,'SAP Working'!H47,'Commited_30 Jun'!$I:$I) -> 0 | Z47: =Y47+X47 -> 0 | AA47: =W47-Z47 -> 2788100 | AC47: =SUMIF(Budgeted_01jun!$U:$U,'SAP Working'!I47,Budgeted_01jun!$R:$R) -> 0 | AD47: =SUMIF('Actual_30 jun'!$I:$I,'SAP Working'!I47,'Actual_30 jun'!$K:$K) -> 0 | AE47: =SUMIF('Commited_30 Jun'!$H:$H,'SAP Working'!I47,'Commited_30 Jun'!$I:$I) -> 0 | AF47: =AE47+AD47 -> 0 | AG47: =AC47-AF47 -> 0
B48: Khavda- PSS 11 | C48: AGE27BL | D48: =D47+1 -> 44 | E48: 3 | F48: Roads | G48: H-5XA1-08-03 | H48: H-63A1-08-03 | I48: H-6074-08-03 | K48: =W48 -> 28533000 | L48: =X48 -> 0 | M48: =Y48 -> 1.3904244e+09 | N48: =M48+L48 -> 1.3904244e+09 | O48: =K48-N48 -> -1.3618914e+09 | Q48: =SUMIF(Budgeted_01jun!U:U,'SAP Working'!G48,Budgeted_01jun!R:R) -> 0 | R48: =SUMIF('Actual_30 jun'!I:I,'SAP Working'!G48,'Actual_30 jun'!K:K) -> 0 | S48: =SUMIF('Commited_30 Jun'!H:H,'SAP Working'!G48,'Commited_30 Jun'!I:I) -> 0 | T48: =S48+R48 -> 0 | U48: =Q48-T48 -> 0 | W48: =SUMIF(Budgeted_01jun!$U:$U,H48,Budgeted_01jun!$R:$R) -> 28533000 | X48: =SUMIF('Actual_30 jun'!$I:$I,'SAP Working'!H48,'Actual_30 jun'!$K:$K) -> 0 | Y48: =SUMIF('Commited_30 Jun'!$H:$H,'SAP Working'!H48,'Commited_30 Jun'!$I:$I) -> 1.3904244e+09 | Z48: =Y48+X48 -> 1.3904244e+09 | AA48: =W48-Z48 -> -1.3618914e+09 | AC48: =SUMIF(Budgeted_01jun!$U:$U,'SAP Working'!I48,Budgeted_01jun!$R:$R) -> 0 | AD48: =SUMIF('Actual_30 jun'!$I:$I,'SAP Working'!I48,'Actual_30 jun'!$K:$K) -> 0 | AE48: =SUMIF('Commited_30 Jun'!$H:$H,'SAP Working'!I48,'Commited_30 Jun'!$I:$I) -> 0 | AF48: =AE48+AD48 -> 0 | AG48: =AC48-AF48 -> 0
B49: Khavda- PSS 11 | C49: AGE27BL | D49: =D48+1 -> 45 | E49: 3 | F49: Area Grading | G49: H-5XA1-08-04 | H49: H-63A1-08-04 | I49: H-6074-08-04 | K49: =W49 -> 0 | L49: =X49 -> 0 | M49: =Y49 -> 0 | N49: =M49+L49 -> 0 | O49: =K49-N49 -> 0 | Q49: =SUMIF(Budgeted_01jun!U:U,'SAP Working'!G49,Budgeted_01jun!R:R) -> 0 | R49: =SUMIF('Actual_30 jun'!I:I,'SAP Working'!G49,'Actual_30 jun'!K:K) -> 0 | S49: =SUMIF('Commited_30 Jun'!H:H,'SAP Working'!G49,'Commited_30 Jun'!I:I) -> 0 | T49: =S49+R49 -> 0 | U49: =Q49-T49 -> 0 | W49: =SUMIF(Budgeted_01jun!$U:$U,H49,Budgeted_01jun!$R:$R) -> 0 | X49: =SUMIF('Actual_30 jun'!$I:$I,'SAP Working'!H49,'Actual_30 jun'!$K:$K) -> 0 | Y49: =SUMIF('Commited_30 Jun'!$H:$H,'SAP Working'!H49,'Commited_30 Jun'!$I:$I) -> 0 | Z49: =Y49+X49 -> 0 | AA49: =W49-Z49 -> 0 | AC49: =SUMIF(Budgeted_01jun!$U:$U,'SAP Working'!I49,Budgeted_01jun!$R:$R) -> 0 | AD49: =SUMIF('Actual_30 jun'!$I:$I,'SAP Working'!I49,'Actual_30 jun'!$K:$K) -> 0 | AE49: =SUMIF('Commited_30 Jun'!$H:$H,'SAP Working'!I49,'Commited_30 Jun'!$I:$I) -> 0 | AF49: =AE49+AD49 -> 0 | AG49: =AC49-AF49 -> 0
B50: Khavda- PSS 11 | C50: AGE27BL | D50: =D49+1 -> 46 | E50: 3 | F50: Boundry wall and Fencing | G50: H-5XA1-08-05 | H50: H-63A1-08-05 | I50: H-6074-08-05 | K50: =W50 -> 11475100 | L50: =X50 -> 0 | M50: =Y50 -> 5.8681112e+08 | N50: =M50+L50 -> 5.8681112e+08 | O50: =K50-N50 -> -5.7533602e+08 | Q50: =SUMIF(Budgeted_01jun!U:U,'SAP Working'!G50,Budgeted_01jun!R:R) -> 0 | R50: =SUMIF('Actual_30 jun'!I:I,'SAP Working'!G50,'Actual_30 jun'!K:K) -> 0 | S50: =SUMIF('Commited_30 Jun'!H:H,'SAP Working'!G50,'Commited_30 Jun'!I:I) -> 0 | T50: =S50+R50 -> 0 | U50: =Q50-T50 -> 0 | W50: =SUMIF(Budgeted_01jun!$U:$U,H50,Budgeted_01jun!$R:$R) -> 11475100 | X50: =SUMIF('Actual_30 jun'!$I:$I,'SAP Working'!H50,'Actual_30 jun'!$K:$K) -> 0 | Y50: =SUMIF('Commited_30 Jun'!$H:$H,'SAP Working'!H50,'Commited_30 Jun'!$I:$I) -> 5.8681112e+08 | Z50: =Y50+X50 -> 5.8681112e+08 | AA50: =W50-Z50 -> -5.7533602e+08 | AC50: =SUMIF(Budgeted_01jun!$U:$U,'SAP Working'!I50,Budgeted_01jun!$R:$R) -> 0 | AD50: =SUMIF('Actual_30 jun'!$I:$I,'SAP Working'!I50,'Actual_30 jun'!$K:$K) -> 0 | AE50: =SUMIF('Commited_30 Jun'!$H:$H,'SAP Working'!I50,'Commited_30 Jun'!$I:$I) -> 0 | AF50: =AE50+AD50 -> 0 | AG50: =AC50-AF50 -> 0
A51: 10 | B51: Khavda- PSS 11 | C51: AGE27BL | D51: =D50+1 -> 47 | E51: 2 | F51: Land Cost | G51: H-5XA1-09 | H51: H-63A1-09 | I51: H-6074-09 | K51: =SUM(K52:K55) -> 2.050356e+09 | L51: =SUM(L52:L55) -> 7415910 | M51: =SUM(M52:M55) -> 1.4325459e+09 | N51: =SUM(N52:N55) -> 1.4399618e+09 | O51: =SUM(O52:O55) -> 6.1039414e+08 | Q51: =SUM(Q52:Q55) -> 0 | R51: =SUM(R52:R55) -> 0 | S51: =SUM(S52:S55) -> 0 | T51: =SUM(T52:T55) -> 0 | U51: =SUM(U52:U55) -> 0 | W51: =SUM(W52:W55) -> 0 | X51: =SUMIF('Actual_30 jun'!$I:$I,'SAP Working'!H51,'Actual_30 jun'!$K:$K) -> 0 | Y51: =SUMIF('Commited_30 Jun'!$H:$H,'SAP Working'!H51,'Commited_30 Jun'!$I:$I) -> 0 | Z51: =SUM(Z52:Z55) -> 0 | AA51: =SUM(AA52:AA55) -> 0 | AC51: =SUM(AC52:AC55) -> 2.050356e+09 | AD51: =SUM(AD52:AD55) -> 7415910 | AE51: =SUM(AE52:AE55) -> 1.4325459e+09 | AF51: =SUM(AF52:AF55) -> 1.4399618e+09 | AG51: =SUM(AG52:AG55) -> 6.1039414e+08
B52: Khavda- PSS 11 | C52: AGE27BL | D52: =D51+1 -> 48 | E52: 3 | F52: Land Lease Charges | G52: H-5XA1-09-01 | H52: H-63A1-09-01 | I52: H-6074-09-01 | K52: =AC52 -> 349078.48 | L52: =AD52 -> 3510840 | M52: =AE52 -> 0 | N52: =M52+L52 -> 3510840 | O52: =K52-N52 -> -3161761.5 | Q52: =SUMIF(Budgeted_01jun!U:U,'SAP Working'!G52,Budgeted_01jun!R:R) -> 0 | R52: =SUMIF('Actual_30 jun'!I:I,'SAP Working'!G52,'Actual_30 jun'!K:K) -> 0 | S52: =SUMIF('Commited_30 Jun'!H:H,'SAP Working'!G52,'Commited_30 Jun'!I:I) -> 0 | T52: =S52+R52 -> 0 | U52: =Q52-T52 -> 0 | W52: =SUMIF(Budgeted_01jun!$U:$U,H52,Budgeted_01jun!$R:$R) -> 0 | X52: =SUMIF('Actual_30 jun'!$I:$I,'SAP Working'!H52,'Actual_30 jun'!$K:$K) -> 0 | Y52: =SUMIF('Commited_30 Jun'!$H:$H,'SAP Working'!H52,'Commited_30 Jun'!$I:$I) -> 0 | Z52: =Y52+X52 -> 0 | AA52: =W52-Z52 -> 0 | AC52: =SUMIF(Budgeted_01jun!$U:$U,'SAP Working'!I52,Budgeted_01jun!$R:$R) -> 349078.48 | AD52: =SUMIF('Actual_30 jun'!$I:$I,'SAP Working'!I52,'Actual_30 jun'!$K:$K) -> 3510840 | AE52: =SUMIF('Commited_30 Jun'!$H:$H,'SAP Working'!I52,'Commited_30 Jun'!$I:$I) -> 0 | AF52: =AE52+AD52 -> 3510840 | AG52: =AC52-AF52 -> -3161761.5
B53: Khavda- PSS 11 | C53: AGE27BL | D53: =D52+1 -> 49 | E53: 3 | F53: ISA Charges | G53: H-5XA1-09-02 | H53: H-63A1-09-02 | I53: H-6074-09-02 | K53: =AC53 -> 150000000 | L53: =AD53 -> 0 | M53: =AE53 -> 1.4325459e+09 | N53: =M53+L53 -> 1.4325459e+09 | O53: =K53-N53 -> -1.2825459e+09 | Q53: =SUMIF(Budgeted_01jun!U:U,'SAP Working'!G53,Budgeted_01jun!R:R) -> 0 | R53: =SUMIF('Actual_30 jun'!I:I,'SAP Working'!G53,'Actual_30 jun'!K:K) -> 0 | S53: =SUMIF('Commited_30 Jun'!H:H,'SAP Working'!G53,'Commited_30 Jun'!I:I) -> 0 | T53: =S53+R53 -> 0 | U53: =Q53-T53 -> 0 | W53: =SUMIF(Budgeted_01jun!$U:$U,H53,Budgeted_01jun!$R:$R) -> 0 | X53: =SUMIF('Actual_30 jun'!$I:$I,'SAP Working'!H53,'Actual_30 jun'!$K:$K) -> 0 | Y53: =SUMIF('Commited_30 Jun'!$H:$H,'SAP Working'!H53,'Commited_30 Jun'!$I:$I) -> 0 | Z53: =Y53+X53 -> 0 | AA53: =W53-Z53 -> 0 | AC53: =SUMIF(Budgeted_01jun!$U:$U,'SAP Working'!I53,Budgeted_01jun!$R:$R) -> 150000000 | AD53: =SUMIF('Actual_30 jun'!$I:$I,'SAP Working'!I53,'Actual_30 jun'!$K:$K) -> 0 | AE53: =SUMIF('Commited_30 Jun'!$H:$H,'SAP Working'!I53,'Commited_30 Jun'!$I:$I) -> 1.4325459e+09 | AF53: =AE53+AD53 -> 1.4325459e+09 | AG53: =AC53-AF53 -> -1.2825459e+09
B54: Khavda- PSS 11 | C54: AGE27BL | D54: =D53+1 -> 50 | E54: 3 | F54: ESIA Charges | G54: H-5XA1-09-03 | H54: H-63A1-09-03 | I54: H-6074-09-03 | K54: =AC54 -> 1900000000 | L54: =AD54 -> 3905070 | M54: =AE54 -> 0 | N54: =M54+L54 -> 3905070 | O54: =K54-N54 -> 1896094930 | Q54: =SUMIF(Budgeted_01jun!U:U,'SAP Working'!G54,Budgeted_01jun!R:R) -> 0 | R54: =SUMIF('Actual_30 jun'!I:I,'SAP Working'!G54,'Actual_30 jun'!K:K) -> 0 | S54: =SUMIF('Commited_30 Jun'!H:H,'SAP Working'!G54,'Commited_30 Jun'!I:I) -> 0 | T54: =S54+R54 -> 0 | U54: =Q54-T54 -> 0 | W54: =SUMIF(Budgeted_01jun!$U:$U,H54,Budgeted_01jun!$R:$R) -> 0 | X54: =SUMIF('Actual_30 jun'!$I:$I,'SAP Working'!H54,'Actual_30 jun'!$K:$K) -> 0 | Y54: =SUMIF('Commited_30 Jun'!$H:$H,'SAP Working'!H54,'Commited_30 Jun'!$I:$I) -> 0 | Z54: =Y54+X54 -> 0 | AA54: =W54-Z54 -> 0 | AC54: =SUMIF(Budgeted_01jun!$U:$U,'SAP Working'!I54,Budgeted_01jun!$R:$R) -> 1900000000 | AD54: =SUMIF('Actual_30 jun'!$I:$I,'SAP Working'!I54,'Actual_30 jun'!$K:$K) -> 3905070 | AE54: =SUMIF('Commited_30 Jun'!$H:$H,'SAP Working'!I54,'Commited_30 Jun'!$I:$I) -> 0 | AF54: =AE54+AD54 -> 3905070 | AG54: =AC54-AF54 -> 1896094930
B55: Khavda- PSS 11 | C55: AGE27BL | D55: =D54+1 -> 51 | E55: 3 | F55: Other Statutory Charges | G55: H-5XA1-09-04 | H55: H-63A1-09-04 | I55: H-6074-09-04 | K55: =AC55 -> 6900 | L55: =AD55 -> 0 | M55: =AE55 -> 0 | N55: =M55+L55 -> 0 | O55: =K55-N55 -> 6900 | Q55: =SUMIF(Budgeted_01jun!U:U,'SAP Working'!G55,Budgeted_01jun!R:R) -> 0 | R55: =SUMIF('Actual_30 jun'!I:I,'SAP Working'!G55,'Actual_30 jun'!K:K) -> 0 | S55: =SUMIF('Commited_30 Jun'!H:H,'SAP Working'!G55,'Commited_30 Jun'!I:I) -> 0 | T55: =S55+R55 -> 0 | U55: =Q55-T55 -> 0 | W55: =SUMIF(Budgeted_01jun!$U:$U,H55,Budgeted_01jun!$R:$R) -> 0 | X55: =SUMIF('Actual_30 jun'!$I:$I,'SAP Working'!H55,'Actual_30 jun'!$K:$K) -> 0 | Y55: =SUMIF('Commited_30 Jun'!$H:$H,'SAP Working'!H55,'Commited_30 Jun'!$I:$I) -> 0 | Z55: =Y55+X55 -> 0 | AA55: =W55-Z55 -> 0 | AC55: =SUMIF(Budgeted_01jun!$U:$U,'SAP Working'!I55,Budgeted_01jun!$R:$R) -> 6900 | AD55: =SUMIF('Actual_30 jun'!$I:$I,'SAP Working'!I55,'Actual_30 jun'!$K:$K) -> 0 | AE55: =SUMIF('Commited_30 Jun'!$H:$H,'SAP Working'!I55,'Commited_30 Jun'!$I:$I) -> 0 | AF55: =AE55+AD55 -> 0 | AG55: =AC55-AF55 -> 6900
A56: 12 | B56: Khavda- PSS 11 | C56: AGE27BL | D56: =D55+1 -> 52 | E56: 2 | F56: Pre-operative Expenses | G56: H-5XA1-10 | H56: H-63A1-10 | I56: H-6074-10 | K56: =SUM(K57:K74,K79:K80) -> 80978223 | L56: =SUM(L57:L74,L79:L80) -> 43723320 | M56: =SUM(M57:M74,M79:M80) -> 1.482142e+10 | N56: =SUM(N57:N74,N79:N80) -> 1.4865143e+10 | O56: =SUM(O57:O74,O79:O80) -> -1.4784165e+10 | P56: =SUM(P57:P74,P79:P80) -> 0 | Q56: =SUM(Q57:Q74,Q79:Q80) -> 0 | R56: =SUM(R57:R74,R79:R80) -> 0 | ... AI56: =SUM(AI57:AI74,AI79:AI80) -> 0
B57: Khavda- PSS 11 | C57: AGE27BL | D57: =D56+1 -> 53 | E57: 3 | F57: Construction Power | G57: H-5XA1-10-01 | H57: H-63A1-10-01 | I57: H-6074-10-01 | K57: =AC57 -> 497381 | L57: =AD57 -> 3216570 | M57: =AE57 -> 1.28925e+09 | N57: =M57+L57 -> 1.2924666e+09 | O57: =K57-N57 -> -1.2919692e+09 | Q57: =SUMIF(Budgeted_01jun!U:U,'SAP Working'!G57,Budgeted_01jun!R:R) -> 0 | R57: =SUMIF('Actual_30 jun'!I:I,'SAP Working'!G57,'Actual_30 jun'!K:K) -> 0 | S57: =SUMIF('Commited_30 Jun'!H:H,'SAP Working'!G57,'Commited_30 Jun'!I:I) -> 0 | T57: =S57+R57 -> 0 | U57: =Q57-T57 -> 0 | W57: =SUMIF(Budgeted_01jun!$U:$U,H57,Budgeted_01jun!$R:$R) -> 0 | X57: =SUMIF('Actual_30 jun'!$I:$I,'SAP Working'!H57,'Actual_30 jun'!$K:$K) -> 0 | Y57: =SUMIF('Commited_30 Jun'!$H:$H,'SAP Working'!H57,'Commited_30 Jun'!$I:$I) -> 0 | Z57: =Y57+X57 -> 0 | AA57: =W57-Z57 -> 0 | AC57: =SUMIF(Budgeted_01jun!$U:$U,'SAP Working'!I57,Budgeted_01jun!$R:$R) -> 497381 | AD57: =SUMIF('Actual_30 jun'!$I:$I,'SAP Working'!I57,'Actual_30 jun'!$K:$K) -> 3216570 | AE57: =SUMIF('Commited_30 Jun'!$H:$H,'SAP Working'!I57,'Commited_30 Jun'!$I:$I) -> 1.28925e+09 | AF57: =AE57+AD57 -> 1.2924666e+09 | AG57: =AC57-AF57 -> -1.2919692e+09
B58: Khavda- PSS 11 | C58: AGE27BL | D58: =D57+1 -> 54 | E58: 3 | F58: Area Lighting | G58: H-5XA1-10-02 | H58: H-63A1-10-02 | I58: H-6074-10-02 | K58: =AC58 -> 10258300 | L58: =AD58 -> 5386620 | M58: =AE58 -> 6.8137814e+08 | N58: =M58+L58 -> 6.8676476e+08 | O58: =K58-N58 -> -6.7650646e+08 | Q58: =SUMIF(Budgeted_01jun!U:U,'SAP Working'!G58,Budgeted_01jun!R:R) -> 0 | R58: =SUMIF('Actual_30 jun'!I:I,'SAP Working'!G58,'Actual_30 jun'!K:K) -> 0 | S58: =SUMIF('Commited_30 Jun'!H:H,'SAP Working'!G58,'Commited_30 Jun'!I:I) -> 0 | T58: =S58+R58 -> 0 | U58: =Q58-T58 -> 0 | W58: =SUMIF(Budgeted_01jun!$U:$U,H58,Budgeted_01jun!$R:$R) -> 0 | X58: =SUMIF('Actual_30 jun'!$I:$I,'SAP Working'!H58,'Actual_30 jun'!$K:$K) -> 0 | Y58: =SUMIF('Commited_30 Jun'!$H:$H,'SAP Working'!H58,'Commited_30 Jun'!$I:$I) -> 0 | Z58: =Y58+X58 -> 0 | AA58: =W58-Z58 -> 0 | AC58: =SUMIF(Budgeted_01jun!$U:$U,'SAP Working'!I58,Budgeted_01jun!$R:$R) -> 10258300 | AD58: =SUMIF('Actual_30 jun'!$I:$I,'SAP Working'!I58,'Actual_30 jun'!$K:$K) -> 5386620 | AE58: =SUMIF('Commited_30 Jun'!$H:$H,'SAP Working'!I58,'Commited_30 Jun'!$I:$I) -> 6.8137814e+08 | AF58: =AE58+AD58 -> 6.8676476e+08 | AG58: =AC58-AF58 -> -6.7650646e+08
B59: Khavda- PSS 11 | C59: AGE27BL | D59: =D58+1 -> 55 | E59: 3 | F59: Site Office & Store Setup | G59: H-5XA1-10-03 | H59: H-63A1-10-03 | I59: H-6074-10-03 | K59: =AC59 -> 1736204 | L59: =AD59 -> 3057450 | M59: =AE59 -> 1.4721897e+09 | N59: =M59+L59 -> 1.4752472e+09 | O59: =K59-N59 -> -1.473511e+09 | Q59: =SUMIF(Budgeted_01jun!U:U,'SAP Working'!G59,Budgeted_01jun!R:R) -> 0 | R59: =SUMIF('Actual_30 jun'!I:I,'SAP Working'!G59,'Actual_30 jun'!K:K) -> 0 | S59: =SUMIF('Commited_30 Jun'!H:H,'SAP Working'!G59,'Commited_30 Jun'!I:I) -> 0 | T59: =S59+R59 -> 0 | U59: =Q59-T59 -> 0 | W59: =SUMIF(Budgeted_01jun!$U:$U,H59,Budgeted_01jun!$R:$R) -> 0 | X59: =SUMIF('Actual_30 jun'!$I:$I,'SAP Working'!H59,'Actual_30 jun'!$K:$K) -> 0 | Y59: =SUMIF('Commited_30 Jun'!$H:$H,'SAP Working'!H59,'Commited_30 Jun'!$I:$I) -> 0 | Z59: =Y59+X59 -> 0 | AA59: =W59-Z59 -> 0 | AC59: =SUMIF(Budgeted_01jun!$U:$U,'SAP Working'!I59,Budgeted_01jun!$R:$R) -> 1736204 | AD59: =SUMIF('Actual_30 jun'!$I:$I,'SAP Working'!I59,'Actual_30 jun'!$K:$K) -> 3057450 | AE59: =SUMIF('Commited_30 Jun'!$H:$H,'SAP Working'!I59,'Commited_30 Jun'!$I:$I) -> 1.4721897e+09 | AF59: =AE59+AD59 -> 1.4752472e+09 | AG59: =AC59-AF59 -> -1.473511e+09
B60: Khavda- PSS 11 | C60: AGE27BL | D60: =D59+1 -> 56 | E60: 3 | F60: Guest house / Office set up | G60: H-5XA1-10-04 | H60: H-63A1-10-04 | I60: H-6074-10-04 | K60: =AC60 -> 0 | L60: =AD60 -> 0 | M60: =AE60 -> 0 | N60: =M60+L60 -> 0 | O60: =K60-N60 -> 0 | Q60: =SUMIF(Budgeted_01jun!U:U,'SAP Working'!G60,Budgeted_01jun!R:R) -> 0 | R60: =SUMIF('Actual_30 jun'!I:I,'SAP Working'!G60,'Actual_30 jun'!K:K) -> 0 | S60: =SUMIF('Commited_30 Jun'!H:H,'SAP Working'!G60,'Commited_30 Jun'!I:I) -> 0 | T60: =S60+R60 -> 0 | U60: =Q60-T60 -> 0 | W60: =SUMIF(Budgeted_01jun!$U:$U,H60,Budgeted_01jun!$R:$R) -> 0 | X60: =SUMIF('Actual_30 jun'!$I:$I,'SAP Working'!H60,'Actual_30 jun'!$K:$K) -> 0 | Y60: =SUMIF('Commited_30 Jun'!$H:$H,'SAP Working'!H60,'Commited_30 Jun'!$I:$I) -> 0 | Z60: =Y60+X60 -> 0 | AA60: =W60-Z60 -> 0 | AC60: =SUMIF(Budgeted_01jun!$U:$U,'SAP Working'!I60,Budgeted_01jun!$R:$R) -> 0 | AD60: =SUMIF('Actual_30 jun'!$I:$I,'SAP Working'!I60,'Actual_30 jun'!$K:$K) -> 0 | AE60: =SUMIF('Commited_30 Jun'!$H:$H,'SAP Working'!I60,'Commited_30 Jun'!$I:$I) -> 0 | AF60: =AE60+AD60 -> 0 | AG60: =AC60-AF60 -> 0
B61: Khavda- PSS 11 | C61: AGE27BL | D61: =D60+1 -> 57 | E61: 3 | F61: Administration and Office Expenses | G61: H-5XA1-10-05 | H61: H-63A1-10-05 | I61: H-6074-10-05 | K61: =AC61 -> 0 | L61: =AD61 -> 0 | M61: =AE61 -> 0 | N61: =M61+L61 -> 0 | O61: =K61-N61 -> 0 | Q61: =SUMIF(Budgeted_01jun!U:U,'SAP Working'!G61,Budgeted_01jun!R:R) -> 0 | R61: =SUMIF('Actual_30 jun'!I:I,'SAP Working'!G61,'Actual_30 jun'!K:K) -> 0 | S61: =SUMIF('Commited_30 Jun'!H:H,'SAP Working'!G61,'Commited_30 Jun'!I:I) -> 0 | T61: =S61+R61 -> 0 | U61: =Q61-T61 -> 0 | W61: =SUMIF(Budgeted_01jun!$U:$U,H61,Budgeted_01jun!$R:$R) -> 0 | X61: =SUMIF('Actual_30 jun'!$I:$I,'SAP Working'!H61,'Actual_30 jun'!$K:$K) -> 0 | Y61: =SUMIF('Commited_30 Jun'!$H:$H,'SAP Working'!H61,'Commited_30 Jun'!$I:$I) -> 0 | Z61: =Y61+X61 -> 0 | AA61: =W61-Z61 -> 0 | AC61: =SUMIF(Budgeted_01jun!$U:$U,'SAP Working'!I61,Budgeted_01jun!$R:$R) -> 0 | AD61: =SUMIF('Actual_30 jun'!$I:$I,'SAP Working'!I61,'Actual_30 jun'!$K:$K) -> 0 | AE61: =SUMIF('Commited_30 Jun'!$H:$H,'SAP Working'!I61,'Commited_30 Jun'!$I:$I) -> 0 | AF61: =AE61+AD61 -> 0 | AG61: =AC61-AF61 -> 0
B62: Khavda- PSS 11 | C62: AGE27BL | D62: =D61+1 -> 58 | E62: 3 | F62: Vehicle Running | G62: H-5XA1-10-06 | H62: H-63A1-10-06 | I62: H-6074-10-06 | K62: =AC62 -> 0 | L62: =AD62 -> 0 | M62: =AE62 -> 0 | N62: =M62+L62 -> 0 | O62: =K62-N62 -> 0 | Q62: =SUMIF(Budgeted_01jun!U:U,'SAP Working'!G62,Budgeted_01jun!R:R) -> 0 | R62: =SUMIF('Actual_30 jun'!I:I,'SAP Working'!G62,'Actual_30 jun'!K:K) -> 0 | S62: =SUMIF('Commited_30 Jun'!H:H,'SAP Working'!G62,'Commited_30 Jun'!I:I) -> 0 | T62: =S62+R62 -> 0 | U62: =Q62-T62 -> 0 | W62: =SUMIF(Budgeted_01jun!$U:$U,H62,Budgeted_01jun!$R:$R) -> 0 | X62: =SUMIF('Actual_30 jun'!$I:$I,'SAP Working'!H62,'Actual_30 jun'!$K:$K) -> 0 | Y62: =SUMIF('Commited_30 Jun'!$H:$H,'SAP Working'!H62,'Commited_30 Jun'!$I:$I) -> 0 | Z62: =Y62+X62 -> 0 | AA62: =W62-Z62 -> 0 | AC62: =SUMIF(Budgeted_01jun!$U:$U,'SAP Working'!I62,Budgeted_01jun!$R:$R) -> 0 | AD62: =SUMIF('Actual_30 jun'!$I:$I,'SAP Working'!I62,'Actual_30 jun'!$K:$K) -> 0 | AE62: =SUMIF('Commited_30 Jun'!$H:$H,'SAP Working'!I62,'Commited_30 Jun'!$I:$I) -> 0 | AF62: =AE62+AD62 -> 0 | AG62: =AC62-AF62 -> 0
B63: Khavda- PSS 11 | C63: AGE27BL | D63: =D62+1 -> 59 | E63: 3 | F63: HSE | G63: H-5XA1-10-07 | H63: H-63A1-10-07 | I63: H-6074-10-07 | K63: =AC63 -> 0 | L63: =AD63 -> 0 | M63: =AE63 -> 0 | N63: =M63+L63 -> 0 | O63: =K63-N63 -> 0 | Q63: =SUMIF(Budgeted_01jun!U:U,'SAP Working'!G63,Budgeted_01jun!R:R) -> 0 | R63: =SUMIF('Actual_30 jun'!I:I,'SAP Working'!G63,'Actual_30 jun'!K:K) -> 0 | S63: =SUMIF('Commited_30 Jun'!H:H,'SAP Working'!G63,'Commited_30 Jun'!I:I) -> 0 | T63: =S63+R63 -> 0 | U63: =Q63-T63 -> 0 | W63: =SUMIF(Budgeted_01jun!$U:$U,H63,Budgeted_01jun!$R:$R) -> 0 | X63: =SUMIF('Actual_30 jun'!$I:$I,'SAP Working'!H63,'Actual_30 jun'!$K:$K) -> 0 | Y63: =SUMIF('Commited_30 Jun'!$H:$H,'SAP Working'!H63,'Commited_30 Jun'!$I:$I) -> 0 | Z63: =Y63+X63 -> 0 | AA63: =W63-Z63 -> 0 | AC63: =SUMIF(Budgeted_01jun!$U:$U,'SAP Working'!I63,Budgeted_01jun!$R:$R) -> 0 | AD63: =SUMIF('Actual_30 jun'!$I:$I,'SAP Working'!I63,'Actual_30 jun'!$K:$K) -> 0 | AE63: =SUMIF('Commited_30 Jun'!$H:$H,'SAP Working'!I63,'Commited_30 Jun'!$I:$I) -> 0 | AF63: =AE63+AD63 -> 0 | AG63: =AC63-AF63 -> 0
B64: Khavda- PSS 11 | C64: AGE27BL | D64: =D63+1 -> 60 | E64: 3 | F64: Security | G64: H-5XA1-10-08 | H64: H-63A1-10-08 | I64: H-6074-10-08 | K64: =AC64 -> 0 | L64: =AD64 -> 0 | M64: =AE64 -> 0 | N64: =M64+L64 -> 0 | O64: =K64-N64 -> 0 | Q64: =SUMIF(Budgeted_01jun!U:U,'SAP Working'!G64,Budgeted_01jun!R:R) -> 0 | R64: =SUMIF('Actual_30 jun'!I:I,'SAP Working'!G64,'Actual_30 jun'!K:K) -> 0 | S64: =SUMIF('Commited_30 Jun'!H:H,'SAP Working'!G64,'Commited_30 Jun'!I:I) -> 0 | T64: =S64+R64 -> 0 | U64: =Q64-T64 -> 0 | W64: =SUMIF(Budgeted_01jun!$U:$U,H64,Budgeted_01jun!$R:$R) -> 0 | X64: =SUMIF('Actual_30 jun'!$I:$I,'SAP Working'!H64,'Actual_30 jun'!$K:$K) -> 0 | Y64: =SUMIF('Commited_30 Jun'!$H:$H,'SAP Working'!H64,'Commited_30 Jun'!$I:$I) -> 0 | Z64: =Y64+X64 -> 0 | AA64: =W64-Z64 -> 0 | AC64: =SUMIF(Budgeted_01jun!$U:$U,'SAP Working'!I64,Budgeted_01jun!$R:$R) -> 0 | AD64: =SUMIF('Actual_30 jun'!$I:$I,'SAP Working'!I64,'Actual_30 jun'!$K:$K) -> 0 | AE64: =SUMIF('Commited_30 Jun'!$H:$H,'SAP Working'!I64,'Commited_30 Jun'!$I:$I) -> 0 | AF64: =AE64+AD64 -> 0 | AG64: =AC64-AF64 -> 0
B65: Khavda- PSS 11 | C65: AGE27BL | D65: =D64+1 -> 61 | E65: 3 | F65: IT Infrastructure | G65: H-5XA1-10-09 | H65: H-63A1-10-09 | I65: H-6074-10-09 | K65: =AC65 -> 3251080 | L65: =AD65 -> 0 | M65: =AE65 -> 7.1937014e+08 | N65: =M65+L65 -> 7.1937014e+08 | O65: =K65-N65 -> -7.1611906e+08 | Q65: =SUMIF(Budgeted_01jun!U:U,'SAP Working'!G65,Budgeted_01jun!R:R) -> 0 | R65: =SUMIF('Actual_30 jun'!I:I,'SAP Working'!G65,'Actual_30 jun'!K:K) -> 0 | S65: =SUMIF('Commited_30 Jun'!H:H,'SAP Working'!G65,'Commited_30 Jun'!I:I) -> 0 | T65: =S65+R65 -> 0 | U65: =Q65-T65 -> 0 | W65: =SUMIF(Budgeted_01jun!$U:$U,H65,Budgeted_01jun!$R:$R) -> 0 | X65: =SUMIF('Actual_30 jun'!$I:$I,'SAP Working'!H65,'Actual_30 jun'!$K:$K) -> 0 | Y65: =SUMIF('Commited_30 Jun'!$H:$H,'SAP Working'!H65,'Commited_30 Jun'!$I:$I) -> 0 | Z65: =Y65+X65 -> 0 | AA65: =W65-Z65 -> 0 | AC65: =SUMIF(Budgeted_01jun!$U:$U,'SAP Working'!I65,Budgeted_01jun!$R:$R) -> 3251080 | AD65: =SUMIF('Actual_30 jun'!$I:$I,'SAP Working'!I65,'Actual_30 jun'!$K:$K) -> 0 | AE65: =SUMIF('Commited_30 Jun'!$H:$H,'SAP Working'!I65,'Commited_30 Jun'!$I:$I) -> 7.1937014e+08 | AF65: =AE65+AD65 -> 7.1937014e+08 | AG65: =AC65-AF65 -> -7.1611906e+08
B66: Khavda- PSS 11 | C66: AGE27BL | D66: =D65+1 -> 62 | E66: 3 | F66: Manpower & Equipment Hiring | G66: H-5XA1-10-10 | H66: H-63A1-10-10 | I66: H-6074-10-10 | K66: =AC66 -> 56000000 | L66: =AD66 -> 13633830 | M66: =AE66 -> 9.9456431e+09 | N66: =M66+L66 -> 9.959277e+09 | O66: =K66-N66 -> -9.903277e+09 | Q66: =SUMIF(Budgeted_01jun!U:U,'SAP Working'!G66,Budgeted_01jun!R:R) -> 0 | R66: =SUMIF('Actual_30 jun'!I:I,'SAP Working'!G66,'Actual_30 jun'!K:K) -> 0 | S66: =SUMIF('Commited_30 Jun'!H:H,'SAP Working'!G66,'Commited_30 Jun'!I:I) -> 0 | T66: =S66+R66 -> 0 | U66: =Q66-T66 -> 0 | W66: =SUMIF(Budgeted_01jun!$U:$U,H66,Budgeted_01jun!$R:$R) -> 0 | X66: =SUMIF('Actual_30 jun'!$I:$I,'SAP Working'!H66,'Actual_30 jun'!$K:$K) -> 0 | Y66: =SUMIF('Commited_30 Jun'!$H:$H,'SAP Working'!H66,'Commited_30 Jun'!$I:$I) -> 0 | Z66: =Y66+X66 -> 0 | AA66: =W66-Z66 -> 0 | AC66: =SUMIF(Budgeted_01jun!$U:$U,'SAP Working'!I66,Budgeted_01jun!$R:$R) -> 56000000 | AD66: =SUMIF('Actual_30 jun'!$I:$I,'SAP Working'!I66,'Actual_30 jun'!$K:$K) -> 13633830 | AE66: =SUMIF('Commited_30 Jun'!$H:$H,'SAP Working'!I66,'Commited_30 Jun'!$I:$I) -> 9.9456431e+09 | AF66: =AE66+AD66 -> 9.959277e+09 | AG66: =AC66-AF66 -> -9.903277e+09
B67: Khavda- PSS 11 | C67: AGE27BL | D67: =D66+1 -> 63 | E67: 3 | F67: Professional & Consultancy Fees | G67: H-5XA1-10-11 | H67: H-63A1-10-11 | I67: H-6074-10-11 | K67: =AC67 -> 0 | L67: =AD67 -> 0 | M67: =AE67 -> 0 | N67: =M67+L67 -> 0 | O67: =K67-N67 -> 0 | Q67: =SUMIF(Budgeted_01jun!U:U,'SAP Working'!G67,Budgeted_01jun!R:R) -> 0 | R67: =SUMIF('Actual_30 jun'!I:I,'SAP Working'!G67,'Actual_30 jun'!K:K) -> 0 | S67: =SUMIF('Commited_30 Jun'!H:H,'SAP Working'!G67,'Commited_30 Jun'!I:I) -> 0 | T67: =S67+R67 -> 0 | U67: =Q67-T67 -> 0 | W67: =SUMIF(Budgeted_01jun!$U:$U,H67,Budgeted_01jun!$R:$R) -> 0 | X67: =SUMIF('Actual_30 jun'!$I:$I,'SAP Working'!H67,'Actual_30 jun'!$K:$K) -> 0 | Y67: =SUMIF('Commited_30 Jun'!$H:$H,'SAP Working'!H67,'Commited_30 Jun'!$I:$I) -> 0 | Z67: =Y67+X67 -> 0 | AA67: =W67-Z67 -> 0 | AC67: =SUMIF(Budgeted_01jun!$U:$U,'SAP Working'!I67,Budgeted_01jun!$R:$R) -> 0 | AD67: =SUMIF('Actual_30 jun'!$I:$I,'SAP Working'!I67,'Actual_30 jun'!$K:$K) -> 0 | AE67: =SUMIF('Commited_30 Jun'!$H:$H,'SAP Working'!I67,'Commited_30 Jun'!$I:$I) -> 0 | AF67: =AE67+AD67 -> 0 | AG67: =AC67-AF67 -> 0
B68: Khavda- PSS 11 | C68: AGE27BL | D68: =D67+1 -> 64 | E68: 3 | F68: Rates & Taxes | G68: H-5XA1-10-12 | H68: H-63A1-10-12 | I68: H-6074-10-12 | K68: =AC68 -> 1300 | L68: =AD68 -> 0 | M68: =AE68 -> 0 | N68: =M68+L68 -> 0 | O68: =K68-N68 -> 1300 | Q68: =SUMIF(Budgeted_01jun!U:U,'SAP Working'!G68,Budgeted_01jun!R:R) -> 0 | R68: =SUMIF('Actual_30 jun'!I:I,'SAP Working'!G68,'Actual_30 jun'!K:K) -> 0 | S68: =SUMIF('Commited_30 Jun'!H:H,'SAP Working'!G68,'Commited_30 Jun'!I:I) -> 0 | T68: =S68+R68 -> 0 | U68: =Q68-T68 -> 0 | W68: =SUMIF(Budgeted_01jun!$U:$U,H68,Budgeted_01jun!$R:$R) -> 0 | X68: =SUMIF('Actual_30 jun'!$I:$I,'SAP Working'!H68,'Actual_30 jun'!$K:$K) -> 0 | Y68: =SUMIF('Commited_30 Jun'!$H:$H,'SAP Working'!H68,'Commited_30 Jun'!$I:$I) -> 0 | Z68: =Y68+X68 -> 0 | AA68: =W68-Z68 -> 0 | AC68: =SUMIF(Budgeted_01jun!$U:$U,'SAP Working'!I68,Budgeted_01jun!$R:$R) -> 1300 | AD68: =SUMIF('Actual_30 jun'!$I:$I,'SAP Working'!I68,'Actual_30 jun'!$K:$K) -> 0 | AE68: =SUMIF('Commited_30 Jun'!$H:$H,'SAP Working'!I68,'Commited_30 Jun'!$I:$I) -> 0 | AF68: =AE68+AD68 -> 0 | AG68: =AC68-AF68 -> 1300
... B73: Khavda- PSS 11 | C73: AGE27BL | D73: =D72+1 -> 69 | E73: 3 | F73: Corporate Allocation | G73: H-5XA1-10-17 | H73: H-63A1-10-17 | I73: H-6074-10-17 | K73: =AC73 -> 0 | L73: =AD73 -> 2660670 | M73: =AE73 -> 0 | N73: =M73+L73 -> 2660670 | O73: =K73-N73 -> -2660670 | Q73: =SUMIF(Budgeted_01jun!U:U,'SAP Working'!G73,Budgeted_01jun!R:R) -> 0 | R73: =SUMIF('Actual_30 jun'!I:I,'SAP Working'!G73,'Actual_30 jun'!K:K) -> 0 | S73: =SUMIF('Commited_30 Jun'!H:H,'SAP Working'!G73,'Commited_30 Jun'!I:I) -> 0 | T73: =S73+R73 -> 0 | U73: =Q73-T73 -> 0 | W73: =SUMIF(Budgeted_01jun!$U:$U,H73,Budgeted_01jun!$R:$R) -> 0 | X73: =SUMIF('Actual_30 jun'!$I:$I,'SAP Working'!H73,'Actual_30 jun'!$K:$K) -> 0 | Y73: =SUMIF('Commited_30 Jun'!$H:$H,'SAP Working'!H73,'Commited_30 Jun'!$I:$I) -> 0 | Z73: =Y73+X73 -> 0 | AA73: =W73-Z73 -> 0 | AC73: =SUMIF(Budgeted_01jun!$U:$U,'SAP Working'!I73,Budgeted_01jun!$R:$R) -> 0 | AD73: =SUMIF('Actual_30 jun'!$I:$I,'SAP Working'!I73,'Actual_30 jun'!$K:$K) -> 2660670 | AE73: =SUMIF('Commited_30 Jun'!$H:$H,'SAP Working'!I73,'Commited_30 Jun'!$I:$I) -> 0 | AF73: =AE73+AD73 -> 2660670 | AG73: =AC73-AF73 -> -2660670
B74: Khavda- PSS 11 | C74: AGE27BL | D74: =D73+1 -> 70 | E74: 3 | F74: Statutory Charges | G74: H-5XA1-10-18 | H74: H-63A1-10-18 | I74: H-6074-10-18 | K74: =SUM(K75:K78) -> 2124000 | L74: =SUM(L75:L78) -> 5748720 | M74: =SUM(M75:M78) -> 7.1358875e+08 | N74: =SUM(N75:N78) -> 7.1933747e+08 | O74: {=SUM(O75+O75:O78)} -> -7.1721347e+08 | Q74: =SUM(Q75:Q78) -> 0 | R74: =SUM(R75:R78) -> 0 | S74: =SUM(S75:S78) -> 0 | T74: =SUM(T75:T78) -> 0 | U74: {=SUM(U75+U75:U78)} -> 0 | V74: {=SUM(V75+V75:V78)} -> 0 | W74: =SUM(W75:W78) -> 0 | X74: =SUM(X75:X78) -> 0 | Y74: =SUM(Y75:Y78) -> 0 | Z74: =SUM(Z75:Z78) -> 0 | AA74: {=SUM(AA75+AA75:AA78)} -> 0 | AB74: {=SUM(AB75+AB75:AB78)} -> 0 | AC74: =SUM(AC75:AC78) -> 2124000 | AD74: =SUM(AD75:AD78) -> 5748720 | AE74: =SUM(AE75:AE78) -> 7.1358875e+08 | AF74: =SUM(AF75:AF78) -> 7.1933747e+08 | AG74: =SUM(AG75:AG78) -> -7.1721347e+08 | AH74: {=SUM(AH75+AH75:AH78)} -> 0 | AI74: {=SUM(AI75+AI75:AI78)} -> 0
B75: Khavda- PSS 11 | C75: AGE27BL | D75: =D74+1 -> 71 | E75: 4 | F75: RLDC Regsitartion Fees | G75: H-5XA1-10-18-01 | H75: H-63A1-10-18-01 | I75: H-6074-10-18-01 | K75: =AC75 -> 0 | L75: =AD75 -> 0 | M75: =AE75 -> 0 | N75: =M75+L75 -> 0 | O75: =K75-N75 -> 0 | Q75: =SUMIF(Budgeted_01jun!U:U,'SAP Working'!G75,Budgeted_01jun!R:R) -> 0 | R75: =SUMIF('Actual_30 jun'!I:I,'SAP Working'!G75,'Actual_30 jun'!K:K) -> 0 | S75: =SUMIF('Commited_30 Jun'!H:H,'SAP Working'!G75,'Commited_30 Jun'!I:I) -> 0 | T75: =S75+R75 -> 0 | U75: =Q75-T75 -> 0 | W75: =SUMIF(Budgeted_01jun!$U:$U,H75,Budgeted_01jun!$R:$R) -> 0 | X75: =SUMIF('Actual_30 jun'!$I:$I,'SAP Working'!H75,'Actual_30 jun'!$K:$K) -> 0 | Y75: =SUMIF('Commited_30 Jun'!$H:$H,'SAP Working'!H75,'Commited_30 Jun'!$I:$I) -> 0 | Z75: =Y75+X75 -> 0 | AA75: =W75-Z75 -> 0 | AC75: =SUMIF(Budgeted_01jun!$U:$U,'SAP Working'!I75,Budgeted_01jun!$R:$R) -> 0 | AD75: =SUMIF('Actual_30 jun'!$I:$I,'SAP Working'!I75,'Actual_30 jun'!$K:$K) -> 0 | AE75: =SUMIF('Commited_30 Jun'!$H:$H,'SAP Working'!I75,'Commited_30 Jun'!$I:$I) -> 0 | AF75: =AE75+AD75 -> 0 | AG75: =AC75-AF75 -> 0
B76: Khavda- PSS 11 | C76: AGE27BL | D76: =D75+1 -> 72 | E76: 4 | F76: GNA Charges | G76: H-5XA1-10-18-02 | H76: H-63A1-10-18-02 | I76: H-6074-10-18-02 | K76: =AC76 -> 0 | L76: =AD76 -> 0 | M76: =AE76 -> 0 | N76: =M76+L76 -> 0 | O76: =K76-N76 -> 0 | Q76: =SUMIF(Budgeted_01jun!U:U,'SAP Working'!G76,Budgeted_01jun!R:R) -> 0 | R76: =SUMIF('Actual_30 jun'!I:I,'SAP Working'!G76,'Actual_30 jun'!K:K) -> 0 | S76: =SUMIF('Commited_30 Jun'!H:H,'SAP Working'!G76,'Commited_30 Jun'!I:I) -> 0 | T76: =S76+R76 -> 0 | U76: =Q76-T76 -> 0 | W76: =SUMIF(Budgeted_01jun!$U:$U,H76,Budgeted_01jun!$R:$R) -> 0 | X76: =SUMIF('Actual_30 jun'!$I:$I,'SAP Working'!H76,'Actual_30 jun'!$K:$K) -> 0 | Y76: =SUMIF('Commited_30 Jun'!$H:$H,'SAP Working'!H76,'Commited_30 Jun'!$I:$I) -> 0 | Z76: =Y76+X76 -> 0 | AA76: =W76-Z76 -> 0 | AC76: =SUMIF(Budgeted_01jun!$U:$U,'SAP Working'!I76,Budgeted_01jun!$R:$R) -> 0 | AD76: =SUMIF('Actual_30 jun'!$I:$I,'SAP Working'!I76,'Actual_30 jun'!$K:$K) -> 0 | AE76: =SUMIF('Commited_30 Jun'!$H:$H,'SAP Working'!I76,'Commited_30 Jun'!$I:$I) -> 0 | AF76: =AE76+AD76 -> 0 | AG76: =AC76-AF76 -> 0
B77: Khavda- PSS 11 | C77: AGE27BL | D77: =D76+1 -> 73 | E77: 4 | F77: Misc Charges (GEDA MOOWER) | G77: H-5XA1-10-18-03 | H77: H-63A1-10-18-03 | I77: H-6074-10-18-03 | K77: =AC77 -> 2124000 | L77: =AD77 -> 5748720 | M77: =AE77 -> 7.1358875e+08 | N77: =M77+L77 -> 7.1933747e+08 | O77: =K77-N77 -> -7.1721347e+08 | Q77: =SUMIF(Budgeted_01jun!U:U,'SAP Working'!G77,Budgeted_01jun!R:R) -> 0 | R77: =SUMIF('Actual_30 jun'!I:I,'SAP Working'!G77,'Actual_30 jun'!K:K) -> 0 | S77: =SUMIF('Commited_30 Jun'!H:H,'SAP Working'!G77,'Commited_30 Jun'!I:I) -> 0 | T77: =S77+R77 -> 0 | U77: =Q77-T77 -> 0 | W77: =SUMIF(Budgeted_01jun!$U:$U,H77,Budgeted_01jun!$R:$R) -> 0 | X77: =SUMIF('Actual_30 jun'!$I:$I,'SAP Working'!H77,'Actual_30 jun'!$K:$K) -> 0 | Y77: =SUMIF('Commited_30 Jun'!$H:$H,'SAP Working'!H77,'Commited_30 Jun'!$I:$I) -> 0 | Z77: =Y77+X77 -> 0 | AA77: =W77-Z77 -> 0 | AC77: =SUMIF(Budgeted_01jun!$U:$U,'SAP Working'!I77,Budgeted_01jun!$R:$R) -> 2124000 | AD77: =SUMIF('Actual_30 jun'!$I:$I,'SAP Working'!I77,'Actual_30 jun'!$K:$K) -> 5748720 | AE77: =SUMIF('Commited_30 Jun'!$H:$H,'SAP Working'!I77,'Commited_30 Jun'!$I:$I) -> 7.1358875e+08 | AF77: =AE77+AD77 -> 7.1933747e+08 | AG77: =AC77-AF77 -> -7.1721347e+08
B78: Khavda- PSS 11 | C78: AGE27BL | D78: =D77+1 -> 74 | E78: 4 | F78: BOCW & CLRA | G78: H-5XA1-10-18-04 | H78: H-63A1-10-18-04 | I78: H-6074-10-18-04 | K78: =AC78 -> 0 | L78: =AD78 -> 0 | M78: =AE78 -> 0 | N78: =M78+L78 -> 0 | O78: =K78-N78 -> 0 | Q78: =SUMIF(Budgeted_01jun!U:U,'SAP Working'!G78,Budgeted_01jun!R:R) -> 0 | R78: =SUMIF('Actual_30 jun'!I:I,'SAP Working'!G78,'Actual_30 jun'!K:K) -> 0 | S78: =SUMIF('Commited_30 Jun'!H:H,'SAP Working'!G78,'Commited_30 Jun'!I:I) -> 0 | T78: =S78+R78 -> 0 | U78: =Q78-T78 -> 0 | W78: =SUMIF(Budgeted_01jun!$U:$U,H78,Budgeted_01jun!$R:$R) -> 0 | X78: =SUMIF('Actual_30 jun'!$I:$I,'SAP Working'!H78,'Actual_30 jun'!$K:$K) -> 0 | Y78: =SUMIF('Commited_30 Jun'!$H:$H,'SAP Working'!H78,'Commited_30 Jun'!$I:$I) -> 0 | Z78: =Y78+X78 -> 0 | AA78: =W78-Z78 -> 0 | AC78: =SUMIF(Budgeted_01jun!$U:$U,'SAP Working'!I78,Budgeted_01jun!$R:$R) -> 0 | AD78: =SUMIF('Actual_30 jun'!$I:$I,'SAP Working'!I78,'Actual_30 jun'!$K:$K) -> 0 | AE78: =SUMIF('Commited_30 Jun'!$H:$H,'SAP Working'!I78,'Commited_30 Jun'!$I:$I) -> 0 | AF78: =AE78+AD78 -> 0 | AG78: =AC78-AF78 -> 0
B79: Khavda- PSS 11 | C79: AGE27BL | D79: =D78+1 -> 75 | E79: 3 | F79: Bid & Success Fee | G79: H-5XA1-10-19 | H79: H-63A1-10-19 | I79: H-6074-10-19 | K79: =AC79 -> 0 | L79: =AD79 -> 0 | M79: =AE79 -> 0 | N79: =M79+L79 -> 0 | O79: =K79-N79 -> 0 | Q79: =SUMIF(Budgeted_01jun!U:U,'SAP Working'!G79,Budgeted_01jun!R:R) -> 0 | R79: =SUMIF('Actual_30 jun'!I:I,'SAP Working'!G79,'Actual_30 jun'!K:K) -> 0 | S79: =SUMIF('Commited_30 Jun'!H:H,'SAP Working'!G79,'Commited_30 Jun'!I:I) -> 0 | T79: =S79+R79 -> 0 | U79: =Q79-T79 -> 0 | W79: =SUMIF(Budgeted_01jun!$U:$U,H79,Budgeted_01jun!$R:$R) -> 0 | X79: =SUMIF('Actual_30 jun'!$I:$I,'SAP Working'!H79,'Actual_30 jun'!$K:$K) -> 0 | Y79: =SUMIF('Commited_30 Jun'!$H:$H,'SAP Working'!H79,'Commited_30 Jun'!$I:$I) -> 0 | Z79: =Y79+X79 -> 0 | AA79: =W79-Z79 -> 0 | AC79: =SUMIF(Budgeted_01jun!$U:$U,'SAP Working'!I79,Budgeted_01jun!$R:$R) -> 0 | AD79: =SUMIF('Actual_30 jun'!$I:$I,'SAP Working'!I79,'Actual_30 jun'!$K:$K) -> 0 | AE79: =SUMIF('Commited_30 Jun'!$H:$H,'SAP Working'!I79,'Commited_30 Jun'!$I:$I) -> 0 | AF79: =AE79+AD79 -> 0 | AG79: =AC79-AF79 -> 0
B80: Khavda- PSS 11 | C80: AGE27BL | D80: =D79+1 -> 76 | E80: 3 | F80: Depreciation | G80: H-5XA1-10-20 | H80: H-63A1-10-20 | I80: H-6074-10-20 | K80: =AC80 -> 98957.79 | L80: =AD80 -> 6400500 | M80: =AE80 -> 0 | N80: =M80+L80 -> 6400500 | O80: =K80-N80 -> -6301542.2 | Q80: =SUMIF(Budgeted_01jun!U:U,'SAP Working'!G80,Budgeted_01jun!R:R) -> 0 | R80: =SUMIF('Actual_30 jun'!I:I,'SAP Working'!G80,'Actual_30 jun'!K:K) -> 0 | S80: =SUMIF('Commited_30 Jun'!H:H,'SAP Working'!G80,'Commited_30 Jun'!I:I) -> 0 | T80: =S80+R80 -> 0 | U80: =Q80-T80 -> 0 | W80: =SUMIF(Budgeted_01jun!$U:$U,H80,Budgeted_01jun!$R:$R) -> 0 | X80: =SUMIF('Actual_30 jun'!$I:$I,'SAP Working'!H80,'Actual_30 jun'!$K:$K) -> 0 | Y80: =SUMIF('Commited_30 Jun'!$H:$H,'SAP Working'!H80,'Commited_30 Jun'!$I:$I) -> 0 | Z80: =Y80+X80 -> 0 | AA80: =W80-Z80 -> 0 | AC80: =SUMIF(Budgeted_01jun!$U:$U,'SAP Working'!I80,Budgeted_01jun!$R:$R) -> 98957.79 | AD80: =SUMIF('Actual_30 jun'!$I:$I,'SAP Working'!I80,'Actual_30 jun'!$K:$K) -> 6400500 | AE80: =SUMIF('Commited_30 Jun'!$H:$H,'SAP Working'!I80,'Commited_30 Jun'!$I:$I) -> 0 | AF80: =AE80+AD80 -> 6400500 | AG80: =AC80-AF80 -> -6301542.2
A81: 13 | B81: Khavda- PSS 11 | C81: AGE27BL | D81: =D80+1 -> 77 | E81: 2 | F81: Finance & IDC | G81: H-5XA1-11 | H81: H-63A1-11 | I81: H-6074-11 | K81: =SUM(K82:K88) -> 0 | L81: =SUM(L82:L88) -> 0 | M81: =SUM(M82:M88) -> 0 | N81: =SUM(N82:N88) -> 0 | O81: =SUM(O82:O88) -> 0 | P81: =SUM(P82:P88) -> 0 | Q81: =SUM(Q82:Q88) -> 20043390 | R81: =SUM(R82:R88) -> 5022990 | ... AA81: =SUM(AA82:AA88) -> 0 | AC81: =SUM(AC82:AC88) -> 0 | AD81: =SUM(AD82:AD88) -> 0 | AE81: =SUM(AE82:AE88) -> 0 | AF81: =SUM(AF82:AF88) -> 0 | AG81: =SUM(AG82:AG88) -> 0 | AH81: =SUM(AH82:AH88) -> 0 | AI81: =SUM(AI82:AI88) -> 0 | AJ81: =SUM(AJ82:AJ88) -> 0
B82: Khavda- PSS 11 | C82: AGE27BL | D82: =D81+1 -> 78 | E82: 3 | F82: Finance Cost - Group | G82: H-5XA1-11-01 | H82: H-63A1-11-01 | I82: H-6074-11-01 | K82: =AC82 -> 0 | L82: =AD82 -> 0 | M82: =AE82 -> 0 | N82: =M82+L82 -> 0 | O82: =K82-N82 -> 0 | Q82: =SUMIF(Budgeted_01jun!U:U,'SAP Working'!G82,Budgeted_01jun!R:R) -> 0 | R82: =SUMIF('Actual_30 jun'!I:I,'SAP Working'!G82,'Actual_30 jun'!K:K) -> 0 | S82: =SUMIF('Commited_30 Jun'!H:H,'SAP Working'!G82,'Commited_30 Jun'!I:I) -> 0 | T82: =S82+R82 -> 0 | U82: =Q82-T82 -> 0 | W82: =SUMIF(Budgeted_01jun!$U:$U,H82,Budgeted_01jun!$R:$R) -> 0 | X82: =SUMIF('Actual_30 jun'!$I:$I,'SAP Working'!H82,'Actual_30 jun'!$K:$K) -> 0 | Y82: =SUMIF('Commited_30 Jun'!$H:$H,'SAP Working'!H82,'Commited_30 Jun'!$I:$I) -> 0 | Z82: =Y82+X82 -> 0 | AA82: =W82-Z82 -> 0 | AC82: =SUMIF(Budgeted_01jun!$U:$U,'SAP Working'!I82,Budgeted_01jun!$R:$R) -> 0 | AD82: =SUMIF('Actual_30 jun'!$I:$I,'SAP Working'!I82,'Actual_30 jun'!$K:$K) -> 0 | AE82: =SUMIF('Commited_30 Jun'!$H:$H,'SAP Working'!I82,'Commited_30 Jun'!$I:$I) -> 0 | AF82: =AE82+AD82 -> 0 | AG82: =AC82-AF82 -> 0
B83: Khavda- PSS 11 | C83: AGE27BL | D83: =D82+1 -> 79 | E83: 3 | F83: Finance Cost - Outside | G83: H-5XA1-11-02 | H83: H-63A1-11-02 | I83: H-6074-11-02 | K83: =AC83 -> 0 | L83: =AD83 -> 0 | M83: =AE83 -> 0 | N83: =M83+L83 -> 0 | O83: =K83-N83 -> 0 | Q83: =SUMIF(Budgeted_01jun!U:U,'SAP Working'!G83,Budgeted_01jun!R:R) -> 20043390 | R83: =SUMIF('Actual_30 jun'!I:I,'SAP Working'!G83,'Actual_30 jun'!K:K) -> 4642530 | S83: =SUMIF('Commited_30 Jun'!H:H,'SAP Working'!G83,'Commited_30 Jun'!I:I) -> 0 | T83: =S83+R83 -> 4642530 | U83: =Q83-T83 -> 15400860 | W83: =SUMIF(Budgeted_01jun!$U:$U,H83,Budgeted_01jun!$R:$R) -> 0 | X83: =SUMIF('Actual_30 jun'!$I:$I,'SAP Working'!H83,'Actual_30 jun'!$K:$K) -> 0 | Y83: =SUMIF('Commited_30 Jun'!$H:$H,'SAP Working'!H83,'Commited_30 Jun'!$I:$I) -> 0 | Z83: =Y83+X83 -> 0 | AA83: =W83-Z83 -> 0 | AC83: =SUMIF(Budgeted_01jun!$U:$U,'SAP Working'!I83,Budgeted_01jun!$R:$R) -> 0 | AD83: =SUMIF('Actual_30 jun'!$I:$I,'SAP Working'!I83,'Actual_30 jun'!$K:$K) -> 0 | AE83: =SUMIF('Commited_30 Jun'!$H:$H,'SAP Working'!I83,'Commited_30 Jun'!$I:$I) -> 0 | AF83: =AE83+AD83 -> 0 | AG83: =AC83-AF83 -> 0
B84: Khavda- PSS 11 | C84: AGE27BL | D84: =D83+1 -> 80 | E84: 3 | F84: IDC - Group | G84: H-5XA1-11-03 | H84: H-63A1-11-03 | I84: H-6074-11-03 | K84: =AC84 -> 0 | L84: =AD84 -> 0 | M84: =AE84 -> 0 | N84: =M84+L84 -> 0 | O84: =K84-N84 -> 0 | Q84: =SUMIF(Budgeted_01jun!U:U,'SAP Working'!G84,Budgeted_01jun!R:R) -> 0 | R84: =SUMIF('Actual_30 jun'!I:I,'SAP Working'!G84,'Actual_30 jun'!K:K) -> 0 | S84: =SUMIF('Commited_30 Jun'!H:H,'SAP Working'!G84,'Commited_30 Jun'!I:I) -> 0 | T84: =S84+R84 -> 0 | U84: =Q84-T84 -> 0 | W84: =SUMIF(Budgeted_01jun!$U:$U,H84,Budgeted_01jun!$R:$R) -> 0 | X84: =SUMIF('Actual_30 jun'!$I:$I,'SAP Working'!H84,'Actual_30 jun'!$K:$K) -> 0 | Y84: =SUMIF('Commited_30 Jun'!$H:$H,'SAP Working'!H84,'Commited_30 Jun'!$I:$I) -> 0 | Z84: =Y84+X84 -> 0 | AA84: =W84-Z84 -> 0 | AC84: =SUMIF(Budgeted_01jun!$U:$U,'SAP Working'!I84,Budgeted_01jun!$R:$R) -> 0 | AD84: =SUMIF('Actual_30 jun'!$I:$I,'SAP Working'!I84,'Actual_30 jun'!$K:$K) -> 0 | AE84: =SUMIF('Commited_30 Jun'!$H:$H,'SAP Working'!I84,'Commited_30 Jun'!$I:$I) -> 0 | AF84: =AE84+AD84 -> 0 | AG84: =AC84-AF84 -> 0
B85: Khavda- PSS 11 | C85: AGE27BL | D85: =D84+1 -> 81 | E85: 3 | F85: IDC - Outside | G85: H-5XA1-11-04 | H85: H-63A1-11-04 | I85: H-6074-11-04 | K85: =AC85 -> 0 | L85: =AD85 -> 0 | M85: =AE85 -> 0 | N85: =M85+L85 -> 0 | O85: =K85-N85 -> 0 | Q85: =SUMIF(Budgeted_01jun!U:U,'SAP Working'!G85,Budgeted_01jun!R:R) -> 0 | R85: =SUMIF('Actual_30 jun'!I:I,'SAP Working'!G85,'Actual_30 jun'!K:K) -> 380460 | S85: =SUMIF('Commited_30 Jun'!H:H,'SAP Working'!G85,'Commited_30 Jun'!I:I) -> 0 | T85: =S85+R85 -> 380460 | U85: =Q85-T85 -> -380460 | W85: =SUMIF(Budgeted_01jun!$U:$U,H85,Budgeted_01jun!$R:$R) -> 0 | X85: =SUMIF('Actual_30 jun'!$I:$I,'SAP Working'!H85,'Actual_30 jun'!$K:$K) -> 0 | Y85: =SUMIF('Commited_30 Jun'!$H:$H,'SAP Working'!H85,'Commited_30 Jun'!$I:$I) -> 0 | Z85: =Y85+X85 -> 0 | AA85: =W85-Z85 -> 0 | AC85: =SUMIF(Budgeted_01jun!$U:$U,'SAP Working'!I85,Budgeted_01jun!$R:$R) -> 0 | AD85: =SUMIF('Actual_30 jun'!$I:$I,'SAP Working'!I85,'Actual_30 jun'!$K:$K) -> 0 | AE85: =SUMIF('Commited_30 Jun'!$H:$H,'SAP Working'!I85,'Commited_30 Jun'!$I:$I) -> 0 | AF85: =AE85+AD85 -> 0 | AG85: =AC85-AF85 -> 0
B86: Khavda- PSS 11 | C86: AGE27BL | D86: =D85+1 -> 82 | E86: 3 | F86: Income from Mutual Fund | G86: H-5XA1-11-05 | H86: H-63A1-11-05 | I86: H-6074-11-05 | K86: =AC86 -> 0 | L86: =AD86 -> 0 | M86: =AE86 -> 0 | N86: =M86+L86 -> 0 | O86: =K86-N86 -> 0 | Q86: =SUMIF(Budgeted_01jun!U:U,'SAP Working'!G86,Budgeted_01jun!R:R) -> 0 | R86: =SUMIF('Actual_30 jun'!I:I,'SAP Working'!G86,'Actual_30 jun'!K:K) -> 0 | S86: =SUMIF('Commited_30 Jun'!H:H,'SAP Working'!G86,'Commited_30 Jun'!I:I) -> 0 | T86: =S86+R86 -> 0 | U86: =Q86-T86 -> 0 | W86: =SUMIF(Budgeted_01jun!$U:$U,H86,Budgeted_01jun!$R:$R) -> 0 | X86: =SUMIF('Actual_30 jun'!$I:$I,'SAP Working'!H86,'Actual_30 jun'!$K:$K) -> 0 | Y86: =SUMIF('Commited_30 Jun'!$H:$H,'SAP Working'!H86,'Commited_30 Jun'!$I:$I) -> 0 | Z86: =Y86+X86 -> 0 | AA86: =W86-Z86 -> 0 | AC86: =SUMIF(Budgeted_01jun!$U:$U,'SAP Working'!I86,Budgeted_01jun!$R:$R) -> 0 | AD86: =SUMIF('Actual_30 jun'!$I:$I,'SAP Working'!I86,'Actual_30 jun'!$K:$K) -> 0 | AE86: =SUMIF('Commited_30 Jun'!$H:$H,'SAP Working'!I86,'Commited_30 Jun'!$I:$I) -> 0 | AF86: =AE86+AD86 -> 0 | AG86: =AC86-AF86 -> 0
B87: Khavda- PSS 11 | C87: AGE27BL | D87: =D86+1 -> 83 | E87: 3 | F87: Pre-Payment | G87: H-5XA1-11-06 | H87: H-63A1-11-06 | I87: H-6074-11-06 | K87: =AC87 -> 0 | L87: =AD87 -> 0 | M87: =AE87 -> 0 | N87: =M87+L87 -> 0 | O87: =K87-N87 -> 0 | Q87: =SUMIF(Budgeted_01jun!U:U,'SAP Working'!G87,Budgeted_01jun!R:R) -> 0 | R87: =SUMIF('Actual_30 jun'!I:I,'SAP Working'!G87,'Actual_30 jun'!K:K) -> 0 | S87: =SUMIF('Commited_30 Jun'!H:H,'SAP Working'!G87,'Commited_30 Jun'!I:I) -> 0 | T87: =S87+R87 -> 0 | U87: =Q87-T87 -> 0 | W87: =SUMIF(Budgeted_01jun!$U:$U,H87,Budgeted_01jun!$R:$R) -> 0 | X87: =SUMIF('Actual_30 jun'!$I:$I,'SAP Working'!H87,'Actual_30 jun'!$K:$K) -> 0 | Y87: =SUMIF('Commited_30 Jun'!$H:$H,'SAP Working'!H87,'Commited_30 Jun'!$I:$I) -> 0 | Z87: =Y87+X87 -> 0 | AA87: =W87-Z87 -> 0 | AC87: =SUMIF(Budgeted_01jun!$U:$U,'SAP Working'!I87,Budgeted_01jun!$R:$R) -> 0 | AD87: =SUMIF('Actual_30 jun'!$I:$I,'SAP Working'!I87,'Actual_30 jun'!$K:$K) -> 0 | AE87: =SUMIF('Commited_30 Jun'!$H:$H,'SAP Working'!I87,'Commited_30 Jun'!$I:$I) -> 0 | AF87: =AE87+AD87 -> 0 | AG87: =AC87-AF87 -> 0
B88: Khavda- PSS 11 | C88: AGE27BL | D88: =D87+1 -> 84 | E88: 3 | F88: Interest Income - Outside | G88: H-5XA1-11-07 | H88: H-63A1-11-07 | I88: H-6074-11-07 | K88: =AC88 -> 0 | L88: =AD88 -> 0 | M88: =AE88 -> 0 | N88: =M88+L88 -> 0 | O88: =K88-N88 -> 0 | Q88: =SUMIF(Budgeted_01jun!U:U,'SAP Working'!G88,Budgeted_01jun!R:R) -> 0 | R88: =SUMIF('Actual_30 jun'!I:I,'SAP Working'!G88,'Actual_30 jun'!K:K) -> 0 | S88: =SUMIF('Commited_30 Jun'!H:H,'SAP Working'!G88,'Commited_30 Jun'!I:I) -> 0 | T88: =S88+R88 -> 0 | U88: =Q88-T88 -> 0 | W88: =SUMIF(Budgeted_01jun!$U:$U,H88,Budgeted_01jun!$R:$R) -> 0 | X88: =SUMIF('Actual_30 jun'!$I:$I,'SAP Working'!H88,'Actual_30 jun'!$K:$K) -> 0 | Y88: =SUMIF('Commited_30 Jun'!$H:$H,'SAP Working'!H88,'Commited_30 Jun'!$I:$I) -> 0 | Z88: =Y88+X88 -> 0 | AA88: =W88-Z88 -> 0 | AC88: =SUMIF(Budgeted_01jun!$U:$U,'SAP Working'!I88,Budgeted_01jun!$R:$R) -> 0 | AD88: =SUMIF('Actual_30 jun'!$I:$I,'SAP Working'!I88,'Actual_30 jun'!$K:$K) -> 0 | AE88: =SUMIF('Commited_30 Jun'!$H:$H,'SAP Working'!I88,'Commited_30 Jun'!$I:$I) -> 0 | AF88: =AE88+AD88 -> 0 | AG88: =AC88-AF88 -> 0
A89: 14 | B89: Khavda- PSS 11 | C89: AGE27BL | D89: =D88+1 -> 85 | E89: 2 | F89: PMC Fee | G89: H-5XA1-12 | H89: H-63A1-12 | I89: H-6074-12 | K89: =AC89 -> 2991525424 | L89: =AD89 -> 1297950 | M89: =AE89 -> 4.1142851e+09 | N89: =M89+L89 -> 4.1155831e+09 | O89: =K89-N89 -> -1.1240576e+09 | Q89: =SUMIF(Budgeted_01jun!U:U,'SAP Working'!G89,Budgeted_01jun!R:R) -> 0 | R89: =SUMIF('Actual_30 jun'!I:I,'SAP Working'!G89,'Actual_30 jun'!K:K) -> 0 | S89: =SUMIF('Commited_30 Jun'!H:H,'SAP Working'!G89,'Commited_30 Jun'!I:I) -> 0 | T89: =S89+R89 -> 0 | U89: =Q89-T89 -> 0 | W89: =SUMIF(Budgeted_01jun!$U:$U,H89,Budgeted_01jun!$R:$R) -> 0 | X89: =SUMIF('Actual_30 jun'!$I:$I,'SAP Working'!H89,'Actual_30 jun'!$K:$K) -> 0 | Y89: =SUMIF('Commited_30 Jun'!$H:$H,'SAP Working'!H89,'Commited_30 Jun'!$I:$I) -> 0 | Z89: =Y89+X89 -> 0 | AA89: =W89-Z89 -> 0 | AC89: =SUMIF(Budgeted_01jun!$U:$U,'SAP Working'!I89,Budgeted_01jun!$R:$R) -> 2991525424 | AD89: =SUMIF('Actual_30 jun'!$I:$I,'SAP Working'!I89,'Actual_30 jun'!$K:$K) -> 1297950 | AE89: =SUMIF('Commited_30 Jun'!$H:$H,'SAP Working'!I89,'Commited_30 Jun'!$I:$I) -> 4.1142851e+09 | AF89: =AE89+AD89 -> 4.1155831e+09 | AG89: =AC89-AF89 -> -1.1240576e+09
A90: 8 | B90: Khavda- PSS 11 | C90: AGE27BL | D90: =D89+1 -> 86 | E90: 2 | F90: O&M Spares | G90: H-5XA1-13 | H90: H-63A1-13 | I90: H-6074-13 | K90: =Q90 -> 19900000 | L90: =R90 -> 2307750 | M90: =S90 -> 65247119 | N90: =M90+L90 -> 67554869 | O90: =K90-N90 -> -47654869 | Q90: =SUMIF(Budgeted_01jun!U:U,'SAP Working'!G90,Budgeted_01jun!R:R) -> 19900000 | R90: =SUMIF('Actual_30 jun'!I:I,'SAP Working'!G90,'Actual_30 jun'!K:K) -> 2307750 | S90: =SUMIF('Commited_30 Jun'!H:H,'SAP Working'!G90,'Commited_30 Jun'!I:I) -> 65247119 | T90: =S90+R90 -> 67554869 | U90: =Q90-T90 -> -47654869 | W90: =SUMIF(Budgeted_01jun!$U:$U,H90,Budgeted_01jun!$R:$R) -> 0 | X90: =SUMIF('Actual_30 jun'!$I:$I,'SAP Working'!H90,'Actual_30 jun'!$K:$K) -> 0 | Y90: =SUMIF('Commited_30 Jun'!$H:$H,'SAP Working'!H90,'Commited_30 Jun'!$I:$I) -> 0 | Z90: =Y90+X90 -> 0 | AA90: =W90-Z90 -> 0 | AC90: =SUMIF(Budgeted_01jun!$U:$U,'SAP Working'!I90,Budgeted_01jun!$R:$R) -> 0 | AD90: =SUMIF('Actual_30 jun'!$I:$I,'SAP Working'!I90,'Actual_30 jun'!$K:$K) -> 0 | AE90: =SUMIF('Commited_30 Jun'!$H:$H,'SAP Working'!I90,'Commited_30 Jun'!$I:$I) -> 0 | AF90: =AE90+AD90 -> 0 | AG90: =AC90-AF90 -> 0
A91: 15 | B91: Khavda- PSS 11 | C91: AGE27BL | D91: =D90+1 -> 87 | E91: 2 | F91: Contingency | G91: H-5XA1-14 | H91: H-63A1-14 | I91: H-6074-14 | K91: =SUM(Q91,W91,AC91) -> 0 | L91: =SUM(R91,X91,AD91) -> 0 | M91: =SUM(S91,Y91,AE91) -> 0 | N91: =M91+L91 -> 0 | O91: =K91-N91 -> 0 | Q91: =SUMIF(Budgeted_01jun!U:U,'SAP Working'!G91,Budgeted_01jun!R:R) -> 0 | R91: =SUMIF('Actual_30 jun'!I:I,'SAP Working'!G91,'Actual_30 jun'!K:K) -> 0 | S91: =SUMIF('Commited_30 Jun'!H:H,'SAP Working'!G91,'Commited_30 Jun'!I:I) -> 0 | T91: =S91+R91 -> 0 | U91: =Q91-T91 -> 0 | W91: =SUMIF(Budgeted_01jun!$U:$U,H91,Budgeted_01jun!$R:$R) -> 0 | X91: =SUMIF('Actual_30 jun'!$I:$I,'SAP Working'!H91,'Actual_30 jun'!$K:$K) -> 0 | Y91: =SUMIF('Commited_30 Jun'!$H:$H,'SAP Working'!H91,'Commited_30 Jun'!$I:$I) -> 0 | Z91: =Y91+X91 -> 0 | AA91: =W91-Z91 -> 0 | AC91: =SUMIF(Budgeted_01jun!$U:$U,'SAP Working'!I91,Budgeted_01jun!$R:$R) -> 0 | AD91: =SUMIF('Actual_30 jun'!$I:$I,'SAP Working'!I91,'Actual_30 jun'!$K:$K) -> 0 | AE91: =SUMIF('Commited_30 Jun'!$H:$H,'SAP Working'!I91,'Commited_30 Jun'!$I:$I) -> 0 | AF91: =AE91+AD91 -> 0 | AG91: =AC91-AF91 -> 0
R92: =SUMIF('Actual_30 jun'!I:I,'SAP Working'!G92,'Actual_30 jun'!K:K) -> 0 | S92: =SUMIF('Commited_30 Jun'!H:H,'SAP Working'!G92,'Commited_30 Jun'!I:I) -> 0 | X92: =SUMIF('Actual_30 jun'!$I:$I,'SAP Working'!H92,'Actual_30 jun'!$K:$K) -> 0 | Y92: =SUMIF('Commited_30 Jun'!$H:$H,'SAP Working'!H92,'Commited_30 Jun'!$I:$I) -> 0 | AD92: =SUMIF('Actual_30 jun'!$I:$I,'SAP Working'!I92,'Actual_30 jun'!$K:$K) -> 0 | AE92: =SUMIF('Commited_30 Jun'!$H:$H,'SAP Working'!I92,'Commited_30 Jun'!$I:$I) -> 0
R93: =SUMIF('Actual_30 jun'!I:I,'SAP Working'!G93,'Actual_30 jun'!K:K) -> 0 | S93: =SUMIF('Commited_30 Jun'!H:H,'SAP Working'!G93,'Commited_30 Jun'!I:I) -> 0 | X93: =SUMIF('Actual_30 jun'!$I:$I,'SAP Working'!H93,'Actual_30 jun'!$K:$K) -> 0 | Y93: =SUMIF('Commited_30 Jun'!$H:$H,'SAP Working'!H93,'Commited_30 Jun'!$I:$I) -> 0 | AD93: =SUMIF('Actual_30 jun'!$I:$I,'SAP Working'!I93,'Actual_30 jun'!$K:$K) -> 0 | AE93: =SUMIF('Commited_30 Jun'!$H:$H,'SAP Working'!I93,'Commited_30 Jun'!$I:$I) -> 0

Sheet PSS 09_EAC_WBS Mapped
A1: PSS-11 (2 Hrs System) | M1: =TODAY() -> 46254
A3: Sr No | B3: Description | C3: WBS w.r.t Line Items | F3: Approved Capex (INR Cr) - Non editable column | G3: Incurred - Non editable column | H3: Commited - Non editable column | I3: Balance To completion - editable column | J3: EAC - Non editable column | K3: Variance WRT Approved NFA - Non editable column | L3: EAC Remarks -editable column
C4: AGEL | D4: AGE6L | E4: SPV
A5: 1 | B5: Battery Containers (2 Hour system) | C5: H-5XWG-01-01 | F5: 1728.4085 | G5: =SUMIF('SAP Working'!$A$4:$A$91,A5,'SAP Working'!$L$4:$L$91)/10^7*1.0825 -> 2.6212521 | H5: =SUMIF('SAP Working'!$A$4:$A$91,A5,'SAP Working'!$M$4:$M$91)/10^7*1.0825 -> 138.66727 | I5: 0 | J5: =SUM(G5:I6) -> 141.28852 | K5: =F5-J5 -> 1587.12
C6: H-5XWG-01-02
A7: 2 | B7: PCS (2 Hour system) | C7: H-5XWG-02-01 | F7: =124.335686771073*5 -> 621.67843 | G7: =SUMIF('SAP Working'!$A$4:$A$91,A7,'SAP Working'!$L$4:$L$91)/10^7*1.0825 -> 0.39931585 | H7: =SUMIF('SAP Working'!$A$4:$A$91,A7,'SAP Working'!$M$4:$M$91)/10^7*1.0825+5.3358516898775 -> 364.38662 | I7: 0 | J7: =SUM(G7:I8) -> 364.78593 | K7: =F7-J7 -> 256.8925
C8: H-5XWG-02-02
A9: 3 | B9: EMS (2 Hour system) | C9: H-5XWG-03-01 | F9: 22.157 | G9: =SUMIF('SAP Working'!$A$4:$A$91,A9,'SAP Working'!$L$4:$L$91)/10^7 -> 0.292179 | H9: =SUMIF('SAP Working'!$A$4:$A$91,A9,'SAP Working'!$M$4:$M$91)/10^7 -> 19.780614 | J9: =SUM(G9:I10) -> 20.072793 | K9: =F9-J9 -> 2.084207
C10: H-5XWG-03-02
A11: 3.1 | B11: Battery + PCS + EMS | F11: =F9+F7+F5 -> 2372.2439 | G11: =G9+G7+G5 -> 3.3127469 | H11: =H9+H7+H5 -> 522.8345 | I11: =I9+I7+I5 -> 0 | J11: =J9+J7+J5 -> 526.14725 | K11: =F11-J11 -> 1846.0967
A12: 4 | B12: Transformer & NIFPS | C12: H-5XWG-04 | D12: H-63WG-04 | F12: 97.003574 | G12: =SUMIF('SAP Working'!$A$4:$A$91,A12,'SAP Working'!$L$4:$L$91)/10^7 -> 16.33377 | H12: =SUMIF('SAP Working'!$A$4:$A$91,A12,'SAP Working'!$M$4:$M$91)/10^7+5.4 -> 145.97038 | J12: =SUM(G12:I12) -> 162.30415 | K12: =F12-J12 -> -65.300571
A13: 5 | B13: BOS Elec | F13: =SUM(F14:F22) -> 139.65604 | G13: =SUM(G14:G22) -> 30.478875 | H13: =SUM(H14:H22) -> 2412.5117 | J13: =SUM(J14:J22) -> 2442.9905 | K13: =F13-J13 -> -2303.3345
A14: 5.1 | B14: HT Panel | C14: H-5XWG-06-01 | D14: H-63WG-06-01 | F14: 14.697 | G14: =SUMIF('SAP Working'!$A$4:$A$91,A14,'SAP Working'!$L$4:$L$91)/10^7 -> 8.11257 | H14: =SUMIF('SAP Working'!$A$4:$A$91,A14,'SAP Working'!$M$4:$M$91)/10^7 -> 99.5638 | J14: =SUM(G14:I14) -> 107.67637 | K14: =F14-J14 -> -92.97937
A15: 5.2 | B15: DC LT Cable | C15: H-5XWG-06-02 | D15: H-63WG-06-02 | F15: 57.115152 | G15: =SUMIF('SAP Working'!$A$4:$A$91,A15,'SAP Working'!$L$4:$L$91)/10^7 -> 6.403968 | H15: =SUMIF('SAP Working'!$A$4:$A$91,A15,'SAP Working'!$M$4:$M$91)/10^7+0.48 -> 292.5641 | J15: =SUM(G15:I16) -> 298.96807 | K15: =F15-J15 -> -241.85291
A17: 5.3 | B17: HT Cable | C17: H-5XWG-06-03 | D17: H-63WG-06-03 | F17: 18.882638 | G17: =SUMIF('SAP Working'!$A$4:$A$91,A17,'SAP Working'!$L$4:$L$91)/10^7 -> 5.344035 | H17: =SUMIF('SAP Working'!$A$4:$A$91,A17,'SAP Working'!$M$4:$M$91)/10^7 -> 64.503797 | J17: =SUM(G17:I18) -> 69.847832 | K17: =F17-J17 -> -50.965194
A19: 5.4 | B19: Scada Cable & FO | C19: H-5XWG-06-05 | D19: H-63WG-06-05 | F19: 2.492267 | G19: =SUMIF('SAP Working'!$A$4:$A$91,A19,'SAP Working'!$L$4:$L$91)/10^7 -> 2.495889 | H19: =SUMIF('SAP Working'!$A$4:$A$91,A19,'SAP Working'!$M$4:$M$91)/10^7 -> 221.38595 | J19: =SUM(G19:I19) -> 223.88184 | K19: =F19-J19 -> -221.38957
